Workbook

Sheet Cover
A1: NIFTY 50 Equity Derivatives – Futures Analysis
A2: Prepared by: Tushar Varkhede (MBA)
A3: =TEXT(Summary!B2,"dd-mmm-yyyy")&" to "&TEXT(Summary!B3,"dd-mmm-yyyy")&" | NSE NIFTY Index Futures" -> 01-Jan-2025 to 31-Dec-2025 | NSE NIFTY Index Futures
A5: Field | B5: Value
A6: Actual data period | B6: =TEXT(Summary!B2,"dd-mmm-yyyy")&" to "&TEXT(Summary!B3,"dd-mmm-yyyy") -> 01-Jan-2025 to 31-Dec-2025
A7: Source | B7: NSE NIFTY Index Futures CSV supplied by user
A8: Objective | B8: Describe how NIFTY index futures traded in 2025 – liquidity, basis (futures vs index), open interest and price–OI behaviour – and test whether simple price–OI labels carry any next-day information.
A9: Key questions | B9: 1) Where does trading concentrate across contracts? 2) How does basis behave across tenor, time to expiry and month? 3) How does open interest roll between contracts? 4) Do price–OI labels predict the next day's move?
A10: Scope | B10: Futures price, basis, contracts, open interest and price–OI interpretation
A11: Limitation | B11: Options data is not included; this is a futures-only study. No interest-rate or dividend data, so carry is measured but not benchmarked.
A12: Method note | B12: Exact duplicate rows removed; repeated headers and blank rows excluded. Derived columns (basis, returns, OI interpretation) and all summary tables are live formulas on Cleaned_Futures_Data.
A13: Definitions | B13: Basis = futures close − underlying value (index points). Basis % = basis ÷ underlying. Annualised basis = Basis % × 365 ÷ days to expiry. Near month = contract with the earliest expiry on that date (Series Rank 1).
A14: OI interpretation rule | B14: Compared with the previous row of the same contract: price up & OI up = Long buildup; price down & OI up = Short buildup; price up & OI down = Short covering; price down & OI down = Long unwinding.
A15: Sheet guide | B15: Executive_Summary – overview and headline results | Scope_and_Approach – what was studied and how | Findings – detailed findings and data notes | Dashboard – charts and KPIs | Cleaned_Futures_Data – data plus derived/helper columns (blue headers V–AB are analysis helpers) | Summary, Monthly_Summary, Expiry_Summary, OI_Interpretation_Summary – tables | Basis_Analysis – basis by tenor, expiry proximity and OI rollover (holds the editable inputs) | NearMonth_Daily – daily near-month series | Conclusion – answers, limitations and next steps
A16: Editable inputs | B16: Basis_Analysis: expiry-week cutoff (B3), days-to-expiry bucket bounds and series rank bounds (blue text).

Sheet Executive_Summary
A1: Executive Summary
A2: NIFTY 50 Equity Derivatives – Futures Analysis 2025 | Prepared by Tushar Varkhede (MBA)
A4: Executive summary
A5: Overview | B5: ="This project analyses NIFTY 50 index futures from "&TEXT(Summary!B2,"dd-mmm-yyyy")&" to "&TEXT(Summary!B3,"dd-mmm-yyyy")&" using the NSE NIFTY futures file supplied for the project: "&TEXT(Summary!B4,"#,##0")&" contract-day records across "&Summary!B5&" trading dates and "&Summary!B6&" expiries, with "&TEXT(Summary!B11/1000000,"0.0")&" mn contracts traded (turnover about ₹"&TEXT(Summary!B12/10000000,"0.0")&" lakh crore). It asks where trading concentrates, how the futures-to-index basis behaves, how open interest rolls between contracts, and whether simple price–open interest labels say anything about the next day." -> This project analyses NIFTY 50 index futures from 01-Jan-2025 to 31-Dec-2025 using the NSE NIFTY futures file supplied for the project: 755 contract-day records across 249 trading dates and 16 expiries, with 29.9 mn contracts traded (turnover about ₹48.3 lakh crore). It asks where trading concentrates, how the futures-to-index basis behaves, how open interest rolls between contracts, and whether simple price–open interest labels say anything about the next day.
A7: Headline results
A8: 1. Liquidity | B8: ="The near-month contract accounts for "&TEXT(Basis_Analysis!F18,"0.0%")&" of all contracts traded ("&TEXT(Basis_Analysis!F19,"0.0%")&" next month, "&TEXT(Basis_Analysis!F20,"0.0%")&" far month), so the analysis focuses on the near-month series." -> The near-month contract accounts for 79.3% of all contracts traded (18.3% next month, 2.4% far month), so the analysis focuses on the near-month series.
A9: 2. Basis | B9: ="Near-month futures traded at an average premium of about "&TEXT(Basis_Analysis!H18,"0")&" points ("&TEXT(Basis_Analysis!I18,"0.00%")&") to the index. The premium is larger for longer tenors ("&TEXT(Basis_Analysis!H19,"0")&" and "&TEXT(Basis_Analysis!H20,"0")&" points for next and far month) and narrows to about "&TEXT(Basis_Analysis!E8,"0.0")&" points on expiry day. Annualised, the near-month premium is about "&TEXT(Basis_Analysis!B4,"0.0%")&", the pattern expected from cost-of-carry pricing." -> Near-month futures traded at an average premium of about 68 points (0.28%) to the index. The premium is larger for longer tenors (202 and 340 points for next and far month) and narrows to about -3.5 points on expiry day. Annualised, the near-month premium is about 6.9%, the pattern expected from cost-of-carry pricing.
A10: 3. Open-interest rollover | B10: ="Open interest moves from the near to the next month mainly in the final week: the near-month share of near+next open interest falls from "&TEXT(Basis_Analysis!J13,"0%")&" at 21+ days to expiry to "&TEXT(Basis_Analysis!J9,"0%")&" at 1–5 days and "&TEXT(Basis_Analysis!J8,"0%")&" on expiry day." -> Open interest moves from the near to the next month mainly in the final week: the near-month share of near+next open interest falls from 91% at 21+ days to expiry to 52% at 1–5 days and 23% on expiry day.
A11: 4. Price–OI labels | B11: ="Buildup labels (long or short) made up "&TEXT(OI_Interpretation_Summary!C2+OI_Interpretation_Summary!C3,"0%")&" of records. Outside expiry week, the next day's close was higher after only "&TEXT(MIN(OI_Interpretation_Summary!E13:E16),"0%")&" to "&TEXT(MAX(OI_Interpretation_Summary!E13:E16),"0%")&" of labelled days, so the labels did not give a reliable next-day signal. In expiry week "&TEXT(OI_Interpretation_Summary!B22,"0%")&" of classified near-month days showed falling open interest, which is contract expiry rather than a change in view." -> Buildup labels (long or short) made up 72% of records. Outside expiry week, the next day's close was higher after only 40% to 51% of labelled days, so the labels did not give a reliable next-day signal. In expiry week 100% of classified near-month days showed falling open interest, which is contract expiry rather than a change in view.
A12: Bottom line | B12: In 2025 NIFTY futures behaved as cost-of-carry pricing and an expiry-driven roll cycle would suggest. The price–OI labels are useful for describing what happened on a given day but should not be treated as a trading signal on this evidence.

Sheet Scope_and_Approach
A1: Scope and Approach
A2: NIFTY 50 Equity Derivatives – Futures Analysis 2025 | Prepared by Tushar Varkhede (MBA)
A4: Scope
A5: In scope | B5: ="NIFTY 50 index futures, all listed expiries, daily data from "&TEXT(Summary!B2,"dd-mmm-yyyy")&" to "&TEXT(Summary!B3,"dd-mmm-yyyy")&": prices, contracts traded, turnover, open interest and the underlying index value." -> NIFTY 50 index futures, all listed expiries, daily data from 01-Jan-2025 to 31-Dec-2025: prices, contracts traded, turnover, open interest and the underlying index value.
A6: Out of scope | B6: Options, other indices and stock futures, intraday data, interest-rate and dividend data, and any trading-strategy test with costs.
A7: Data source | B7: NSE NIFTY Index Futures CSV supplied by the user. Exact duplicate rows were removed and repeated headers and blank rows excluded. The data was not re-verified against NSE directly.
A8: Data gaps | B8: ="Of the "&TEXT(Summary!B4,"#,##0")&" records, "&Findings!D19&" are no-trade rows, "&Findings!D20&" have prices but no index value (basis left blank) and "&Findings!D21&" cannot be classified for price–OI direction (the first observation of each expiry or a no-trade row without prior price/OI inputs). They are kept in the data but excluded from averages." -> Of the 755 records, 8 are no-trade rows, 15 have prices but no index value (basis left blank) and 24 cannot be classified for price–OI direction (the first observation of each expiry or a no-trade row without prior price/OI inputs). They are kept in the data but excluded from averages.
A10: Approach
A11: Step 1 – Prepare | B11: Add derived measures as live formulas on the cleaned data: basis (futures close minus index), basis %, days to expiry, daily price and open-interest changes, and the price–OI label.
A12: Step 2 – Near month | B12: Rank the listed expiries on each date. Rank 1 is the near-month contract and is used for like-for-like comparisons, because averaging across tenors mixes different basis levels.
A13: Step 3 – Basis | B13: Measure basis by contract series, by days to expiry and by month, and annualise it to get the carry rate implied by futures prices.
A14: Step 4 – Rollover | B14: Compare near- and next-month open interest as expiry approaches to see when positions roll.
A15: Step 5 – OI interpretation | B15: Label each day long buildup, short buildup, short covering or long unwinding from the direction of price and open interest against the previous day for the same contract.
A16: Step 6 – Signal test | B16: ="Outside expiry week (last "&Basis_Analysis!B3&" days to expiry excluded, because open interest falls mechanically then), test whether each label is followed by a higher close the next day." -> Outside expiry week (last 5 days to expiry excluded, because open interest falls mechanically then), test whether each label is followed by a higher close the next day.
A17: Step 7 – Present | B17: Summarise in the Findings sheet, dashboard charts and summary tables. Every figure is formula-linked to the cleaned data, so it updates if the data or inputs change.

Sheet Findings
A1: Key Findings
A2: Figures are formula-linked to the analysis sheets and update if the data or inputs change.
A4: # | B4: Theme | C4: Finding | D4: Evidence
A5: 1 | B5: Liquidity concentration | C5: ="The near-month contract carries "&TEXT(Basis_Analysis!F18,"0.0%")&" of all contracts traded ("&TEXT(Basis_Analysis!F19,"0.0%")&" next month, "&TEXT(Basis_Analysis!F20,"0.0%")&" far month). Price, basis and OI behaviour is therefore best read on the near-month series, which is what the near-month (NM) columns and charts use." -> The near-month contract carries 79.3% of all contracts traded (18.3% next month, 2.4% far month). Price, basis and OI behaviour is therefore best read on the near-month series, which is what the near-month (NM) columns and charts use. | D5: Basis_Analysis §2
A6: 2 | B6: Basis and tenor | C6: ="Basis widens with tenor: about "&TEXT(Basis_Analysis!H18,"0")&" pts (near), "&TEXT(Basis_Analysis!H19,"0")&" pts (next) and "&TEXT(Basis_Analysis!H20,"0")&" pts (far), or "&TEXT(Basis_Analysis!I18,"0.00%")&", "&TEXT(Basis_Analysis!I19,"0.00%")&" and "&TEXT(Basis_Analysis!I20,"0.00%")&" of the index. This is the pattern expected from cost-of-carry pricing. The all-series average of "&TEXT(Summary!B8,"0")&" pts on the Summary sheet blends these tenors and overstates the typical near-month basis." -> Basis widens with tenor: about 68 pts (near), 202 pts (next) and 340 pts (far), or 0.28%, 0.82% and 1.38% of the index. This is the pattern expected from cost-of-carry pricing. The all-series average of 203 pts on the Summary sheet blends these tenors and overstates the typical near-month basis. | D6: Basis_Analysis §2; Summary
A7: 3 | B7: Basis decay into expiry | C7: ="Near-month basis averages "&TEXT(Basis_Analysis!E13,"0")&" pts with 21+ days to expiry, "&TEXT(Basis_Analysis!E11,"0")&" pts at 11–15 days, "&TEXT(Basis_Analysis!E9,"0")&" pts in the last 1–5 days and "&TEXT(Basis_Analysis!E8,"0.0")&" pts on expiry day: the futures price converges on the index as expiry approaches." -> Near-month basis averages 109 pts with 21+ days to expiry, 70 pts at 11–15 days, 27 pts in the last 1–5 days and -3.5 pts on expiry day: the futures price converges on the index as expiry approaches. | D7: Basis_Analysis §1; Dashboard
A8: 4 | B8: Implied carry | C8: ="For near-month contracts outside expiry week, the annualised basis averages "&TEXT(Basis_Analysis!B4,"0.0%")&". This is the carry rate implied by futures prices. It has not been compared with a money-market rate or dividend yield because no such data was supplied, so mispricing cannot be concluded from this workbook." -> For near-month contracts outside expiry week, the annualised basis averages 6.9%. This is the carry rate implied by futures prices. It has not been compared with a money-market rate or dividend yield because no such data was supplied, so mispricing cannot be concluded from this workbook. | D8: Basis_Analysis B4
A9: 5 | B9: Open-interest rollover | C9: ="Open interest rolls from near to next month mostly in the final week. Near-month share of (near + next) OI is "&TEXT(Basis_Analysis!J13,"0%")&" at 21+ days, "&TEXT(Basis_Analysis!J10,"0%")&" at 6–10 days, "&TEXT(Basis_Analysis!J9,"0%")&" at 1–5 days and "&TEXT(Basis_Analysis!J8,"0%")&" on expiry day." -> Open interest rolls from near to next month mostly in the final week. Near-month share of (near + next) OI is 91% at 21+ days, 78% at 6–10 days, 52% at 1–5 days and 23% on expiry day. | D9: Basis_Analysis §1; Dashboard
A10: 6 | B10: Basis over the year | C10: ="Average near-month basis was about "&TEXT(AVERAGE(Monthly_Summary!I2:I9),"0")&" pts in Jan–Aug versus "&TEXT(AVERAGE(Monthly_Summary!I10:I13),"0")&" pts in Sep–Dec. The data cannot say why (rates, dividends, positioning and the change in expiry dates visible in the data from Sep-2025 are all candidates); it would need extra inputs to test." -> Average near-month basis was about 58 pts in Jan–Aug versus 88 pts in Sep–Dec. The data cannot say why (rates, dividends, positioning and the change in expiry dates visible in the data from Sep-2025 are all candidates); it would need extra inputs to test. | D10: Monthly_Summary col I; Dashboard
A11: 7 | B11: Volume trend | C11: ="January was the busiest month with "&TEXT(Monthly_Summary!C2/1000000,"0.0")&" mn contracts, about "&TEXT(Monthly_Summary!C2/AVERAGE(Monthly_Summary!C3:C13),"0.0")&"x the Feb–Dec monthly average of "&TEXT(AVERAGE(Monthly_Summary!C3:C13)/1000000,"0.0")&" mn. The busiest single near-month day was "&TEXT(INDEX(NearMonth_Daily!A2:A250,MATCH(MAX(NearMonth_Daily!G2:G250),NearMonth_Daily!G2:G250,0)),"dd-mmm-yyyy")&" ("&TEXT(MAX(NearMonth_Daily!G2:G250),"#,##0")&" contracts)." -> January was the busiest month with 6.0 mn contracts, about 2.8x the Feb–Dec monthly average of 2.2 mn. The busiest single near-month day was 21-Jan-2025 (388,434 contracts). | D11: Monthly_Summary; NearMonth_Daily
A12: 8 | B12: Peak open interest | C12: ="Near-month open interest peaked at "&TEXT(MAX(NearMonth_Daily!H2:H250)/1000000,"0.0")&" mn contracts on "&TEXT(INDEX(NearMonth_Daily!A2:A250,MATCH(MAX(NearMonth_Daily!H2:H250),NearMonth_Daily!H2:H250,0)),"dd-mmm-yyyy")&"." -> Near-month open interest peaked at 18.5 mn contracts on 07-Nov-2025. | D12: NearMonth_Daily; Dashboard
A13: 9 | B13: OI classification mix | C13: ="Short buildup ("&TEXT(OI_Interpretation_Summary!C2,"0%")&") and long buildup ("&TEXT(OI_Interpretation_Summary!C3,"0%")&") were the most common labels, together "&TEXT(OI_Interpretation_Summary!C2+OI_Interpretation_Summary!C3,"0%")&" of records; short covering and long unwinding made up "&TEXT(OI_Interpretation_Summary!C4+OI_Interpretation_Summary!C5,"0%")&". OI rose on most days, consistent with positions building up over each contract's life before expiry." -> Short buildup (41%) and long buildup (32%) were the most common labels, together 72% of records; short covering and long unwinding made up 24%. OI rose on most days, consistent with positions building up over each contract's life before expiry. | D13: OI_Interpretation_Summary
A14: 10 | B14: Expiry-week distortion | C14: ="In expiry week, "&TEXT(OI_Interpretation_Summary!B22,"0%")&" of classified near-month days are labelled long unwinding or short covering. That is mainly contracts expiring and OI rolling to the next month, not traders changing view, so expiry-week labels should not be read as sentiment." -> In expiry week, 100% of classified near-month days are labelled long unwinding or short covering. That is mainly contracts expiring and OI rolling to the next month, not traders changing view, so expiry-week labels should not be read as sentiment. | D14: OI_Interpretation_Summary
A15: 11 | B15: Do the labels predict? | C15: ="Outside expiry week, the close was higher the next day after only "&TEXT(MIN(OI_Interpretation_Summary!E13:E16),"0%")&" to "&TEXT(MAX(OI_Interpretation_Summary!E13:E16),"0%")&" of labelled days across the four labels (all labels: "&TEXT(OI_Interpretation_Summary!E17,"0%")&"; "&TEXT(MIN(OI_Interpretation_Summary!B13:B16),"0")&" to "&TEXT(MAX(OI_Interpretation_Summary!B13:B16),"0")&" observations each). The labels describe the day; in this sample they do not give a reliable next-day signal." -> Outside expiry week, the close was higher the next day after only 40% to 51% of labelled days across the four labels (all labels: 46%; 25 to 67 observations each). The labels describe the day; in this sample they do not give a reliable next-day signal. | D15: OI_Interpretation_Summary
A17: Limitations and data notes
A18: # | B18: Topic | C18: Detail | D18: Count / value
A19: 1 | B19: No-trade rows | C19: Contract listed but with no prices, volume or OI on that date; kept in the data but excluded from averages. | D19: =COUNTBLANK(Cleaned_Futures_Data!$G$2:$G$756) -> 8
A20: 2 | B20: Missing underlying | C20: Rows that have prices but no index value in the source file, so basis cannot be computed. | D20: =COUNT(Cleaned_Futures_Data!$G$2:$G$756)-COUNT(Cleaned_Futures_Data!$N$2:$N$756) -> 15
A21: 3 | B21: Not classified | C21: Rows with no previous-day price/OI for the same contract (first observation of each expiry or a no-trade row lacking prior price/OI inputs). | D21: =COUNTIF(Cleaned_Futures_Data!$U$2:$U$756,"Not classified") -> 24
A22: 4 | B22: Neutral | C22: Close price exactly unchanged, so no price direction to label. | D22: =COUNTIF(Cleaned_Futures_Data!$U$2:$U$756,"Neutral") -> 1
A23: 5 | B23: Partial expiries | C23: Expiries listed before 01-Jan-2025 or running past 31-Dec-2025 are only partly observed (see Expiry_Summary). | D23: =COUNTIF(Expiry_Summary!K2:K17,"Partial*") -> 6
A24: 6 | B24: Futures only | C24: No options data, interest-rate or dividend data was used, so carry/mispricing and put-call analysis are out of scope.
A25: 7 | B25: Source not re-verified | C25: Data is the NSE-format CSV supplied by the user; it was cleaned (exact duplicates removed) but not reconciled to NSE directly.
A26: 8 | B26: Units | C26: Basis % is stored as a fraction (shown as %). Close Return % and OI Change % are in percentage points. Turnover is in ₹ lakhs.

Sheet Dashboard
A1: NIFTY Futures Dashboard
A3: Key metric | B3: Value
A4: Trading dates | B4: =Summary!B5 -> 249
A5: Contract-day records | B5: =Summary!B4 -> 755
A6: Expiries in data | B6: =Summary!B6 -> 16
A7: Total contracts (mn) | B7: =Summary!B11/1000000 -> 29.854788
A8: Total turnover (₹ lakh crore) | B8: =Summary!B12/10000000 -> 48.299874
A9: Near-month share of contracts | B9: =Summary!B18 -> 0.79259293
A10: Near-month avg basis (pts) | B10: =Summary!B19 -> 68.065779
A11: Near-month annualised basis | B11: =Summary!B21 -> 0.069360256
A12: Peak near-month OI (mn) | B12: =Summary!B22/1000000 -> 18.5475
A13: Peak OI date | B13: =Summary!B23 -> 45968
A15: Conclusions: see the Findings sheet.
A16: NM = near month (earliest listed expiry on each date).

Sheet Summary
A1: Metric | B1: Value
A2: Data start | B2: =MIN(Cleaned_Futures_Data!$B$2:$B$756) -> 45658
A3: Data end | B3: =MAX(Cleaned_Futures_Data!$B$2:$B$756) -> 46022
A4: Cleaned records | B4: =COUNTA(Cleaned_Futures_Data!$A$2:$A$756) -> 755
A5: Unique trading dates | B5: =SUMPRODUCT(1/COUNTIF(Cleaned_Futures_Data!$B$2:$B$756,Cleaned_Futures_Data!$B$2:$B$756)) -> 249
A6: Unique expiries | B6: =SUMPRODUCT(1/COUNTIF(Cleaned_Futures_Data!$C$2:$C$756,Cleaned_Futures_Data!$C$2:$C$756)) -> 16
A7: Valid basis records | B7: =COUNT(Cleaned_Futures_Data!$O$2:$O$756) -> 732
A8: Basis average | B8: =AVERAGE(Cleaned_Futures_Data!$O$2:$O$756) -> 203.47425
A9: Basis minimum | B9: =MIN(Cleaned_Futures_Data!$O$2:$O$756) -> -19.4
A10: Basis maximum | B10: =MAX(Cleaned_Futures_Data!$O$2:$O$756) -> 537.7
A11: Total contracts | B11: =SUM(Cleaned_Futures_Data!$J$2:$J$756) -> 29854788
A12: Total turnover (₹ Lakhs) | B12: =SUM(Cleaned_Futures_Data!$K$2:$K$756) -> 4.8299874e+08
A13: OI classified records | B13: =COUNTA(Cleaned_Futures_Data!$U$2:$U$756)-COUNTIF(Cleaned_Futures_Data!$U$2:$U$756,"Not classified") -> 731
A15: Near-month (front-series) metrics
A16: Metric | B16: Value
A17: Near-month observations | B17: =COUNTIF(Cleaned_Futures_Data!$W$2:$W$756,1) -> 249
A18: Near-month share of contracts | B18: =Basis_Analysis!F18 -> 0.79259293
A19: Near-month basis average (pts) | B19: =AVERAGEIFS(Cleaned_Futures_Data!$O$2:$O$756,Cleaned_Futures_Data!$W$2:$W$756,1) -> 68.065779
A20: Near-month basis average (%) | B20: =AVERAGEIFS(Cleaned_Futures_Data!$P$2:$P$756,Cleaned_Futures_Data!$W$2:$W$756,1) -> 0.0027611099
A21: Near-month annualised basis (DTE > cutoff) | B21: =Basis_Analysis!B4 -> 0.069360256
A22: Peak near-month open interest | B22: =MAX(NearMonth_Daily!$H$2:$H$250) -> 18547500
A23: Peak open interest date | B23: =INDEX(NearMonth_Daily!$A$2:$A$250,MATCH(MAX(NearMonth_Daily!$H$2:$H$250),NearMonth_Daily!$H$2:$H$250,0)) -> 45968
A25: Basis average above (row 8) blends near, next and far contracts. Use the near-month figures for a like-for-like view.

Sheet Monthly_Summary
A1: Month | B1: Observations | C1: Total_Contracts | D1: Avg_OI | E1: Avg_Basis | F1: Turnover_Lakhs | G1: NM_Contracts | H1: NM_Share_of_Contracts | I1: NM_Avg_Basis | J1: NM_Avg_Basis_% | K1: NM_Avg_OI
A2: 2025-01 | B2: =COUNTIFS(Cleaned_Futures_Data!$V$2:$V$756,$A2) -> 70 | C2: =SUMIFS(Cleaned_Futures_Data!$J$2:$J$756,Cleaned_Futures_Data!$V$2:$V$756,$A2) -> 6009928 | D2: =AVERAGEIFS(Cleaned_Futures_Data!$L$2:$L$756,Cleaned_Futures_Data!$V$2:$V$756,$A2) -> 5801928.6 | E2: =AVERAGEIFS(Cleaned_Futures_Data!$O$2:$O$756,Cleaned_Futures_Data!$V$2:$V$756,$A2) -> 208.81594 | F2: =SUMIFS(Cleaned_Futures_Data!$K$2:$K$756,Cleaned_Futures_Data!$V$2:$V$756,$A2) -> 42926850 | G2: =SUMIFS(Cleaned_Futures_Data!$J$2:$J$756,Cleaned_Futures_Data!$V$2:$V$756,$A2,Cleaned_Futures_Data!$W$2:$W$756,1) -> 5440422 | H2: =G2/C2 -> 0.90523913 | I2: =AVERAGEIFS(Cleaned_Futures_Data!$O$2:$O$756,Cleaned_Futures_Data!$V$2:$V$756,$A2,Cleaned_Futures_Data!$W$2:$W$756,1) -> 67.136957 | J2: =AVERAGEIFS(Cleaned_Futures_Data!$P$2:$P$756,Cleaned_Futures_Data!$V$2:$V$756,$A2,Cleaned_Futures_Data!$W$2:$W$756,1) -> 0.0028587268 | K2: =AVERAGEIFS(Cleaned_Futures_Data!$L$2:$L$756,Cleaned_Futures_Data!$V$2:$V$756,$A2,Cleaned_Futures_Data!$W$2:$W$756,1) -> 12654868
A3: 2025-02 | B3: =COUNTIFS(Cleaned_Futures_Data!$V$2:$V$756,$A3) -> 61 | C3: =SUMIFS(Cleaned_Futures_Data!$J$2:$J$756,Cleaned_Futures_Data!$V$2:$V$756,$A3) -> 2326946 | D3: =AVERAGEIFS(Cleaned_Futures_Data!$L$2:$L$756,Cleaned_Futures_Data!$V$2:$V$756,$A3) -> 6342351.2 | E3: =AVERAGEIFS(Cleaned_Futures_Data!$O$2:$O$756,Cleaned_Futures_Data!$V$2:$V$756,$A3) -> 203.67982 | F3: =SUMIFS(Cleaned_Futures_Data!$K$2:$K$756,Cleaned_Futures_Data!$V$2:$V$756,$A3) -> 40274515 | G3: =SUMIFS(Cleaned_Futures_Data!$J$2:$J$756,Cleaned_Futures_Data!$V$2:$V$756,$A3,Cleaned_Futures_Data!$W$2:$W$756,1) -> 1876281 | H3: =G3/C3 -> 0.80632769 | I3: =AVERAGEIFS(Cleaned_Futures_Data!$O$2:$O$756,Cleaned_Futures_Data!$V$2:$V$756,$A3,Cleaned_Futures_Data!$W$2:$W$756,1) -> 62.421053 | J3: =AVERAGEIFS(Cleaned_Futures_Data!$P$2:$P$756,Cleaned_Futures_Data!$V$2:$V$756,$A3,Cleaned_Futures_Data!$W$2:$W$756,1) -> 0.0027107936 | K3: =AVERAGEIFS(Cleaned_Futures_Data!$L$2:$L$756,Cleaned_Futures_Data!$V$2:$V$756,$A3,Cleaned_Futures_Data!$W$2:$W$756,1) -> 15540165
A4: 2025-03 | B4: =COUNTIFS(Cleaned_Futures_Data!$V$2:$V$756,$A4) -> 58 | C4: =SUMIFS(Cleaned_Futures_Data!$J$2:$J$756,Cleaned_Futures_Data!$V$2:$V$756,$A4) -> 2149492 | D4: =AVERAGEIFS(Cleaned_Futures_Data!$L$2:$L$756,Cleaned_Futures_Data!$V$2:$V$756,$A4) -> 6439617.1 | E4: =AVERAGEIFS(Cleaned_Futures_Data!$O$2:$O$756,Cleaned_Futures_Data!$V$2:$V$756,$A4) -> 199.35093 | F4: =SUMIFS(Cleaned_Futures_Data!$K$2:$K$756,Cleaned_Futures_Data!$V$2:$V$756,$A4) -> 37214609 | G4: =SUMIFS(Cleaned_Futures_Data!$J$2:$J$756,Cleaned_Futures_Data!$V$2:$V$756,$A4,Cleaned_Futures_Data!$W$2:$W$756,1) -> 1613022 | H4: =G4/C4 -> 0.7504201 | I4: =AVERAGEIFS(Cleaned_Futures_Data!$O$2:$O$756,Cleaned_Futures_Data!$V$2:$V$756,$A4,Cleaned_Futures_Data!$W$2:$W$756,1) -> 61.708333 | J4: =AVERAGEIFS(Cleaned_Futures_Data!$P$2:$P$756,Cleaned_Futures_Data!$V$2:$V$756,$A4,Cleaned_Futures_Data!$W$2:$W$756,1) -> 0.0027337817 | K4: =AVERAGEIFS(Cleaned_Futures_Data!$L$2:$L$756,Cleaned_Futures_Data!$V$2:$V$756,$A4,Cleaned_Futures_Data!$W$2:$W$756,1) -> 15222375
A5: 2025-04 | B5: =COUNTIFS(Cleaned_Futures_Data!$V$2:$V$756,$A5) -> 58 | C5: =SUMIFS(Cleaned_Futures_Data!$J$2:$J$756,Cleaned_Futures_Data!$V$2:$V$756,$A5) -> 2543096 | D5: =AVERAGEIFS(Cleaned_Futures_Data!$L$2:$L$756,Cleaned_Futures_Data!$V$2:$V$756,$A5) -> 5103951.3 | E5: =AVERAGEIFS(Cleaned_Futures_Data!$O$2:$O$756,Cleaned_Futures_Data!$V$2:$V$756,$A5) -> 170.39216 | F5: =SUMIFS(Cleaned_Futures_Data!$K$2:$K$756,Cleaned_Futures_Data!$V$2:$V$756,$A5) -> 44839197 | G5: =SUMIFS(Cleaned_Futures_Data!$J$2:$J$756,Cleaned_Futures_Data!$V$2:$V$756,$A5,Cleaned_Futures_Data!$W$2:$W$756,1) -> 2028952 | H5: =G5/C5 -> 0.79782753 | I5: =AVERAGEIFS(Cleaned_Futures_Data!$O$2:$O$756,Cleaned_Futures_Data!$V$2:$V$756,$A5,Cleaned_Futures_Data!$W$2:$W$756,1) -> 56.576471 | J5: =AVERAGEIFS(Cleaned_Futures_Data!$P$2:$P$756,Cleaned_Futures_Data!$V$2:$V$756,$A5,Cleaned_Futures_Data!$W$2:$W$756,1) -> 0.0024068558 | K5: =AVERAGEIFS(Cleaned_Futures_Data!$L$2:$L$756,Cleaned_Futures_Data!$V$2:$V$756,$A5,Cleaned_Futures_Data!$W$2:$W$756,1) -> 11641867
A6: 2025-05 | B6: =COUNTIFS(Cleaned_Futures_Data!$V$2:$V$756,$A6) -> 64 | C6: =SUMIFS(Cleaned_Futures_Data!$J$2:$J$756,Cleaned_Futures_Data!$V$2:$V$756,$A6) -> 2972628 | D6: =AVERAGEIFS(Cleaned_Futures_Data!$L$2:$L$756,Cleaned_Futures_Data!$V$2:$V$756,$A6) -> 5592363.1 | E6: =AVERAGEIFS(Cleaned_Futures_Data!$O$2:$O$756,Cleaned_Futures_Data!$V$2:$V$756,$A6) -> 160.0525 | F6: =SUMIFS(Cleaned_Futures_Data!$K$2:$K$756,Cleaned_Futures_Data!$V$2:$V$756,$A6) -> 55201331 | G6: =SUMIFS(Cleaned_Futures_Data!$J$2:$J$756,Cleaned_Futures_Data!$V$2:$V$756,$A6,Cleaned_Futures_Data!$W$2:$W$756,1) -> 2235930 | H6: =G6/C6 -> 0.75217282 | I6: =AVERAGEIFS(Cleaned_Futures_Data!$O$2:$O$756,Cleaned_Futures_Data!$V$2:$V$756,$A6,Cleaned_Futures_Data!$W$2:$W$756,1) -> 43.9075 | J6: =AVERAGEIFS(Cleaned_Futures_Data!$P$2:$P$756,Cleaned_Futures_Data!$V$2:$V$756,$A6,Cleaned_Futures_Data!$W$2:$W$756,1) -> 0.001781648 | K6: =AVERAGEIFS(Cleaned_Futures_Data!$L$2:$L$756,Cleaned_Futures_Data!$V$2:$V$756,$A6,Cleaned_Futures_Data!$W$2:$W$756,1) -> 11132689
A7: 2025-06 | B7: =COUNTIFS(Cleaned_Futures_Data!$V$2:$V$756,$A7) -> 64 | C7: =SUMIFS(Cleaned_Futures_Data!$J$2:$J$756,Cleaned_Futures_Data!$V$2:$V$756,$A7) -> 2390931 | D7: =AVERAGEIFS(Cleaned_Futures_Data!$L$2:$L$756,Cleaned_Futures_Data!$V$2:$V$756,$A7) -> 5930657.1 | E7: =AVERAGEIFS(Cleaned_Futures_Data!$O$2:$O$756,Cleaned_Futures_Data!$V$2:$V$756,$A7) -> 172.63571 | F7: =SUMIFS(Cleaned_Futures_Data!$K$2:$K$756,Cleaned_Futures_Data!$V$2:$V$756,$A7) -> 45009826 | G7: =SUMIFS(Cleaned_Futures_Data!$J$2:$J$756,Cleaned_Futures_Data!$V$2:$V$756,$A7,Cleaned_Futures_Data!$W$2:$W$756,1) -> 1771663 | H7: =G7/C7 -> 0.74099294 | I7: =AVERAGEIFS(Cleaned_Futures_Data!$O$2:$O$756,Cleaned_Futures_Data!$V$2:$V$756,$A7,Cleaned_Futures_Data!$W$2:$W$756,1) -> 55.978571 | J7: =AVERAGEIFS(Cleaned_Futures_Data!$P$2:$P$756,Cleaned_Futures_Data!$V$2:$V$756,$A7,Cleaned_Futures_Data!$W$2:$W$756,1) -> 0.002241768 | K7: =AVERAGEIFS(Cleaned_Futures_Data!$L$2:$L$756,Cleaned_Futures_Data!$V$2:$V$756,$A7,Cleaned_Futures_Data!$W$2:$W$756,1) -> 11058639
A8: 2025-07 | B8: =COUNTIFS(Cleaned_Futures_Data!$V$2:$V$756,$A8) -> 71 | C8: =SUMIFS(Cleaned_Futures_Data!$J$2:$J$756,Cleaned_Futures_Data!$V$2:$V$756,$A8) -> 1909479 | D8: =AVERAGEIFS(Cleaned_Futures_Data!$L$2:$L$756,Cleaned_Futures_Data!$V$2:$V$756,$A8) -> 6126076.1 | E8: =AVERAGEIFS(Cleaned_Futures_Data!$O$2:$O$756,Cleaned_Futures_Data!$V$2:$V$756,$A8) -> 176.39275 | F8: =SUMIFS(Cleaned_Futures_Data!$K$2:$K$756,Cleaned_Futures_Data!$V$2:$V$756,$A8) -> 36037760 | G8: =SUMIFS(Cleaned_Futures_Data!$J$2:$J$756,Cleaned_Futures_Data!$V$2:$V$756,$A8,Cleaned_Futures_Data!$W$2:$W$756,1) -> 1417569 | H8: =G8/C8 -> 0.74238523 | I8: =AVERAGEIFS(Cleaned_Futures_Data!$O$2:$O$756,Cleaned_Futures_Data!$V$2:$V$756,$A8,Cleaned_Futures_Data!$W$2:$W$756,1) -> 56.373913 | J8: =AVERAGEIFS(Cleaned_Futures_Data!$P$2:$P$756,Cleaned_Futures_Data!$V$2:$V$756,$A8,Cleaned_Futures_Data!$W$2:$W$756,1) -> 0.0022302335 | K8: =AVERAGEIFS(Cleaned_Futures_Data!$L$2:$L$756,Cleaned_Futures_Data!$V$2:$V$756,$A8,Cleaned_Futures_Data!$W$2:$W$756,1) -> 12515354
A9: 2025-08 | B9: =COUNTIFS(Cleaned_Futures_Data!$V$2:$V$756,$A9) -> 57 | C9: =SUMIFS(Cleaned_Futures_Data!$J$2:$J$756,Cleaned_Futures_Data!$V$2:$V$756,$A9) -> 1812422 | D9: =AVERAGEIFS(Cleaned_Futures_Data!$L$2:$L$756,Cleaned_Futures_Data!$V$2:$V$756,$A9) -> 6054259.2 | E9: =AVERAGEIFS(Cleaned_Futures_Data!$O$2:$O$756,Cleaned_Futures_Data!$V$2:$V$756,$A9) -> 187.67632 | F9: =SUMIFS(Cleaned_Futures_Data!$K$2:$K$756,Cleaned_Futures_Data!$V$2:$V$756,$A9) -> 33710196 | G9: =SUMIFS(Cleaned_Futures_Data!$J$2:$J$756,Cleaned_Futures_Data!$V$2:$V$756,$A9,Cleaned_Futures_Data!$W$2:$W$756,1) -> 1368990 | H9: =G9/C9 -> 0.75533733 | I9: =AVERAGEIFS(Cleaned_Futures_Data!$O$2:$O$756,Cleaned_Futures_Data!$V$2:$V$756,$A9,Cleaned_Futures_Data!$W$2:$W$756,1) -> 57.028947 | J9: =AVERAGEIFS(Cleaned_Futures_Data!$P$2:$P$756,Cleaned_Futures_Data!$V$2:$V$756,$A9,Cleaned_Futures_Data!$W$2:$W$756,1) -> 0.0023134896 | K9: =AVERAGEIFS(Cleaned_Futures_Data!$L$2:$L$756,Cleaned_Futures_Data!$V$2:$V$756,$A9,Cleaned_Futures_Data!$W$2:$W$756,1) -> 14934983
A10: 2025-09 | B10: =COUNTIFS(Cleaned_Futures_Data!$V$2:$V$756,$A10) -> 66 | C10: =SUMIFS(Cleaned_Futures_Data!$J$2:$J$756,Cleaned_Futures_Data!$V$2:$V$756,$A10) -> 1810486 | D10: =AVERAGEIFS(Cleaned_Futures_Data!$L$2:$L$756,Cleaned_Futures_Data!$V$2:$V$756,$A10) -> 6210584.1 | E10: =AVERAGEIFS(Cleaned_Futures_Data!$O$2:$O$756,Cleaned_Futures_Data!$V$2:$V$756,$A10) -> 207.24167 | F10: =SUMIFS(Cleaned_Futures_Data!$K$2:$K$756,Cleaned_Futures_Data!$V$2:$V$756,$A10) -> 33965790 | G10: =SUMIFS(Cleaned_Futures_Data!$J$2:$J$756,Cleaned_Futures_Data!$V$2:$V$756,$A10,Cleaned_Futures_Data!$W$2:$W$756,1) -> 1341682 | H10: =G10/C10 -> 0.74106179 | I10: =AVERAGEIFS(Cleaned_Futures_Data!$O$2:$O$756,Cleaned_Futures_Data!$V$2:$V$756,$A10,Cleaned_Futures_Data!$W$2:$W$756,1) -> 84.347727 | J10: =AVERAGEIFS(Cleaned_Futures_Data!$P$2:$P$756,Cleaned_Futures_Data!$V$2:$V$756,$A10,Cleaned_Futures_Data!$W$2:$W$756,1) -> 0.0033804911 | K10: =AVERAGEIFS(Cleaned_Futures_Data!$L$2:$L$756,Cleaned_Futures_Data!$V$2:$V$756,$A10,Cleaned_Futures_Data!$W$2:$W$756,1) -> 14679893
A11: 2025-10 | B11: =COUNTIFS(Cleaned_Futures_Data!$V$2:$V$756,$A11) -> 63 | C11: =SUMIFS(Cleaned_Futures_Data!$J$2:$J$756,Cleaned_Futures_Data!$V$2:$V$756,$A11) -> 2117667 | D11: =AVERAGEIFS(Cleaned_Futures_Data!$L$2:$L$756,Cleaned_Futures_Data!$V$2:$V$756,$A11) -> 6396007.3 | E11: =AVERAGEIFS(Cleaned_Futures_Data!$O$2:$O$756,Cleaned_Futures_Data!$V$2:$V$756,$A11) -> 238.49762 | F11: =SUMIFS(Cleaned_Futures_Data!$K$2:$K$756,Cleaned_Futures_Data!$V$2:$V$756,$A11) -> 40800354 | G11: =SUMIFS(Cleaned_Futures_Data!$J$2:$J$756,Cleaned_Futures_Data!$V$2:$V$756,$A11,Cleaned_Futures_Data!$W$2:$W$756,1) -> 1646457 | H11: =G11/C11 -> 0.77748626 | I11: =AVERAGEIFS(Cleaned_Futures_Data!$O$2:$O$756,Cleaned_Futures_Data!$V$2:$V$756,$A11,Cleaned_Futures_Data!$W$2:$W$756,1) -> 90.130952 | J11: =AVERAGEIFS(Cleaned_Futures_Data!$P$2:$P$756,Cleaned_Futures_Data!$V$2:$V$756,$A11,Cleaned_Futures_Data!$W$2:$W$756,1) -> 0.0035417858 | K11: =AVERAGEIFS(Cleaned_Futures_Data!$L$2:$L$756,Cleaned_Futures_Data!$V$2:$V$756,$A11,Cleaned_Futures_Data!$W$2:$W$756,1) -> 15979439
A12: 2025-11 | B12: =COUNTIFS(Cleaned_Futures_Data!$V$2:$V$756,$A12) -> 57 | C12: =SUMIFS(Cleaned_Futures_Data!$J$2:$J$756,Cleaned_Futures_Data!$V$2:$V$756,$A12) -> 1884889 | D12: =AVERAGEIFS(Cleaned_Futures_Data!$L$2:$L$756,Cleaned_Futures_Data!$V$2:$V$756,$A12) -> 6375696.5 | E12: =AVERAGEIFS(Cleaned_Futures_Data!$O$2:$O$756,Cleaned_Futures_Data!$V$2:$V$756,$A12) -> 261.53246 | F12: =SUMIFS(Cleaned_Futures_Data!$K$2:$K$756,Cleaned_Futures_Data!$V$2:$V$756,$A12) -> 36648977 | G12: =SUMIFS(Cleaned_Futures_Data!$J$2:$J$756,Cleaned_Futures_Data!$V$2:$V$756,$A12,Cleaned_Futures_Data!$W$2:$W$756,1) -> 1444775 | H12: =G12/C12 -> 0.76650402 | I12: =AVERAGEIFS(Cleaned_Futures_Data!$O$2:$O$756,Cleaned_Futures_Data!$V$2:$V$756,$A12,Cleaned_Futures_Data!$W$2:$W$756,1) -> 86.307895 | J12: =AVERAGEIFS(Cleaned_Futures_Data!$P$2:$P$756,Cleaned_Futures_Data!$V$2:$V$756,$A12,Cleaned_Futures_Data!$W$2:$W$756,1) -> 0.0033341762 | K12: =AVERAGEIFS(Cleaned_Futures_Data!$L$2:$L$756,Cleaned_Futures_Data!$V$2:$V$756,$A12,Cleaned_Futures_Data!$W$2:$W$756,1) -> 15692286
A13: 2025-12 | B13: =COUNTIFS(Cleaned_Futures_Data!$V$2:$V$756,$A13) -> 66 | C13: =SUMIFS(Cleaned_Futures_Data!$J$2:$J$756,Cleaned_Futures_Data!$V$2:$V$756,$A13) -> 1926824 | D13: =AVERAGEIFS(Cleaned_Futures_Data!$L$2:$L$756,Cleaned_Futures_Data!$V$2:$V$756,$A13) -> 5789929.4 | E13: =AVERAGEIFS(Cleaned_Futures_Data!$O$2:$O$756,Cleaned_Futures_Data!$V$2:$V$756,$A13) -> 250.17652 | F13: =SUMIFS(Cleaned_Futures_Data!$K$2:$K$756,Cleaned_Futures_Data!$V$2:$V$756,$A13) -> 36369335 | G13: =SUMIFS(Cleaned_Futures_Data!$J$2:$J$756,Cleaned_Futures_Data!$V$2:$V$756,$A13,Cleaned_Futures_Data!$W$2:$W$756,1) -> 1476951 | H13: =G13/C13 -> 0.76652097 | I13: =AVERAGEIFS(Cleaned_Futures_Data!$O$2:$O$756,Cleaned_Futures_Data!$V$2:$V$756,$A13,Cleaned_Futures_Data!$W$2:$W$756,1) -> 90.147727 | J13: =AVERAGEIFS(Cleaned_Futures_Data!$P$2:$P$756,Cleaned_Futures_Data!$V$2:$V$756,$A13,Cleaned_Futures_Data!$W$2:$W$756,1) -> 0.0034668627 | K13: =AVERAGEIFS(Cleaned_Futures_Data!$L$2:$L$756,Cleaned_Futures_Data!$V$2:$V$756,$A13,Cleaned_Futures_Data!$W$2:$W$756,1) -> 14247043
A14: Total / overall | B14: =SUM(B2:B13) -> 755 | C14: =SUM(C2:C13) -> 29854788 | F14: =SUM(F2:F13) -> 4.8299874e+08 | G14: =SUM(G2:G13) -> 23662694 | H14: =G14/C14 -> 0.79259293
A16: Months are text keys (yyyy-mm). Columns B–F use all series (as in the original workbook); columns G–K restrict to the near-month contract (Series Rank = 1). Basis averages ignore rows with no underlying value.

Sheet Expiry_Summary
A1: Expiry | B1: Observations | C1: Avg_Futures_Close | D1: Avg_Underlying | E1: Avg_Basis | F1: Avg_Basis_Pct | G1: Total_Contracts | H1: Avg_OI | I1: Max_OI | J1: Min_OI | K1: Data_Coverage
A2: 45687 | B2: =COUNTIFS(Cleaned_Futures_Data!$C$2:$C$756,$A2) -> 22 | C2: =AVERAGEIFS(Cleaned_Futures_Data!$G$2:$G$756,Cleaned_Futures_Data!$C$2:$C$756,$A2) -> 23425.048 | D2: =AVERAGEIFS(Cleaned_Futures_Data!$N$2:$N$756,Cleaned_Futures_Data!$C$2:$C$756,$A2) -> 23359.941 | E2: =AVERAGEIFS(Cleaned_Futures_Data!$O$2:$O$756,Cleaned_Futures_Data!$C$2:$C$756,$A2) -> 65.106818 | F2: =AVERAGEIFS(Cleaned_Futures_Data!$P$2:$P$756,Cleaned_Futures_Data!$C$2:$C$756,$A2) -> 0.0027724986 | G2: =SUMIFS(Cleaned_Futures_Data!$J$2:$J$756,Cleaned_Futures_Data!$C$2:$C$756,$A2) -> 5351511 | H2: =AVERAGEIFS(Cleaned_Futures_Data!$L$2:$L$756,Cleaned_Futures_Data!$C$2:$C$756,$A2) -> 12422145 | I2: =_xlfn.MAXIFS(Cleaned_Futures_Data!$L$2:$L$756,Cleaned_Futures_Data!$C$2:$C$756,$A2) -> 14572600 | J2: =_xlfn.MINIFS(Cleaned_Futures_Data!$L$2:$L$756,Cleaned_Futures_Data!$C$2:$C$756,$A2) -> 4310725 | K2: =IF($A2>Summary!$B$3,"Partial – expiry after data end",IF(_xlfn.MINIFS(Cleaned_Futures_Data!$B$2:$B$756,Cleaned_Futures_Data!$C$2:$C$756,$A2)<=Summary!$B$2,"Partial – listed before data start","Full life in data")) -> Partial – listed before data start
A3: 45715 | B3: =COUNTIFS(Cleaned_Futures_Data!$C$2:$C$756,$A3) -> 42 | C3: =AVERAGEIFS(Cleaned_Futures_Data!$G$2:$G$756,Cleaned_Futures_Data!$C$2:$C$756,$A3) -> 23384.267 | D3: =AVERAGEIFS(Cleaned_Futures_Data!$N$2:$N$756,Cleaned_Futures_Data!$C$2:$C$756,$A3) -> 23238.583 | E3: =AVERAGEIFS(Cleaned_Futures_Data!$O$2:$O$756,Cleaned_Futures_Data!$C$2:$C$756,$A3) -> 135.9 | F3: =AVERAGEIFS(Cleaned_Futures_Data!$P$2:$P$756,Cleaned_Futures_Data!$C$2:$C$756,$A3) -> 0.0058177685 | G3: =SUMIFS(Cleaned_Futures_Data!$J$2:$J$756,Cleaned_Futures_Data!$C$2:$C$756,$A3) -> 2338965 | H3: =AVERAGEIFS(Cleaned_Futures_Data!$L$2:$L$756,Cleaned_Futures_Data!$C$2:$C$756,$A3) -> 9753196.4 | I3: =_xlfn.MAXIFS(Cleaned_Futures_Data!$L$2:$L$756,Cleaned_Futures_Data!$C$2:$C$756,$A3) -> 17774775 | J3: =_xlfn.MINIFS(Cleaned_Futures_Data!$L$2:$L$756,Cleaned_Futures_Data!$C$2:$C$756,$A3) -> 1045725 | K3: =IF($A3>Summary!$B$3,"Partial – expiry after data end",IF(_xlfn.MINIFS(Cleaned_Futures_Data!$B$2:$B$756,Cleaned_Futures_Data!$C$2:$C$756,$A3)<=Summary!$B$2,"Partial – listed before data start","Full life in data")) -> Partial – listed before data start
A4: 45743 | B4: =COUNTIFS(Cleaned_Futures_Data!$C$2:$C$756,$A4) -> 61 | C4: =AVERAGEIFS(Cleaned_Futures_Data!$G$2:$G$756,Cleaned_Futures_Data!$C$2:$C$756,$A4) -> 23316.927 | D4: =AVERAGEIFS(Cleaned_Futures_Data!$N$2:$N$756,Cleaned_Futures_Data!$C$2:$C$756,$A4) -> 23092.774 | E4: =AVERAGEIFS(Cleaned_Futures_Data!$O$2:$O$756,Cleaned_Futures_Data!$C$2:$C$756,$A4) -> 214.04417 | F4: =AVERAGEIFS(Cleaned_Futures_Data!$P$2:$P$756,Cleaned_Futures_Data!$C$2:$C$756,$A4) -> 0.0092182512 | G4: =SUMIFS(Cleaned_Futures_Data!$J$2:$J$756,Cleaned_Futures_Data!$C$2:$C$756,$A4) -> 2101614 | H4: =AVERAGEIFS(Cleaned_Futures_Data!$L$2:$L$756,Cleaned_Futures_Data!$C$2:$C$756,$A4) -> 6021644.3 | I4: =_xlfn.MAXIFS(Cleaned_Futures_Data!$L$2:$L$756,Cleaned_Futures_Data!$C$2:$C$756,$A4) -> 18198750 | J4: =_xlfn.MINIFS(Cleaned_Futures_Data!$L$2:$L$756,Cleaned_Futures_Data!$C$2:$C$756,$A4) -> 126525 | K4: =IF($A4>Summary!$B$3,"Partial – expiry after data end",IF(_xlfn.MINIFS(Cleaned_Futures_Data!$B$2:$B$756,Cleaned_Futures_Data!$C$2:$C$756,$A4)<=Summary!$B$2,"Partial – listed before data start","Full life in data")) -> Partial – listed before data start
A5: 45771 | B5: =COUNTIFS(Cleaned_Futures_Data!$C$2:$C$756,$A5) -> 56 | C5: =AVERAGEIFS(Cleaned_Futures_Data!$G$2:$G$756,Cleaned_Futures_Data!$C$2:$C$756,$A5) -> 23287.536 | D5: =AVERAGEIFS(Cleaned_Futures_Data!$N$2:$N$756,Cleaned_Futures_Data!$C$2:$C$756,$A5) -> 23078.704 | E5: =AVERAGEIFS(Cleaned_Futures_Data!$O$2:$O$756,Cleaned_Futures_Data!$C$2:$C$756,$A5) -> 219.69412 | F5: =AVERAGEIFS(Cleaned_Futures_Data!$P$2:$P$756,Cleaned_Futures_Data!$C$2:$C$756,$A5) -> 0.0095708758 | G5: =SUMIFS(Cleaned_Futures_Data!$J$2:$J$756,Cleaned_Futures_Data!$C$2:$C$756,$A5) -> 2204839 | H5: =AVERAGEIFS(Cleaned_Futures_Data!$L$2:$L$756,Cleaned_Futures_Data!$C$2:$C$756,$A5) -> 4529143.6 | I5: =_xlfn.MAXIFS(Cleaned_Futures_Data!$L$2:$L$756,Cleaned_Futures_Data!$C$2:$C$756,$A5) -> 13875975 | J5: =_xlfn.MINIFS(Cleaned_Futures_Data!$L$2:$L$756,Cleaned_Futures_Data!$C$2:$C$756,$A5) -> 49125 | K5: =IF($A5>Summary!$B$3,"Partial – expiry after data end",IF(_xlfn.MINIFS(Cleaned_Futures_Data!$B$2:$B$756,Cleaned_Futures_Data!$C$2:$C$756,$A5)<=Summary!$B$2,"Partial – listed before data start","Full life in data")) -> Full life in data
A6: 45806 | B6: =COUNTIFS(Cleaned_Futures_Data!$C$2:$C$756,$A6) -> 60 | C6: =AVERAGEIFS(Cleaned_Futures_Data!$G$2:$G$756,Cleaned_Futures_Data!$C$2:$C$756,$A6) -> 23850.994 | D6: =AVERAGEIFS(Cleaned_Futures_Data!$N$2:$N$756,Cleaned_Futures_Data!$C$2:$C$756,$A6) -> 23725.772 | E6: =AVERAGEIFS(Cleaned_Futures_Data!$O$2:$O$756,Cleaned_Futures_Data!$C$2:$C$756,$A6) -> 172.98482 | F6: =AVERAGEIFS(Cleaned_Futures_Data!$P$2:$P$756,Cleaned_Futures_Data!$C$2:$C$756,$A6) -> 0.0074916305 | G6: =SUMIFS(Cleaned_Futures_Data!$J$2:$J$756,Cleaned_Futures_Data!$C$2:$C$756,$A6) -> 3092764 | H6: =AVERAGEIFS(Cleaned_Futures_Data!$L$2:$L$756,Cleaned_Futures_Data!$C$2:$C$756,$A6) -> 5760575.8 | I6: =_xlfn.MAXIFS(Cleaned_Futures_Data!$L$2:$L$756,Cleaned_Futures_Data!$C$2:$C$756,$A6) -> 13527900 | J6: =_xlfn.MINIFS(Cleaned_Futures_Data!$L$2:$L$756,Cleaned_Futures_Data!$C$2:$C$756,$A6) -> 94950 | K6: =IF($A6>Summary!$B$3,"Partial – expiry after data end",IF(_xlfn.MINIFS(Cleaned_Futures_Data!$B$2:$B$756,Cleaned_Futures_Data!$C$2:$C$756,$A6)<=Summary!$B$2,"Partial – listed before data start","Full life in data")) -> Full life in data
A7: 45834 | B7: =COUNTIFS(Cleaned_Futures_Data!$C$2:$C$756,$A7) -> 61 | C7: =AVERAGEIFS(Cleaned_Futures_Data!$G$2:$G$756,Cleaned_Futures_Data!$C$2:$C$756,$A7) -> 24534.79 | D7: =AVERAGEIFS(Cleaned_Futures_Data!$N$2:$N$756,Cleaned_Futures_Data!$C$2:$C$756,$A7) -> 24460.271 | E7: =AVERAGEIFS(Cleaned_Futures_Data!$O$2:$O$756,Cleaned_Futures_Data!$C$2:$C$756,$A7) -> 147.42054 | F7: =AVERAGEIFS(Cleaned_Futures_Data!$P$2:$P$756,Cleaned_Futures_Data!$C$2:$C$756,$A7) -> 0.0061165069 | G7: =SUMIFS(Cleaned_Futures_Data!$J$2:$J$756,Cleaned_Futures_Data!$C$2:$C$756,$A7) -> 2418474 | H7: =AVERAGEIFS(Cleaned_Futures_Data!$L$2:$L$756,Cleaned_Futures_Data!$C$2:$C$756,$A7) -> 5657630 | I7: =_xlfn.MAXIFS(Cleaned_Futures_Data!$L$2:$L$756,Cleaned_Futures_Data!$C$2:$C$756,$A7) -> 13020000 | J7: =_xlfn.MINIFS(Cleaned_Futures_Data!$L$2:$L$756,Cleaned_Futures_Data!$C$2:$C$756,$A7) -> 172650 | K7: =IF($A7>Summary!$B$3,"Partial – expiry after data end",IF(_xlfn.MINIFS(Cleaned_Futures_Data!$B$2:$B$756,Cleaned_Futures_Data!$C$2:$C$756,$A7)<=Summary!$B$2,"Partial – listed before data start","Full life in data")) -> Full life in data
A8: 45869 | B8: =COUNTIFS(Cleaned_Futures_Data!$C$2:$C$756,$A8) -> 70 | C8: =AVERAGEIFS(Cleaned_Futures_Data!$G$2:$G$756,Cleaned_Futures_Data!$C$2:$C$756,$A8) -> 25089.175 | D8: =AVERAGEIFS(Cleaned_Futures_Data!$N$2:$N$756,Cleaned_Futures_Data!$C$2:$C$756,$A8) -> 24917.006 | E8: =AVERAGEIFS(Cleaned_Futures_Data!$O$2:$O$756,Cleaned_Futures_Data!$C$2:$C$756,$A8) -> 173.44265 | F8: =AVERAGEIFS(Cleaned_Futures_Data!$P$2:$P$756,Cleaned_Futures_Data!$C$2:$C$756,$A8) -> 0.0070044582 | G8: =SUMIFS(Cleaned_Futures_Data!$J$2:$J$756,Cleaned_Futures_Data!$C$2:$C$756,$A8) -> 2223064 | H8: =AVERAGEIFS(Cleaned_Futures_Data!$L$2:$L$756,Cleaned_Futures_Data!$C$2:$C$756,$A8) -> 6670808.7 | I8: =_xlfn.MAXIFS(Cleaned_Futures_Data!$L$2:$L$756,Cleaned_Futures_Data!$C$2:$C$756,$A8) -> 14899275 | J8: =_xlfn.MINIFS(Cleaned_Futures_Data!$L$2:$L$756,Cleaned_Futures_Data!$C$2:$C$756,$A8) -> 67500 | K8: =IF($A8>Summary!$B$3,"Partial – expiry after data end",IF(_xlfn.MINIFS(Cleaned_Futures_Data!$B$2:$B$756,Cleaned_Futures_Data!$C$2:$C$756,$A8)<=Summary!$B$2,"Partial – listed before data start","Full life in data")) -> Full life in data
A9: 45897 | B9: =COUNTIFS(Cleaned_Futures_Data!$C$2:$C$756,$A9) -> 64 | C9: =AVERAGEIFS(Cleaned_Futures_Data!$G$2:$G$756,Cleaned_Futures_Data!$C$2:$C$756,$A9) -> 25145.592 | D9: =AVERAGEIFS(Cleaned_Futures_Data!$N$2:$N$756,Cleaned_Futures_Data!$C$2:$C$756,$A9) -> 24979.048 | E9: =AVERAGEIFS(Cleaned_Futures_Data!$O$2:$O$756,Cleaned_Futures_Data!$C$2:$C$756,$A9) -> 166.86048 | F9: =AVERAGEIFS(Cleaned_Futures_Data!$P$2:$P$756,Cleaned_Futures_Data!$C$2:$C$756,$A9) -> 0.0066679497 | G9: =SUMIFS(Cleaned_Futures_Data!$J$2:$J$756,Cleaned_Futures_Data!$C$2:$C$756,$A9) -> 1821835 | H9: =AVERAGEIFS(Cleaned_Futures_Data!$L$2:$L$756,Cleaned_Futures_Data!$C$2:$C$756,$A9) -> 6433994 | I9: =_xlfn.MAXIFS(Cleaned_Futures_Data!$L$2:$L$756,Cleaned_Futures_Data!$C$2:$C$756,$A9) -> 17244675 | J9: =_xlfn.MINIFS(Cleaned_Futures_Data!$L$2:$L$756,Cleaned_Futures_Data!$C$2:$C$756,$A9) -> 34575 | K9: =IF($A9>Summary!$B$3,"Partial – expiry after data end",IF(_xlfn.MINIFS(Cleaned_Futures_Data!$B$2:$B$756,Cleaned_Futures_Data!$C$2:$C$756,$A9)<=Summary!$B$2,"Partial – listed before data start","Full life in data")) -> Full life in data
A10: 45925 | B10: =COUNTIFS(Cleaned_Futures_Data!$C$2:$C$756,$A10) -> 26 | C10: =AVERAGEIFS(Cleaned_Futures_Data!$G$2:$G$756,Cleaned_Futures_Data!$C$2:$C$756,$A10) -> 25515.164 | D10: =AVERAGEIFS(Cleaned_Futures_Data!$N$2:$N$756,Cleaned_Futures_Data!$C$2:$C$756,$A10) -> 25197.894 | E10: =AVERAGEIFS(Cleaned_Futures_Data!$O$2:$O$756,Cleaned_Futures_Data!$C$2:$C$756,$A10) -> 317.27 | F10: =AVERAGEIFS(Cleaned_Futures_Data!$P$2:$P$756,Cleaned_Futures_Data!$C$2:$C$756,$A10) -> 0.012578453 | G10: =SUMIFS(Cleaned_Futures_Data!$J$2:$J$756,Cleaned_Futures_Data!$C$2:$C$756,$A10) -> 49693 | H10: =AVERAGEIFS(Cleaned_Futures_Data!$L$2:$L$756,Cleaned_Futures_Data!$C$2:$C$756,$A10) -> 414312 | I10: =_xlfn.MAXIFS(Cleaned_Futures_Data!$L$2:$L$756,Cleaned_Futures_Data!$C$2:$C$756,$A10) -> 862425 | J10: =_xlfn.MINIFS(Cleaned_Futures_Data!$L$2:$L$756,Cleaned_Futures_Data!$C$2:$C$756,$A10) -> 105225 | K10: =IF($A10>Summary!$B$3,"Partial – expiry after data end",IF(_xlfn.MINIFS(Cleaned_Futures_Data!$B$2:$B$756,Cleaned_Futures_Data!$C$2:$C$756,$A10)<=Summary!$B$2,"Partial – listed before data start","Full life in data")) -> Full life in data
A11: 45930 | B11: =COUNTIFS(Cleaned_Futures_Data!$C$2:$C$756,$A11) -> 42 | C11: =AVERAGEIFS(Cleaned_Futures_Data!$G$2:$G$756,Cleaned_Futures_Data!$C$2:$C$756,$A11) -> 24961.473 | D11: =AVERAGEIFS(Cleaned_Futures_Data!$N$2:$N$756,Cleaned_Futures_Data!$C$2:$C$756,$A11) -> 24829.337 | E11: =AVERAGEIFS(Cleaned_Futures_Data!$O$2:$O$756,Cleaned_Futures_Data!$C$2:$C$756,$A11) -> 132.13659 | F11: =AVERAGEIFS(Cleaned_Futures_Data!$P$2:$P$756,Cleaned_Futures_Data!$C$2:$C$756,$A11) -> 0.0053322058 | G11: =SUMIFS(Cleaned_Futures_Data!$J$2:$J$756,Cleaned_Futures_Data!$C$2:$C$756,$A11) -> 1804864 | H11: =AVERAGEIFS(Cleaned_Futures_Data!$L$2:$L$756,Cleaned_Futures_Data!$C$2:$C$756,$A11) -> 9609387.8 | I11: =_xlfn.MAXIFS(Cleaned_Futures_Data!$L$2:$L$756,Cleaned_Futures_Data!$C$2:$C$756,$A11) -> 17231025 | J11: =_xlfn.MINIFS(Cleaned_Futures_Data!$L$2:$L$756,Cleaned_Futures_Data!$C$2:$C$756,$A11) -> 905475 | K11: =IF($A11>Summary!$B$3,"Partial – expiry after data end",IF(_xlfn.MINIFS(Cleaned_Futures_Data!$B$2:$B$756,Cleaned_Futures_Data!$C$2:$C$756,$A11)<=Summary!$B$2,"Partial – listed before data start","Full life in data")) -> Full life in data
A12: 45958 | B12: =COUNTIFS(Cleaned_Futures_Data!$C$2:$C$756,$A12) -> 60 | C12: =AVERAGEIFS(Cleaned_Futures_Data!$G$2:$G$756,Cleaned_Futures_Data!$C$2:$C$756,$A12) -> 25211.061 | D12: =AVERAGEIFS(Cleaned_Futures_Data!$N$2:$N$756,Cleaned_Futures_Data!$C$2:$C$756,$A12) -> 25012.283 | E12: =AVERAGEIFS(Cleaned_Futures_Data!$O$2:$O$756,Cleaned_Futures_Data!$C$2:$C$756,$A12) -> 198.77797 | F12: =AVERAGEIFS(Cleaned_Futures_Data!$P$2:$P$756,Cleaned_Futures_Data!$C$2:$C$756,$A12) -> 0.0079963492 | G12: =SUMIFS(Cleaned_Futures_Data!$J$2:$J$756,Cleaned_Futures_Data!$C$2:$C$756,$A12) -> 1860756 | H12: =AVERAGEIFS(Cleaned_Futures_Data!$L$2:$L$756,Cleaned_Futures_Data!$C$2:$C$756,$A12) -> 6308780.1 | I12: =_xlfn.MAXIFS(Cleaned_Futures_Data!$L$2:$L$756,Cleaned_Futures_Data!$C$2:$C$756,$A12) -> 18296400 | J12: =_xlfn.MINIFS(Cleaned_Futures_Data!$L$2:$L$756,Cleaned_Futures_Data!$C$2:$C$756,$A12) -> 61125 | K12: =IF($A12>Summary!$B$3,"Partial – expiry after data end",IF(_xlfn.MINIFS(Cleaned_Futures_Data!$B$2:$B$756,Cleaned_Futures_Data!$C$2:$C$756,$A12)<=Summary!$B$2,"Partial – listed before data start","Full life in data")) -> Full life in data
A13: 45986 | B13: =COUNTIFS(Cleaned_Futures_Data!$C$2:$C$756,$A13) -> 60 | C13: =AVERAGEIFS(Cleaned_Futures_Data!$G$2:$G$756,Cleaned_Futures_Data!$C$2:$C$756,$A13) -> 25583.143 | D13: =AVERAGEIFS(Cleaned_Futures_Data!$N$2:$N$756,Cleaned_Futures_Data!$C$2:$C$756,$A13) -> 25365.325 | E13: =AVERAGEIFS(Cleaned_Futures_Data!$O$2:$O$756,Cleaned_Futures_Data!$C$2:$C$756,$A13) -> 217.81833 | F13: =AVERAGEIFS(Cleaned_Futures_Data!$P$2:$P$756,Cleaned_Futures_Data!$C$2:$C$756,$A13) -> 0.0086593338 | G13: =SUMIFS(Cleaned_Futures_Data!$J$2:$J$756,Cleaned_Futures_Data!$C$2:$C$756,$A13) -> 1945073 | H13: =AVERAGEIFS(Cleaned_Futures_Data!$L$2:$L$756,Cleaned_Futures_Data!$C$2:$C$756,$A13) -> 6172328.8 | I13: =_xlfn.MAXIFS(Cleaned_Futures_Data!$L$2:$L$756,Cleaned_Futures_Data!$C$2:$C$756,$A13) -> 18547500 | J13: =_xlfn.MINIFS(Cleaned_Futures_Data!$L$2:$L$756,Cleaned_Futures_Data!$C$2:$C$756,$A13) -> 47325 | K13: =IF($A13>Summary!$B$3,"Partial – expiry after data end",IF(_xlfn.MINIFS(Cleaned_Futures_Data!$B$2:$B$756,Cleaned_Futures_Data!$C$2:$C$756,$A13)<=Summary!$B$2,"Partial – listed before data start","Full life in data")) -> Full life in data
... A17: 46111 | B17: =COUNTIFS(Cleaned_Futures_Data!$C$2:$C$756,$A17) -> 1 | C17: =AVERAGEIFS(Cleaned_Futures_Data!$G$2:$G$756,Cleaned_Futures_Data!$C$2:$C$756,$A17) -> 26617.1 | D17: =AVERAGEIFS(Cleaned_Futures_Data!$N$2:$N$756,Cleaned_Futures_Data!$C$2:$C$756,$A17) -> 26129.6 | E17: =AVERAGEIFS(Cleaned_Futures_Data!$O$2:$O$756,Cleaned_Futures_Data!$C$2:$C$756,$A17) -> 487.5 | F17: =AVERAGEIFS(Cleaned_Futures_Data!$P$2:$P$756,Cleaned_Futures_Data!$C$2:$C$756,$A17) -> 0.018657002 | G17: =SUMIFS(Cleaned_Futures_Data!$J$2:$J$756,Cleaned_Futures_Data!$C$2:$C$756,$A17) -> 2553 | H17: =AVERAGEIFS(Cleaned_Futures_Data!$L$2:$L$756,Cleaned_Futures_Data!$C$2:$C$756,$A17) -> 138515 | I17: =_xlfn.MAXIFS(Cleaned_Futures_Data!$L$2:$L$756,Cleaned_Futures_Data!$C$2:$C$756,$A17) -> 138515 | J17: =_xlfn.MINIFS(Cleaned_Futures_Data!$L$2:$L$756,Cleaned_Futures_Data!$C$2:$C$756,$A17) -> 138515 | K17: =IF($A17>Summary!$B$3,"Partial – expiry after data end",IF(_xlfn.MINIFS(Cleaned_Futures_Data!$B$2:$B$756,Cleaned_Futures_Data!$C$2:$C$756,$A17)<=Summary!$B$2,"Partial – listed before data start","Full life in data")) -> Partial – expiry after data end
A19: Coverage flag: expiries listed before 01-Jan-2025 or still running after 31-Dec-2025 are only partly observed, so their averages are not comparable with full-life expiries (e.g. Mar-2026 has one row). Sep-2025 shows two expiries (25-Sep and 30-Sep) in the source data.

Sheet Basis_Analysis
A1: Basis & Rollover Analysis
A3: Expiry-week cutoff (days to expiry) | B3: 5 | C3: Input. Rows with Days to Expiry ≤ this value are treated as expiry week; the signal test on the OI_Interpretation_Summary sheet excludes them because OI falls mechanically as contracts expire.
A4: Near-month annualised basis (DTE > cutoff) | B4: =AVERAGEIFS(Cleaned_Futures_Data!$X$2:$X$756,Cleaned_Futures_Data!$W$2:$W$756,1,Cleaned_Futures_Data!$Q$2:$Q$756,">"&B3) -> 0.069360256 | C4: Annualised basis = Basis % × 365 ÷ Days to Expiry: the carry rate implied by the futures price. No interest-rate or dividend data was supplied, so it is not benchmarked here.
A6: 1. Near-month basis by days to expiry
A7: Days-to-expiry bucket | B7: From (DTE) | C7: To (DTE) | D7: Observations | E7: Avg Basis (pts) | F7: Avg Basis % | G7: Avg Annualised Basis % | H7: Avg Near-Month OI | I7: Avg Next-Month OI | J7: Near-Month Share of Near+Next OI
A8: Expiry day (0) | B8: 0 | C8: 0 | D8: =COUNTIFS(Cleaned_Futures_Data!$W$2:$W$756,1,Cleaned_Futures_Data!$Q$2:$Q$756,">="&$B8,Cleaned_Futures_Data!$Q$2:$Q$756,"<="&$C8) -> 12 | E8: =IFERROR(AVERAGEIFS(Cleaned_Futures_Data!$O$2:$O$756,Cleaned_Futures_Data!$W$2:$W$756,1,Cleaned_Futures_Data!$Q$2:$Q$756,">="&$B8,Cleaned_Futures_Data!$Q$2:$Q$756,"<="&$C8),"") -> -3.5375 | F8: =IFERROR(AVERAGEIFS(Cleaned_Futures_Data!$P$2:$P$756,Cleaned_Futures_Data!$W$2:$W$756,1,Cleaned_Futures_Data!$Q$2:$Q$756,">="&$B8,Cleaned_Futures_Data!$Q$2:$Q$756,"<="&$C8),"") -> -0.00014296025 | G8: =IFERROR(AVERAGEIFS(Cleaned_Futures_Data!$X$2:$X$756,Cleaned_Futures_Data!$W$2:$W$756,1,Cleaned_Futures_Data!$Q$2:$Q$756,">="&$B8,Cleaned_Futures_Data!$Q$2:$Q$756,"<="&$C8),"") | H8: =IFERROR(AVERAGEIFS(Cleaned_Futures_Data!$L$2:$L$756,Cleaned_Futures_Data!$W$2:$W$756,1,Cleaned_Futures_Data!$Q$2:$Q$756,">="&$B8,Cleaned_Futures_Data!$Q$2:$Q$756,"<="&$C8),"") -> 4449502.1 | I8: =IFERROR(AVERAGEIFS(Cleaned_Futures_Data!$AA$2:$AA$756,Cleaned_Futures_Data!$W$2:$W$756,1,Cleaned_Futures_Data!$Q$2:$Q$756,">="&$B8,Cleaned_Futures_Data!$Q$2:$Q$756,"<="&$C8),"") -> 14677926 | J8: =IFERROR(AVERAGEIFS(Cleaned_Futures_Data!$AB$2:$AB$756,Cleaned_Futures_Data!$W$2:$W$756,1,Cleaned_Futures_Data!$Q$2:$Q$756,">="&$B8,Cleaned_Futures_Data!$Q$2:$Q$756,"<="&$C8),"") -> 0.23318386
A9: 1–5 days | B9: 1 | C9: 5 | D9: =COUNTIFS(Cleaned_Futures_Data!$W$2:$W$756,1,Cleaned_Futures_Data!$Q$2:$Q$756,">="&$B9,Cleaned_Futures_Data!$Q$2:$Q$756,"<="&$C9) -> 33 | E9: =IFERROR(AVERAGEIFS(Cleaned_Futures_Data!$O$2:$O$756,Cleaned_Futures_Data!$W$2:$W$756,1,Cleaned_Futures_Data!$Q$2:$Q$756,">="&$B9,Cleaned_Futures_Data!$Q$2:$Q$756,"<="&$C9),"") -> 26.9 | F9: =IFERROR(AVERAGEIFS(Cleaned_Futures_Data!$P$2:$P$756,Cleaned_Futures_Data!$W$2:$W$756,1,Cleaned_Futures_Data!$Q$2:$Q$756,">="&$B9,Cleaned_Futures_Data!$Q$2:$Q$756,"<="&$C9),"") -> 0.0010907241 | G9: =IFERROR(AVERAGEIFS(Cleaned_Futures_Data!$X$2:$X$756,Cleaned_Futures_Data!$W$2:$W$756,1,Cleaned_Futures_Data!$Q$2:$Q$756,">="&$B9,Cleaned_Futures_Data!$Q$2:$Q$756,"<="&$C9),"") -> 0.18762342 | H9: =IFERROR(AVERAGEIFS(Cleaned_Futures_Data!$L$2:$L$756,Cleaned_Futures_Data!$W$2:$W$756,1,Cleaned_Futures_Data!$Q$2:$Q$756,">="&$B9,Cleaned_Futures_Data!$Q$2:$Q$756,"<="&$C9),"") -> 9486627.3 | I9: =IFERROR(AVERAGEIFS(Cleaned_Futures_Data!$AA$2:$AA$756,Cleaned_Futures_Data!$W$2:$W$756,1,Cleaned_Futures_Data!$Q$2:$Q$756,">="&$B9,Cleaned_Futures_Data!$Q$2:$Q$756,"<="&$C9),"") -> 8951233.6 | J9: =IFERROR(AVERAGEIFS(Cleaned_Futures_Data!$AB$2:$AB$756,Cleaned_Futures_Data!$W$2:$W$756,1,Cleaned_Futures_Data!$Q$2:$Q$756,">="&$B9,Cleaned_Futures_Data!$Q$2:$Q$756,"<="&$C9),"") -> 0.51673281
A10: 6–10 days | B10: 6 | C10: 10 | D10: =COUNTIFS(Cleaned_Futures_Data!$W$2:$W$756,1,Cleaned_Futures_Data!$Q$2:$Q$756,">="&$B10,Cleaned_Futures_Data!$Q$2:$Q$756,"<="&$C10) -> 49 | E10: =IFERROR(AVERAGEIFS(Cleaned_Futures_Data!$O$2:$O$756,Cleaned_Futures_Data!$W$2:$W$756,1,Cleaned_Futures_Data!$Q$2:$Q$756,">="&$B10,Cleaned_Futures_Data!$Q$2:$Q$756,"<="&$C10),"") -> 38.687755 | F10: =IFERROR(AVERAGEIFS(Cleaned_Futures_Data!$P$2:$P$756,Cleaned_Futures_Data!$W$2:$W$756,1,Cleaned_Futures_Data!$Q$2:$Q$756,">="&$B10,Cleaned_Futures_Data!$Q$2:$Q$756,"<="&$C10),"") -> 0.0015886367 | G10: =IFERROR(AVERAGEIFS(Cleaned_Futures_Data!$X$2:$X$756,Cleaned_Futures_Data!$W$2:$W$756,1,Cleaned_Futures_Data!$Q$2:$Q$756,">="&$B10,Cleaned_Futures_Data!$Q$2:$Q$756,"<="&$C10),"") -> 0.073096908 | H10: =IFERROR(AVERAGEIFS(Cleaned_Futures_Data!$L$2:$L$756,Cleaned_Futures_Data!$W$2:$W$756,1,Cleaned_Futures_Data!$Q$2:$Q$756,">="&$B10,Cleaned_Futures_Data!$Q$2:$Q$756,"<="&$C10),"") -> 14117129 | I10: =IFERROR(AVERAGEIFS(Cleaned_Futures_Data!$AA$2:$AA$756,Cleaned_Futures_Data!$W$2:$W$756,1,Cleaned_Futures_Data!$Q$2:$Q$756,">="&$B10,Cleaned_Futures_Data!$Q$2:$Q$756,"<="&$C10),"") -> 3889119.5 | J10: =IFERROR(AVERAGEIFS(Cleaned_Futures_Data!$AB$2:$AB$756,Cleaned_Futures_Data!$W$2:$W$756,1,Cleaned_Futures_Data!$Q$2:$Q$756,">="&$B10,Cleaned_Futures_Data!$Q$2:$Q$756,"<="&$C10),"") -> 0.78422123
A11: 11–15 days | B11: 11 | C11: 15 | D11: =COUNTIFS(Cleaned_Futures_Data!$W$2:$W$756,1,Cleaned_Futures_Data!$Q$2:$Q$756,">="&$B11,Cleaned_Futures_Data!$Q$2:$Q$756,"<="&$C11) -> 41 | E11: =IFERROR(AVERAGEIFS(Cleaned_Futures_Data!$O$2:$O$756,Cleaned_Futures_Data!$W$2:$W$756,1,Cleaned_Futures_Data!$Q$2:$Q$756,">="&$B11,Cleaned_Futures_Data!$Q$2:$Q$756,"<="&$C11),"") -> 70.434146 | F11: =IFERROR(AVERAGEIFS(Cleaned_Futures_Data!$P$2:$P$756,Cleaned_Futures_Data!$W$2:$W$756,1,Cleaned_Futures_Data!$Q$2:$Q$756,">="&$B11,Cleaned_Futures_Data!$Q$2:$Q$756,"<="&$C11),"") -> 0.002845293 | G11: =IFERROR(AVERAGEIFS(Cleaned_Futures_Data!$X$2:$X$756,Cleaned_Futures_Data!$W$2:$W$756,1,Cleaned_Futures_Data!$Q$2:$Q$756,">="&$B11,Cleaned_Futures_Data!$Q$2:$Q$756,"<="&$C11),"") -> 0.07691491 | H11: =IFERROR(AVERAGEIFS(Cleaned_Futures_Data!$L$2:$L$756,Cleaned_Futures_Data!$W$2:$W$756,1,Cleaned_Futures_Data!$Q$2:$Q$756,">="&$B11,Cleaned_Futures_Data!$Q$2:$Q$756,"<="&$C11),"") -> 15523145 | I11: =IFERROR(AVERAGEIFS(Cleaned_Futures_Data!$AA$2:$AA$756,Cleaned_Futures_Data!$W$2:$W$756,1,Cleaned_Futures_Data!$Q$2:$Q$756,">="&$B11,Cleaned_Futures_Data!$Q$2:$Q$756,"<="&$C11),"") -> 2414347.9 | J11: =IFERROR(AVERAGEIFS(Cleaned_Futures_Data!$AB$2:$AB$756,Cleaned_Futures_Data!$W$2:$W$756,1,Cleaned_Futures_Data!$Q$2:$Q$756,">="&$B11,Cleaned_Futures_Data!$Q$2:$Q$756,"<="&$C11),"") -> 0.86295531
A12: 16–20 days | B12: 16 | C12: 20 | D12: =COUNTIFS(Cleaned_Futures_Data!$W$2:$W$756,1,Cleaned_Futures_Data!$Q$2:$Q$756,">="&$B12,Cleaned_Futures_Data!$Q$2:$Q$756,"<="&$C12) -> 35 | E12: =IFERROR(AVERAGEIFS(Cleaned_Futures_Data!$O$2:$O$756,Cleaned_Futures_Data!$W$2:$W$756,1,Cleaned_Futures_Data!$Q$2:$Q$756,">="&$B12,Cleaned_Futures_Data!$Q$2:$Q$756,"<="&$C12),"") -> 82.492424 | F12: =IFERROR(AVERAGEIFS(Cleaned_Futures_Data!$P$2:$P$756,Cleaned_Futures_Data!$W$2:$W$756,1,Cleaned_Futures_Data!$Q$2:$Q$756,">="&$B12,Cleaned_Futures_Data!$Q$2:$Q$756,"<="&$C12),"") -> 0.0033622228 | G12: =IFERROR(AVERAGEIFS(Cleaned_Futures_Data!$X$2:$X$756,Cleaned_Futures_Data!$W$2:$W$756,1,Cleaned_Futures_Data!$Q$2:$Q$756,">="&$B12,Cleaned_Futures_Data!$Q$2:$Q$756,"<="&$C12),"") -> 0.067884369 | H12: =IFERROR(AVERAGEIFS(Cleaned_Futures_Data!$L$2:$L$756,Cleaned_Futures_Data!$W$2:$W$756,1,Cleaned_Futures_Data!$Q$2:$Q$756,">="&$B12,Cleaned_Futures_Data!$Q$2:$Q$756,"<="&$C12),"") -> 15449382 | I12: =IFERROR(AVERAGEIFS(Cleaned_Futures_Data!$AA$2:$AA$756,Cleaned_Futures_Data!$W$2:$W$756,1,Cleaned_Futures_Data!$Q$2:$Q$756,">="&$B12,Cleaned_Futures_Data!$Q$2:$Q$756,"<="&$C12),"") -> 2086922.9 | J12: =IFERROR(AVERAGEIFS(Cleaned_Futures_Data!$AB$2:$AB$756,Cleaned_Futures_Data!$W$2:$W$756,1,Cleaned_Futures_Data!$Q$2:$Q$756,">="&$B12,Cleaned_Futures_Data!$Q$2:$Q$756,"<="&$C12),"") -> 0.8786989
A13: 21+ days | B13: 21 | C13: 60 | D13: =COUNTIFS(Cleaned_Futures_Data!$W$2:$W$756,1,Cleaned_Futures_Data!$Q$2:$Q$756,">="&$B13,Cleaned_Futures_Data!$Q$2:$Q$756,"<="&$C13) -> 79 | E13: =IFERROR(AVERAGEIFS(Cleaned_Futures_Data!$O$2:$O$756,Cleaned_Futures_Data!$W$2:$W$756,1,Cleaned_Futures_Data!$Q$2:$Q$756,">="&$B13,Cleaned_Futures_Data!$Q$2:$Q$756,"<="&$C13),"") -> 108.64539 | F13: =IFERROR(AVERAGEIFS(Cleaned_Futures_Data!$P$2:$P$756,Cleaned_Futures_Data!$W$2:$W$756,1,Cleaned_Futures_Data!$Q$2:$Q$756,">="&$B13,Cleaned_Futures_Data!$Q$2:$Q$756,"<="&$C13),"") -> 0.0043944588 | G13: =IFERROR(AVERAGEIFS(Cleaned_Futures_Data!$X$2:$X$756,Cleaned_Futures_Data!$W$2:$W$756,1,Cleaned_Futures_Data!$Q$2:$Q$756,">="&$B13,Cleaned_Futures_Data!$Q$2:$Q$756,"<="&$C13),"") -> 0.063516408 | H13: =IFERROR(AVERAGEIFS(Cleaned_Futures_Data!$L$2:$L$756,Cleaned_Futures_Data!$W$2:$W$756,1,Cleaned_Futures_Data!$Q$2:$Q$756,">="&$B13,Cleaned_Futures_Data!$Q$2:$Q$756,"<="&$C13),"") -> 14995779 | I13: =IFERROR(AVERAGEIFS(Cleaned_Futures_Data!$AA$2:$AA$756,Cleaned_Futures_Data!$W$2:$W$756,1,Cleaned_Futures_Data!$Q$2:$Q$756,">="&$B13,Cleaned_Futures_Data!$Q$2:$Q$756,"<="&$C13),"") -> 1469833.2 | J13: =IFERROR(AVERAGEIFS(Cleaned_Futures_Data!$AB$2:$AB$756,Cleaned_Futures_Data!$W$2:$W$756,1,Cleaned_Futures_Data!$Q$2:$Q$756,">="&$B13,Cleaned_Futures_Data!$Q$2:$Q$756,"<="&$C13),"") -> 0.90931415
A14: Note: annualising very short tenors (≤5 days) is noisy because a small basis is divided by a small number of days. Near-month OI share = average of the daily ratio OI(near) ÷ [OI(near)+OI(next)].
A16: 2. Basis and liquidity by contract series
A17: Series | B17: Rank from | C17: Rank to | D17: Observations | E17: Total Contracts | F17: Share of Contracts | G17: Avg Open Interest | H17: Avg Basis (pts) | I17: Avg Basis %
A18: Near month | B18: 1 | C18: 1 | D18: =COUNTIFS(Cleaned_Futures_Data!$W$2:$W$756,">="&$B18,Cleaned_Futures_Data!$W$2:$W$756,"<="&$C18) -> 249 | E18: =SUMIFS(Cleaned_Futures_Data!$J$2:$J$756,Cleaned_Futures_Data!$W$2:$W$756,">="&$B18,Cleaned_Futures_Data!$W$2:$W$756,"<="&$C18) -> 23662694 | F18: =E18/SUM($E$18:$E$20) -> 0.79259293 | G18: =IFERROR(AVERAGEIFS(Cleaned_Futures_Data!$L$2:$L$756,Cleaned_Futures_Data!$W$2:$W$756,">="&$B18,Cleaned_Futures_Data!$W$2:$W$756,"<="&$C18),"") -> 13735084 | H18: =IFERROR(AVERAGEIFS(Cleaned_Futures_Data!$O$2:$O$756,Cleaned_Futures_Data!$W$2:$W$756,">="&$B18,Cleaned_Futures_Data!$W$2:$W$756,"<="&$C18),"") -> 68.065779 | I18: =IFERROR(AVERAGEIFS(Cleaned_Futures_Data!$P$2:$P$756,Cleaned_Futures_Data!$W$2:$W$756,">="&$B18,Cleaned_Futures_Data!$W$2:$W$756,"<="&$C18),"") -> 0.0027611099
A19: Next month | B19: 2 | C19: 2 | D19: =COUNTIFS(Cleaned_Futures_Data!$W$2:$W$756,">="&$B19,Cleaned_Futures_Data!$W$2:$W$756,"<="&$C19) -> 249 | E19: =SUMIFS(Cleaned_Futures_Data!$J$2:$J$756,Cleaned_Futures_Data!$W$2:$W$756,">="&$B19,Cleaned_Futures_Data!$W$2:$W$756,"<="&$C19) -> 5462233 | F19: =E19/SUM($E$18:$E$20) -> 0.18296003 | G19: =IFERROR(AVERAGEIFS(Cleaned_Futures_Data!$L$2:$L$756,Cleaned_Futures_Data!$W$2:$W$756,">="&$B19,Cleaned_Futures_Data!$W$2:$W$756,"<="&$C19),"") -> 3816225.2 | H19: =IFERROR(AVERAGEIFS(Cleaned_Futures_Data!$O$2:$O$756,Cleaned_Futures_Data!$W$2:$W$756,">="&$B19,Cleaned_Futures_Data!$W$2:$W$756,"<="&$C19),"") -> 202.41066 | I19: =IFERROR(AVERAGEIFS(Cleaned_Futures_Data!$P$2:$P$756,Cleaned_Futures_Data!$W$2:$W$756,">="&$B19,Cleaned_Futures_Data!$W$2:$W$756,"<="&$C19),"") -> 0.0082248888
A20: Far month (3+) | B20: 3 | C20: 99 | D20: =COUNTIFS(Cleaned_Futures_Data!$W$2:$W$756,">="&$B20,Cleaned_Futures_Data!$W$2:$W$756,"<="&$C20) -> 257 | E20: =SUMIFS(Cleaned_Futures_Data!$J$2:$J$756,Cleaned_Futures_Data!$W$2:$W$756,">="&$B20,Cleaned_Futures_Data!$W$2:$W$756,"<="&$C20) -> 729861 | F20: =E20/SUM($E$18:$E$20) -> 0.024447033 | G20: =IFERROR(AVERAGEIFS(Cleaned_Futures_Data!$L$2:$L$756,Cleaned_Futures_Data!$W$2:$W$756,">="&$B20,Cleaned_Futures_Data!$W$2:$W$756,"<="&$C20),"") -> 484823.19 | H20: =IFERROR(AVERAGEIFS(Cleaned_Futures_Data!$O$2:$O$756,Cleaned_Futures_Data!$W$2:$W$756,">="&$B20,Cleaned_Futures_Data!$W$2:$W$756,"<="&$C20),"") -> 339.94631 | I20: =IFERROR(AVERAGEIFS(Cleaned_Futures_Data!$P$2:$P$756,Cleaned_Futures_Data!$W$2:$W$756,">="&$B20,Cleaned_Futures_Data!$W$2:$W$756,"<="&$C20),"") -> 0.013813567
A21: Note: the all-series average basis on the Summary sheet blends these three tenors, so it is higher than, and not comparable with, the near-month figure. Rank counts listed expiries per date (on a few dates in Sep-2025 four or five expiries were listed).
A23: Blue = editable input (bucket bounds, rank bounds, cutoff). Everything else is formula-driven from Cleaned_Futures_Data.

Sheet OI_Interpretation_Summary
A1: Interpretation | B1: Observations | C1: Share of Records | D1: Rule (vs previous row, same contract)
A2: Short buildup (interpretation) | B2: =COUNTIF(Cleaned_Futures_Data!$U$2:$U$756,A2) -> 306 | C2: =B2/SUM($B$2:$B$7) -> 0.40529801 | D2: Price down, open interest up
A3: Long buildup (interpretation) | B3: =COUNTIF(Cleaned_Futures_Data!$U$2:$U$756,A3) -> 240 | C3: =B3/SUM($B$2:$B$7) -> 0.31788079 | D3: Price up, open interest up
A4: Short covering (interpretation) | B4: =COUNTIF(Cleaned_Futures_Data!$U$2:$U$756,A4) -> 98 | C4: =B4/SUM($B$2:$B$7) -> 0.12980132 | D4: Price up, open interest down
A5: Long unwinding (interpretation) | B5: =COUNTIF(Cleaned_Futures_Data!$U$2:$U$756,A5) -> 86 | C5: =B5/SUM($B$2:$B$7) -> 0.11390728 | D5: Price down, open interest down
A6: Not classified | B6: =COUNTIF(Cleaned_Futures_Data!$U$2:$U$756,A6) -> 24 | C6: =B6/SUM($B$2:$B$7) -> 0.031788079 | D6: No previous-day price/OI for the same contract (first observation of each expiry or a no-trade row lacking prior price/OI inputs)
A7: Neutral | B7: =COUNTIF(Cleaned_Futures_Data!$U$2:$U$756,A7) -> 1 | C7: =B7/SUM($B$2:$B$7) -> 0.0013245033 | D7: Close price unchanged vs previous day
A8: Total | B8: =SUM(B2:B7) -> 755 | C8: =SUM(C2:C7) -> 1
A10: Signal test: near-month contract, outside expiry week
A11: ="Sample: near-month rows with Days to Expiry > "&Basis_Analysis!B3&" and a next-day return available. Label = previous-day-to-today move; test = the following day's close return." -> Sample: near-month rows with Days to Expiry > 5 and a next-day return available. Label = previous-day-to-today move; test = the following day's close return.
A12: Interpretation | B12: Observations | C12: Avg Same-Day Return % | D12: Avg Next-Day Return % | E12: % of Days Next Close Higher
A13: Long buildup (interpretation) | B13: =COUNTIFS(Cleaned_Futures_Data!$U$2:$U$756,A13,Cleaned_Futures_Data!$Z$2:$Z$756,1) -> 25 | C13: =IFERROR(AVERAGEIFS(Cleaned_Futures_Data!$R$2:$R$756,Cleaned_Futures_Data!$U$2:$U$756,A13,Cleaned_Futures_Data!$Z$2:$Z$756,1),"") -> 0.7358829 | D13: =IFERROR(AVERAGEIFS(Cleaned_Futures_Data!$Y$2:$Y$756,Cleaned_Futures_Data!$U$2:$U$756,A13,Cleaned_Futures_Data!$Z$2:$Z$756,1),"") -> -0.18062637 | E13: =IFERROR(COUNTIFS(Cleaned_Futures_Data!$U$2:$U$756,A13,Cleaned_Futures_Data!$Z$2:$Z$756,1,Cleaned_Futures_Data!$Y$2:$Y$756,">0")/B13,"") -> 0.4
A14: Short buildup (interpretation) | B14: =COUNTIFS(Cleaned_Futures_Data!$U$2:$U$756,A14,Cleaned_Futures_Data!$Z$2:$Z$756,1) -> 54 | C14: =IFERROR(AVERAGEIFS(Cleaned_Futures_Data!$R$2:$R$756,Cleaned_Futures_Data!$U$2:$U$756,A14,Cleaned_Futures_Data!$Z$2:$Z$756,1),"") -> -0.57897397 | D14: =IFERROR(AVERAGEIFS(Cleaned_Futures_Data!$Y$2:$Y$756,Cleaned_Futures_Data!$U$2:$U$756,A14,Cleaned_Futures_Data!$Z$2:$Z$756,1),"") -> -0.022829209 | E14: =IFERROR(COUNTIFS(Cleaned_Futures_Data!$U$2:$U$756,A14,Cleaned_Futures_Data!$Z$2:$Z$756,1,Cleaned_Futures_Data!$Y$2:$Y$756,">0")/B14,"") -> 0.46296296
A15: Short covering (interpretation) | B15: =COUNTIFS(Cleaned_Futures_Data!$U$2:$U$756,A15,Cleaned_Futures_Data!$Z$2:$Z$756,1) -> 67 | C15: =IFERROR(AVERAGEIFS(Cleaned_Futures_Data!$R$2:$R$756,Cleaned_Futures_Data!$U$2:$U$756,A15,Cleaned_Futures_Data!$Z$2:$Z$756,1),"") -> 0.59783464 | D15: =IFERROR(AVERAGEIFS(Cleaned_Futures_Data!$Y$2:$Y$756,Cleaned_Futures_Data!$U$2:$U$756,A15,Cleaned_Futures_Data!$Z$2:$Z$756,1),"") -> 0.13739372 | E15: =IFERROR(COUNTIFS(Cleaned_Futures_Data!$U$2:$U$756,A15,Cleaned_Futures_Data!$Z$2:$Z$756,1,Cleaned_Futures_Data!$Y$2:$Y$756,">0")/B15,"") -> 0.50746269
A16: Long unwinding (interpretation) | B16: =COUNTIFS(Cleaned_Futures_Data!$U$2:$U$756,A16,Cleaned_Futures_Data!$Z$2:$Z$756,1) -> 55 | C16: =IFERROR(AVERAGEIFS(Cleaned_Futures_Data!$R$2:$R$756,Cleaned_Futures_Data!$U$2:$U$756,A16,Cleaned_Futures_Data!$Z$2:$Z$756,1),"") -> -0.41265761 | D16: =IFERROR(AVERAGEIFS(Cleaned_Futures_Data!$Y$2:$Y$756,Cleaned_Futures_Data!$U$2:$U$756,A16,Cleaned_Futures_Data!$Z$2:$Z$756,1),"") -> 0.019565156 | E16: =IFERROR(COUNTIFS(Cleaned_Futures_Data!$U$2:$U$756,A16,Cleaned_Futures_Data!$Z$2:$Z$756,1,Cleaned_Futures_Data!$Y$2:$Y$756,">0")/B16,"") -> 0.41818182
A17: All labelled days | B17: =COUNTIFS(Cleaned_Futures_Data!$U$2:$U$756,"<>Not classified",Cleaned_Futures_Data!$U$2:$U$756,"<>Neutral",Cleaned_Futures_Data!$Z$2:$Z$756,1) -> 201 | C17: =IFERROR(AVERAGEIFS(Cleaned_Futures_Data!$R$2:$R$756,Cleaned_Futures_Data!$U$2:$U$756,"<>Not classified",Cleaned_Futures_Data!$U$2:$U$756,"<>Neutral",Cleaned_Futures_Data!$Z$2:$Z$756,1),"") -> 0.022344429 | D17: =IFERROR(AVERAGEIFS(Cleaned_Futures_Data!$Y$2:$Y$756,Cleaned_Futures_Data!$U$2:$U$756,"<>Not classified",Cleaned_Futures_Data!$U$2:$U$756,"<>Neutral",Cleaned_Futures_Data!$Z$2:$Z$756,1),"") -> 0.02255237 | E17: =IFERROR(COUNTIFS(Cleaned_Futures_Data!$U$2:$U$756,"<>Not classified",Cleaned_Futures_Data!$U$2:$U$756,"<>Neutral",Cleaned_Futures_Data!$Z$2:$Z$756,1,Cleaned_Futures_Data!$Y$2:$Y$756,">0")/B17,"") -> 0.45771144
A19: Expiry-week effect (near-month, classified rows with Days to Expiry ≤ cutoff)
A20: Classified near-month rows in expiry week | B20: =COUNTIFS(Cleaned_Futures_Data!$W$2:$W$756,1,Cleaned_Futures_Data!$Q$2:$Q$756,"<="&Basis_Analysis!B3,Cleaned_Futures_Data!$U$2:$U$756,"<>Not classified") -> 45
A21: …of which Long unwinding or Short covering (OI falling) | B21: =COUNTIFS(Cleaned_Futures_Data!$W$2:$W$756,1,Cleaned_Futures_Data!$Q$2:$Q$756,"<="&Basis_Analysis!B3,Cleaned_Futures_Data!$U$2:$U$756,"Long unwinding (interpretation)")+COUNTIFS(Cleaned_Futures_Data!$W$2:$W$756,1,Cleaned_Futures_Data!$Q$2:$Q$756,"<="&Basis_Analysis!B3,Cleaned_Futures_Data!$U$2:$U$756,"Short covering (interpretation)") -> 45
A22: Share | B22: =IFERROR(B21/B20,"") -> 1
A24: Reading: with only tens of observations per label, and next-day "up" rates near a coin flip, these labels describe what happened on the day; they are not evidence of a tradable edge. No costs, slippage or out-of-sample test were applied.

Sheet Conclusion
A1: Conclusion
A2: NIFTY 50 Equity Derivatives – Futures Analysis 2025 | Prepared by Tushar Varkhede (MBA)
A4: Answers to the key questions
A5: Where does trading concentrate? | B5: ="In the front contract: "&TEXT(Basis_Analysis!F18,"0.0%")&" of contracts traded, against "&TEXT(Basis_Analysis!F19,"0.0%")&" for next month and "&TEXT(Basis_Analysis!F20,"0.0%")&" for far month." -> In the front contract: 79.3% of contracts traded, against 18.3% for next month and 2.4% for far month.
A6: How does basis behave? | B6: ="It follows cost of carry: larger for longer tenors, narrowing steadily into expiry, and about "&TEXT(Basis_Analysis!B4,"0.0%")&" annualised for near-month contracts. Near-month basis averaged about "&TEXT(AVERAGE(Monthly_Summary!I2:I9),"0")&" points in Jan–Aug and "&TEXT(AVERAGE(Monthly_Summary!I10:I13),"0")&" points in Sep–Dec; the data alone cannot explain that shift." -> It follows cost of carry: larger for longer tenors, narrowing steadily into expiry, and about 6.9% annualised for near-month contracts. Near-month basis averaged about 58 points in Jan–Aug and 88 points in Sep–Dec; the data alone cannot explain that shift.
A7: How does open interest roll? | B7: ="On a regular cycle, mostly in the final week before expiry: the near-month share of near+next open interest is "&TEXT(Basis_Analysis!J13,"0%")&" at 21+ days, "&TEXT(Basis_Analysis!J10,"0%")&" at 6–10 days and "&TEXT(Basis_Analysis!J8,"0%")&" on expiry day." -> On a regular cycle, mostly in the final week before expiry: the near-month share of near+next open interest is 91% at 21+ days, 78% at 6–10 days and 23% on expiry day.
A8: Do price–OI labels predict? | B8: ="Not reliably. Next-day close was higher after "&TEXT(MIN(OI_Interpretation_Summary!E13:E16),"0%")&" to "&TEXT(MAX(OI_Interpretation_Summary!E13:E16),"0%")&" of labelled days (all labels: "&TEXT(OI_Interpretation_Summary!E17,"0%")&"), on "&TEXT(MIN(OI_Interpretation_Summary!B13:B16),"0")&" to "&TEXT(MAX(OI_Interpretation_Summary!B13:B16),"0")&" observations per label. The labels describe the day rather than forecast the next." -> Not reliably. Next-day close was higher after 40% to 51% of labelled days (all labels: 46%), on 25 to 67 observations per label. The labels describe the day rather than forecast the next.
A10: Conclusion and next steps
A11: Overall conclusion | B11: The 2025 NIFTY futures market looks orderly and consistent with textbook pricing: liquidity is concentrated in the front contract, basis converges to the index at expiry and open interest rolls forward on a regular cycle. Price–OI labels are a descriptive tool, not a trading signal.
A12: Limitations | B12: One year of data; futures only; implied carry is not benchmarked against interest rates or dividends; no transaction costs; the source file was not reconciled to NSE; label tests rest on small samples.
A13: Suggested next steps | B13: (1) Add interest-rate and dividend data to test whether futures were fairly priced. (2) Extend the study to more years. (3) Add options data, for example a put–call ratio, alongside futures open interest.

Sheet NearMonth_Daily
A1: Date | B1: Near-Month Expiry | C1: Days to Expiry | D1: Futures Close | E1: Underlying | F1: Basis (pts) | G1: Near-Month Contracts | H1: Near-Month OI | I1: All-Series Contracts | K1: One row per trading date (dates listed as keys); every other column is a formula on Cleaned_Futures_Data. Near month = earliest listed expiry on that date. Underlying is blank on dates where the source file has no index value.
A2: 45658 | B2: =_xlfn.MINIFS(Cleaned_Futures_Data!$C$2:$C$756,Cleaned_Futures_Data!$B$2:$B$756,A2) -> 45687 | C2: =B2-A2 -> 29 | D2: =IFERROR(AVERAGEIFS(Cleaned_Futures_Data!$G$2:$G$756,Cleaned_Futures_Data!$B$2:$B$756,A2,Cleaned_Futures_Data!$W$2:$W$756,1),"") -> 23897.85 | E2: =IFERROR(AVERAGEIFS(Cleaned_Futures_Data!$N$2:$N$756,Cleaned_Futures_Data!$B$2:$B$756,A2,Cleaned_Futures_Data!$W$2:$W$756,1),"") -> 23742.9 | F2: =IF(AND(ISNUMBER(D2),ISNUMBER(E2)),D2-E2,"") -> 154.95 | G2: =SUMIFS(Cleaned_Futures_Data!$J$2:$J$756,Cleaned_Futures_Data!$B$2:$B$756,A2,Cleaned_Futures_Data!$W$2:$W$756,1) -> 175729 | H2: =SUMIFS(Cleaned_Futures_Data!$L$2:$L$756,Cleaned_Futures_Data!$B$2:$B$756,A2,Cleaned_Futures_Data!$W$2:$W$756,1) -> 13270450 | I2: =SUMIFS(Cleaned_Futures_Data!$J$2:$J$756,Cleaned_Futures_Data!$B$2:$B$756,A2) -> 179798
A3: 45659 | B3: =_xlfn.MINIFS(Cleaned_Futures_Data!$C$2:$C$756,Cleaned_Futures_Data!$B$2:$B$756,A3) -> 45687 | C3: =B3-A3 -> 28 | D3: =IFERROR(AVERAGEIFS(Cleaned_Futures_Data!$G$2:$G$756,Cleaned_Futures_Data!$B$2:$B$756,A3,Cleaned_Futures_Data!$W$2:$W$756,1),"") -> 24282.65 | E3: =IFERROR(AVERAGEIFS(Cleaned_Futures_Data!$N$2:$N$756,Cleaned_Futures_Data!$B$2:$B$756,A3,Cleaned_Futures_Data!$W$2:$W$756,1),"") -> 24188.65 | F3: =IF(AND(ISNUMBER(D3),ISNUMBER(E3)),D3-E3,"") -> 94 | G3: =SUMIFS(Cleaned_Futures_Data!$J$2:$J$756,Cleaned_Futures_Data!$B$2:$B$756,A3,Cleaned_Futures_Data!$W$2:$W$756,1) -> 339021 | H3: =SUMIFS(Cleaned_Futures_Data!$L$2:$L$756,Cleaned_Futures_Data!$B$2:$B$756,A3,Cleaned_Futures_Data!$W$2:$W$756,1) -> 12424650 | I3: =SUMIFS(Cleaned_Futures_Data!$J$2:$J$756,Cleaned_Futures_Data!$B$2:$B$756,A3) -> 348685
A4: 45660 | B4: =_xlfn.MINIFS(Cleaned_Futures_Data!$C$2:$C$756,Cleaned_Futures_Data!$B$2:$B$756,A4) -> 45687 | C4: =B4-A4 -> 27 | D4: =IFERROR(AVERAGEIFS(Cleaned_Futures_Data!$G$2:$G$756,Cleaned_Futures_Data!$B$2:$B$756,A4,Cleaned_Futures_Data!$W$2:$W$756,1),"") -> 24092.4 | E4: =IFERROR(AVERAGEIFS(Cleaned_Futures_Data!$N$2:$N$756,Cleaned_Futures_Data!$B$2:$B$756,A4,Cleaned_Futures_Data!$W$2:$W$756,1),"") -> 24004.75 | F4: =IF(AND(ISNUMBER(D4),ISNUMBER(E4)),D4-E4,"") -> 87.65 | G4: =SUMIFS(Cleaned_Futures_Data!$J$2:$J$756,Cleaned_Futures_Data!$B$2:$B$756,A4,Cleaned_Futures_Data!$W$2:$W$756,1) -> 262004 | H4: =SUMIFS(Cleaned_Futures_Data!$L$2:$L$756,Cleaned_Futures_Data!$B$2:$B$756,A4,Cleaned_Futures_Data!$W$2:$W$756,1) -> 12608625 | I4: =SUMIFS(Cleaned_Futures_Data!$J$2:$J$756,Cleaned_Futures_Data!$B$2:$B$756,A4) -> 269783
A5: 45663 | B5: =_xlfn.MINIFS(Cleaned_Futures_Data!$C$2:$C$756,Cleaned_Futures_Data!$B$2:$B$756,A5) -> 45687 | C5: =B5-A5 -> 24 | D5: =IFERROR(AVERAGEIFS(Cleaned_Futures_Data!$G$2:$G$756,Cleaned_Futures_Data!$B$2:$B$756,A5,Cleaned_Futures_Data!$W$2:$W$756,1),"") -> 23721.05 | E5: =IFERROR(AVERAGEIFS(Cleaned_Futures_Data!$N$2:$N$756,Cleaned_Futures_Data!$B$2:$B$756,A5,Cleaned_Futures_Data!$W$2:$W$756,1),"") -> 23616.05 | F5: =IF(AND(ISNUMBER(D5),ISNUMBER(E5)),D5-E5,"") -> 105 | G5: =SUMIFS(Cleaned_Futures_Data!$J$2:$J$756,Cleaned_Futures_Data!$B$2:$B$756,A5,Cleaned_Futures_Data!$W$2:$W$756,1) -> 381394 | H5: =SUMIFS(Cleaned_Futures_Data!$L$2:$L$756,Cleaned_Futures_Data!$B$2:$B$756,A5,Cleaned_Futures_Data!$W$2:$W$756,1) -> 12439200 | I5: =SUMIFS(Cleaned_Futures_Data!$J$2:$J$756,Cleaned_Futures_Data!$B$2:$B$756,A5) -> 394700
A6: 45664 | B6: =_xlfn.MINIFS(Cleaned_Futures_Data!$C$2:$C$756,Cleaned_Futures_Data!$B$2:$B$756,A6) -> 45687 | C6: =B6-A6 -> 23 | D6: =IFERROR(AVERAGEIFS(Cleaned_Futures_Data!$G$2:$G$756,Cleaned_Futures_Data!$B$2:$B$756,A6,Cleaned_Futures_Data!$W$2:$W$756,1),"") -> 23795.05 | E6: =IFERROR(AVERAGEIFS(Cleaned_Futures_Data!$N$2:$N$756,Cleaned_Futures_Data!$B$2:$B$756,A6,Cleaned_Futures_Data!$W$2:$W$756,1),"") -> 23707.9 | F6: =IF(AND(ISNUMBER(D6),ISNUMBER(E6)),D6-E6,"") -> 87.15 | G6: =SUMIFS(Cleaned_Futures_Data!$J$2:$J$756,Cleaned_Futures_Data!$B$2:$B$756,A6,Cleaned_Futures_Data!$W$2:$W$756,1) -> 170033 | H6: =SUMIFS(Cleaned_Futures_Data!$L$2:$L$756,Cleaned_Futures_Data!$B$2:$B$756,A6,Cleaned_Futures_Data!$W$2:$W$756,1) -> 12651100 | I6: =SUMIFS(Cleaned_Futures_Data!$J$2:$J$756,Cleaned_Futures_Data!$B$2:$B$756,A6) -> 177038
A7: 45665 | B7: =_xlfn.MINIFS(Cleaned_Futures_Data!$C$2:$C$756,Cleaned_Futures_Data!$B$2:$B$756,A7) -> 45687 | C7: =B7-A7 -> 22 | D7: =IFERROR(AVERAGEIFS(Cleaned_Futures_Data!$G$2:$G$756,Cleaned_Futures_Data!$B$2:$B$756,A7,Cleaned_Futures_Data!$W$2:$W$756,1),"") -> 23781.35 | E7: =IFERROR(AVERAGEIFS(Cleaned_Futures_Data!$N$2:$N$756,Cleaned_Futures_Data!$B$2:$B$756,A7,Cleaned_Futures_Data!$W$2:$W$756,1),"") -> 23688.95 | F7: =IF(AND(ISNUMBER(D7),ISNUMBER(E7)),D7-E7,"") -> 92.4 | G7: =SUMIFS(Cleaned_Futures_Data!$J$2:$J$756,Cleaned_Futures_Data!$B$2:$B$756,A7,Cleaned_Futures_Data!$W$2:$W$756,1) -> 237903 | H7: =SUMIFS(Cleaned_Futures_Data!$L$2:$L$756,Cleaned_Futures_Data!$B$2:$B$756,A7,Cleaned_Futures_Data!$W$2:$W$756,1) -> 12927575 | I7: =SUMIFS(Cleaned_Futures_Data!$J$2:$J$756,Cleaned_Futures_Data!$B$2:$B$756,A7) -> 248848
A8: 45666 | B8: =_xlfn.MINIFS(Cleaned_Futures_Data!$C$2:$C$756,Cleaned_Futures_Data!$B$2:$B$756,A8) -> 45687 | C8: =B8-A8 -> 21 | D8: =IFERROR(AVERAGEIFS(Cleaned_Futures_Data!$G$2:$G$756,Cleaned_Futures_Data!$B$2:$B$756,A8,Cleaned_Futures_Data!$W$2:$W$756,1),"") -> 23648.1 | E8: =IFERROR(AVERAGEIFS(Cleaned_Futures_Data!$N$2:$N$756,Cleaned_Futures_Data!$B$2:$B$756,A8,Cleaned_Futures_Data!$W$2:$W$756,1),"") -> 23526.5 | F8: =IF(AND(ISNUMBER(D8),ISNUMBER(E8)),D8-E8,"") -> 121.6 | G8: =SUMIFS(Cleaned_Futures_Data!$J$2:$J$756,Cleaned_Futures_Data!$B$2:$B$756,A8,Cleaned_Futures_Data!$W$2:$W$756,1) -> 182951 | H8: =SUMIFS(Cleaned_Futures_Data!$L$2:$L$756,Cleaned_Futures_Data!$B$2:$B$756,A8,Cleaned_Futures_Data!$W$2:$W$756,1) -> 13641200 | I8: =SUMIFS(Cleaned_Futures_Data!$J$2:$J$756,Cleaned_Futures_Data!$B$2:$B$756,A8) -> 191468
A9: 45667 | B9: =_xlfn.MINIFS(Cleaned_Futures_Data!$C$2:$C$756,Cleaned_Futures_Data!$B$2:$B$756,A9) -> 45687 | C9: =B9-A9 -> 20 | D9: =IFERROR(AVERAGEIFS(Cleaned_Futures_Data!$G$2:$G$756,Cleaned_Futures_Data!$B$2:$B$756,A9,Cleaned_Futures_Data!$W$2:$W$756,1),"") -> 23500.65 | E9: =IFERROR(AVERAGEIFS(Cleaned_Futures_Data!$N$2:$N$756,Cleaned_Futures_Data!$B$2:$B$756,A9,Cleaned_Futures_Data!$W$2:$W$756,1),"") -> 23431.5 | F9: =IF(AND(ISNUMBER(D9),ISNUMBER(E9)),D9-E9,"") -> 69.15 | G9: =SUMIFS(Cleaned_Futures_Data!$J$2:$J$756,Cleaned_Futures_Data!$B$2:$B$756,A9,Cleaned_Futures_Data!$W$2:$W$756,1) -> 261703 | H9: =SUMIFS(Cleaned_Futures_Data!$L$2:$L$756,Cleaned_Futures_Data!$B$2:$B$756,A9,Cleaned_Futures_Data!$W$2:$W$756,1) -> 13543325 | I9: =SUMIFS(Cleaned_Futures_Data!$J$2:$J$756,Cleaned_Futures_Data!$B$2:$B$756,A9) -> 277229
A10: 45670 | B10: =_xlfn.MINIFS(Cleaned_Futures_Data!$C$2:$C$756,Cleaned_Futures_Data!$B$2:$B$756,A10) -> 45687 | C10: =B10-A10 -> 17 | D10: =IFERROR(AVERAGEIFS(Cleaned_Futures_Data!$G$2:$G$756,Cleaned_Futures_Data!$B$2:$B$756,A10,Cleaned_Futures_Data!$W$2:$W$756,1),"") -> 23162.1 | E10: =IFERROR(AVERAGEIFS(Cleaned_Futures_Data!$N$2:$N$756,Cleaned_Futures_Data!$B$2:$B$756,A10,Cleaned_Futures_Data!$W$2:$W$756,1),"") -> 23085.95 | F10: =IF(AND(ISNUMBER(D10),ISNUMBER(E10)),D10-E10,"") -> 76.15 | G10: =SUMIFS(Cleaned_Futures_Data!$J$2:$J$756,Cleaned_Futures_Data!$B$2:$B$756,A10,Cleaned_Futures_Data!$W$2:$W$756,1) -> 278782 | H10: =SUMIFS(Cleaned_Futures_Data!$L$2:$L$756,Cleaned_Futures_Data!$B$2:$B$756,A10,Cleaned_Futures_Data!$W$2:$W$756,1) -> 13866925 | I10: =SUMIFS(Cleaned_Futures_Data!$J$2:$J$756,Cleaned_Futures_Data!$B$2:$B$756,A10) -> 297053
A11: 45671 | B11: =_xlfn.MINIFS(Cleaned_Futures_Data!$C$2:$C$756,Cleaned_Futures_Data!$B$2:$B$756,A11) -> 45687 | C11: =B11-A11 -> 16 | D11: =IFERROR(AVERAGEIFS(Cleaned_Futures_Data!$G$2:$G$756,Cleaned_Futures_Data!$B$2:$B$756,A11,Cleaned_Futures_Data!$W$2:$W$756,1),"") -> 23271.75 | E11: =IFERROR(AVERAGEIFS(Cleaned_Futures_Data!$N$2:$N$756,Cleaned_Futures_Data!$B$2:$B$756,A11,Cleaned_Futures_Data!$W$2:$W$756,1),"") -> 23176.05 | F11: =IF(AND(ISNUMBER(D11),ISNUMBER(E11)),D11-E11,"") -> 95.7 | G11: =SUMIFS(Cleaned_Futures_Data!$J$2:$J$756,Cleaned_Futures_Data!$B$2:$B$756,A11,Cleaned_Futures_Data!$W$2:$W$756,1) -> 194699 | H11: =SUMIFS(Cleaned_Futures_Data!$L$2:$L$756,Cleaned_Futures_Data!$B$2:$B$756,A11,Cleaned_Futures_Data!$W$2:$W$756,1) -> 13753850 | I11: =SUMIFS(Cleaned_Futures_Data!$J$2:$J$756,Cleaned_Futures_Data!$B$2:$B$756,A11) -> 207552
A12: 45672 | B12: =_xlfn.MINIFS(Cleaned_Futures_Data!$C$2:$C$756,Cleaned_Futures_Data!$B$2:$B$756,A12) -> 45687 | C12: =B12-A12 -> 15 | D12: =IFERROR(AVERAGEIFS(Cleaned_Futures_Data!$G$2:$G$756,Cleaned_Futures_Data!$B$2:$B$756,A12,Cleaned_Futures_Data!$W$2:$W$756,1),"") -> 23265.9 | E12: =IFERROR(AVERAGEIFS(Cleaned_Futures_Data!$N$2:$N$756,Cleaned_Futures_Data!$B$2:$B$756,A12,Cleaned_Futures_Data!$W$2:$W$756,1),"") -> 23213.2 | F12: =IF(AND(ISNUMBER(D12),ISNUMBER(E12)),D12-E12,"") -> 52.7 | G12: =SUMIFS(Cleaned_Futures_Data!$J$2:$J$756,Cleaned_Futures_Data!$B$2:$B$756,A12,Cleaned_Futures_Data!$W$2:$W$756,1) -> 143790 | H12: =SUMIFS(Cleaned_Futures_Data!$L$2:$L$756,Cleaned_Futures_Data!$B$2:$B$756,A12,Cleaned_Futures_Data!$W$2:$W$756,1) -> 13536300 | I12: =SUMIFS(Cleaned_Futures_Data!$J$2:$J$756,Cleaned_Futures_Data!$B$2:$B$756,A12) -> 150371
A13: 45673 | B13: =_xlfn.MINIFS(Cleaned_Futures_Data!$C$2:$C$756,Cleaned_Futures_Data!$B$2:$B$756,A13) -> 45687 | C13: =B13-A13 -> 14 | D13: =IFERROR(AVERAGEIFS(Cleaned_Futures_Data!$G$2:$G$756,Cleaned_Futures_Data!$B$2:$B$756,A13,Cleaned_Futures_Data!$W$2:$W$756,1),"") -> 23377.55 | E13: =IFERROR(AVERAGEIFS(Cleaned_Futures_Data!$N$2:$N$756,Cleaned_Futures_Data!$B$2:$B$756,A13,Cleaned_Futures_Data!$W$2:$W$756,1),"") -> 23311.8 | F13: =IF(AND(ISNUMBER(D13),ISNUMBER(E13)),D13-E13,"") -> 65.75 | G13: =SUMIFS(Cleaned_Futures_Data!$J$2:$J$756,Cleaned_Futures_Data!$B$2:$B$756,A13,Cleaned_Futures_Data!$W$2:$W$756,1) -> 171198 | H13: =SUMIFS(Cleaned_Futures_Data!$L$2:$L$756,Cleaned_Futures_Data!$B$2:$B$756,A13,Cleaned_Futures_Data!$W$2:$W$756,1) -> 13500850 | I13: =SUMIFS(Cleaned_Futures_Data!$J$2:$J$756,Cleaned_Futures_Data!$B$2:$B$756,A13) -> 181490
... A250: 46022 | B250: =_xlfn.MINIFS(Cleaned_Futures_Data!$C$2:$C$756,Cleaned_Futures_Data!$B$2:$B$756,A250) -> 46049 | C250: =B250-A250 -> 27 | D250: =IFERROR(AVERAGEIFS(Cleaned_Futures_Data!$G$2:$G$756,Cleaned_Futures_Data!$B$2:$B$756,A250,Cleaned_Futures_Data!$W$2:$W$756,1),"") -> 26296.3 | E250: =IFERROR(AVERAGEIFS(Cleaned_Futures_Data!$N$2:$N$756,Cleaned_Futures_Data!$B$2:$B$756,A250,Cleaned_Futures_Data!$W$2:$W$756,1),"") -> 26129.6 | F250: =IF(AND(ISNUMBER(D250),ISNUMBER(E250)),D250-E250,"") -> 166.7 | G250: =SUMIFS(Cleaned_Futures_Data!$J$2:$J$756,Cleaned_Futures_Data!$B$2:$B$756,A250,Cleaned_Futures_Data!$W$2:$W$756,1) -> 72942 | H250: =SUMIFS(Cleaned_Futures_Data!$L$2:$L$756,Cleaned_Futures_Data!$B$2:$B$756,A250,Cleaned_Futures_Data!$W$2:$W$756,1) -> 14026480 | I250: =SUMIFS(Cleaned_Futures_Data!$J$2:$J$756,Cleaned_Futures_Data!$B$2:$B$756,A250) -> 80592

Sheet Cleaned_Futures_Data
A1: Symbol | B1: Date | C1: Expiry | D1: Open | E1: High | F1: Low | G1: Close | H1: LTP | I1: Settle Price | J1: No. of contracts | K1: Turnover * in ₹ Lakhs | L1: Open Int | M1: Change in OI | N1: Underlying Value | O1: Basis | P1: Basis % | Q1: Days to Expiry | R1: Close Return % | S1: OI Change % | T1: Price Change | U1: OI Interpretation | V1: Month | W1: Series Rank (1=near) | X1: Annualised Basis % | Y1: Next-Day Return % | Z1: Signal Sample (1/0) | AA1: Next-Series OI | AB1: Near-Month OI Share
A2: NIFTY | B2: 45658 | C2: 45687 | D2: 23500 | E2: 23964 | F2: 23500 | G2: 23897.85 | H2: 23907 | I2: 23897.85 | J2: 175729 | K2: 1047986.8 | L2: 13270450 | M2: -20750 | N2: 23742.9 | O2: =IF(AND(ISNUMBER(G2),ISNUMBER(N2)),G2-N2,"") -> 154.95 | P2: =IF(ISNUMBER(O2),O2/N2,"") -> 0.0065261615 | Q2: =C2-B2 -> 29 | R2: =IF(AND(C2=C1,ISNUMBER(G2),ISNUMBER(G1)),(G2/G1-1)*100,"") | S2: =IF(AND(C2=C1,ISNUMBER(L2),ISNUMBER(L1)),(L2/L1-1)*100,"") | T2: =IF(AND(C2=C1,ISNUMBER(G2),ISNUMBER(G1)),G2-G1,"") | U2: =IF(OR(NOT(ISNUMBER(R2)),NOT(ISNUMBER(S2))),"Not classified",IF(AND(R2>0,S2>0),"Long buildup (interpretation)",IF(AND(R2<0,S2>0),"Short buildup (interpretation)",IF(AND(R2>0,S2<0),"Short covering (interpretation)",IF(AND(R2<0,S2<0),"Long unwinding (interpretation)","Neutral"))))) -> Not classified | V2: =TEXT(B2,"yyyy-mm") -> 2025-01 | W2: =1+COUNTIFS($B$2:$B$756,B2,$C$2:$C$756,"<"&C2) -> 1 | X2: =IF(AND(ISNUMBER(P2),Q2>0),P2*365/Q2,"") -> 0.082139619 | Y2: =IF(AND(C3=C2,ISNUMBER(R3)),R3,"") -> 1.6101867 | Z2: =IF(AND(W2=1,Q2>Basis_Analysis!$B$3,ISNUMBER(Y2)),1,0) -> 1 | AA2: =IF(W2=1,IF(SUMIFS($L$2:$L$756,$B$2:$B$756,B2,$W$2:$W$756,2)>0,SUMIFS($L$2:$L$756,$B$2:$B$756,B2,$W$2:$W$756,2),""),"") -> 1045725 | AB2: =IF(AND(W2=1,ISNUMBER(AA2)),L2/(L2+AA2),"") -> 0.926955
A3: NIFTY | B3: 45659 | C3: 45687 | D3: 23911 | E3: 24314 | F3: 23863.1 | G3: 24282.65 | H3: 24270.1 | I3: 24282.65 | J3: 339021 | K3: 2044991.5 | L3: 12424650 | M3: -845800 | N3: 24188.65 | O3: =IF(AND(ISNUMBER(G3),ISNUMBER(N3)),G3-N3,"") -> 94 | P3: =IF(ISNUMBER(O3),O3/N3,"") -> 0.0038861201 | Q3: =C3-B3 -> 28 | R3: =IF(AND(C3=C2,ISNUMBER(G3),ISNUMBER(G2)),(G3/G2-1)*100,"") -> 1.6101867 | S3: =IF(AND(C3=C2,ISNUMBER(L3),ISNUMBER(L2)),(L3/L2-1)*100,"") -> -6.3735593 | T3: =IF(AND(C3=C2,ISNUMBER(G3),ISNUMBER(G2)),G3-G2,"") -> 384.8 | U3: =IF(OR(NOT(ISNUMBER(R3)),NOT(ISNUMBER(S3))),"Not classified",IF(AND(R3>0,S3>0),"Long buildup (interpretation)",IF(AND(R3<0,S3>0),"Short buildup (interpretation)",IF(AND(R3>0,S3<0),"Short covering (interpretation)",IF(AND(R3<0,S3<0),"Long unwinding (interpretation)","Neutral"))))) -> Short covering (interpretation) | V3: =TEXT(B3,"yyyy-mm") -> 2025-01 | W3: =1+COUNTIFS($B$2:$B$756,B3,$C$2:$C$756,"<"&C3) -> 1 | X3: =IF(AND(ISNUMBER(P3),Q3>0),P3*365/Q3,"") -> 0.050658352 | Y3: =IF(AND(C4=C3,ISNUMBER(R4)),R4,"") -> -0.78348121 | Z3: =IF(AND(W3=1,Q3>Basis_Analysis!$B$3,ISNUMBER(Y3)),1,0) -> 1 | AA3: =IF(W3=1,IF(SUMIFS($L$2:$L$756,$B$2:$B$756,B3,$W$2:$W$756,2)>0,SUMIFS($L$2:$L$756,$B$2:$B$756,B3,$W$2:$W$756,2),""),"") -> 1093575 | AB3: =IF(AND(W3=1,ISNUMBER(AA3)),L3/(L3+AA3),"") -> 0.91910365
A4: NIFTY | B4: 45660 | C4: 45687 | D4: 24240 | E4: 24268.95 | F4: 24071.4 | G4: 24092.4 | H4: 24074.8 | I4: 24092.4 | J4: 262004 | K4: 1582146.6 | L4: 12608625 | M4: 183975 | N4: 24004.75 | O4: =IF(AND(ISNUMBER(G4),ISNUMBER(N4)),G4-N4,"") -> 87.65 | P4: =IF(ISNUMBER(O4),O4/N4,"") -> 0.0036513607 | Q4: =C4-B4 -> 27 | R4: =IF(AND(C4=C3,ISNUMBER(G4),ISNUMBER(G3)),(G4/G3-1)*100,"") -> -0.78348121 | S4: =IF(AND(C4=C3,ISNUMBER(L4),ISNUMBER(L3)),(L4/L3-1)*100,"") -> 1.4807258 | T4: =IF(AND(C4=C3,ISNUMBER(G4),ISNUMBER(G3)),G4-G3,"") -> -190.25 | U4: =IF(OR(NOT(ISNUMBER(R4)),NOT(ISNUMBER(S4))),"Not classified",IF(AND(R4>0,S4>0),"Long buildup (interpretation)",IF(AND(R4<0,S4>0),"Short buildup (interpretation)",IF(AND(R4>0,S4<0),"Short covering (interpretation)",IF(AND(R4<0,S4<0),"Long unwinding (interpretation)","Neutral"))))) -> Short buildup (interpretation) | V4: =TEXT(B4,"yyyy-mm") -> 2025-01 | W4: =1+COUNTIFS($B$2:$B$756,B4,$C$2:$C$756,"<"&C4) -> 1 | X4: =IF(AND(ISNUMBER(P4),Q4>0),P4*365/Q4,"") -> 0.049360987 | Y4: =IF(AND(C5=C4,ISNUMBER(R5)),R5,"") -> -1.5413574 | Z4: =IF(AND(W4=1,Q4>Basis_Analysis!$B$3,ISNUMBER(Y4)),1,0) -> 1 | AA4: =IF(W4=1,IF(SUMIFS($L$2:$L$756,$B$2:$B$756,B4,$W$2:$W$756,2)>0,SUMIFS($L$2:$L$756,$B$2:$B$756,B4,$W$2:$W$756,2),""),"") -> 1084650 | AB4: =IF(AND(W4=1,ISNUMBER(AA4)),L4/(L4+AA4),"") -> 0.92078958
A5: NIFTY | B5: 45663 | C5: 45687 | D5: 24145.1 | E5: 24150 | F5: 23660 | G5: 23721.05 | H5: 23730 | I5: 23721.05 | J5: 381394 | K5: 2275385.4 | L5: 12439200 | M5: -169425 | N5: 23616.05 | O5: =IF(AND(ISNUMBER(G5),ISNUMBER(N5)),G5-N5,"") -> 105 | P5: =IF(ISNUMBER(O5),O5/N5,"") -> 0.0044461288 | Q5: =C5-B5 -> 24 | R5: =IF(AND(C5=C4,ISNUMBER(G5),ISNUMBER(G4)),(G5/G4-1)*100,"") -> -1.5413574 | S5: =IF(AND(C5=C4,ISNUMBER(L5),ISNUMBER(L4)),(L5/L4-1)*100,"") -> -1.343723 | T5: =IF(AND(C5=C4,ISNUMBER(G5),ISNUMBER(G4)),G5-G4,"") -> -371.35 | U5: =IF(OR(NOT(ISNUMBER(R5)),NOT(ISNUMBER(S5))),"Not classified",IF(AND(R5>0,S5>0),"Long buildup (interpretation)",IF(AND(R5<0,S5>0),"Short buildup (interpretation)",IF(AND(R5>0,S5<0),"Short covering (interpretation)",IF(AND(R5<0,S5<0),"Long unwinding (interpretation)","Neutral"))))) -> Long unwinding (interpretation) | V5: =TEXT(B5,"yyyy-mm") -> 2025-01 | W5: =1+COUNTIFS($B$2:$B$756,B5,$C$2:$C$756,"<"&C5) -> 1 | X5: =IF(AND(ISNUMBER(P5),Q5>0),P5*365/Q5,"") -> 0.067618209 | Y5: =IF(AND(C6=C5,ISNUMBER(R6)),R6,"") -> 0.31195921 | Z5: =IF(AND(W5=1,Q5>Basis_Analysis!$B$3,ISNUMBER(Y5)),1,0) -> 1 | AA5: =IF(W5=1,IF(SUMIFS($L$2:$L$756,$B$2:$B$756,B5,$W$2:$W$756,2)>0,SUMIFS($L$2:$L$756,$B$2:$B$756,B5,$W$2:$W$756,2),""),"") -> 1062075 | AB5: =IF(AND(W5=1,ISNUMBER(AA5)),L5/(L5+AA5),"") -> 0.92133521
A6: NIFTY | B6: 45664 | C6: 45687 | D6: 23800.2 | E6: 23890 | F6: 23738.75 | G6: 23795.05 | H6: 23785.45 | I6: 23795.05 | J6: 170033 | K6: 1012673.2 | L6: 12651100 | M6: 211900 | N6: 23707.9 | O6: =IF(AND(ISNUMBER(G6),ISNUMBER(N6)),G6-N6,"") -> 87.15 | P6: =IF(ISNUMBER(O6),O6/N6,"") -> 0.0036759899 | Q6: =C6-B6 -> 23 | R6: =IF(AND(C6=C5,ISNUMBER(G6),ISNUMBER(G5)),(G6/G5-1)*100,"") -> 0.31195921 | S6: =IF(AND(C6=C5,ISNUMBER(L6),ISNUMBER(L5)),(L6/L5-1)*100,"") -> 1.7034858 | T6: =IF(AND(C6=C5,ISNUMBER(G6),ISNUMBER(G5)),G6-G5,"") -> 74 | U6: =IF(OR(NOT(ISNUMBER(R6)),NOT(ISNUMBER(S6))),"Not classified",IF(AND(R6>0,S6>0),"Long buildup (interpretation)",IF(AND(R6<0,S6>0),"Short buildup (interpretation)",IF(AND(R6>0,S6<0),"Short covering (interpretation)",IF(AND(R6<0,S6<0),"Long unwinding (interpretation)","Neutral"))))) -> Long buildup (interpretation) | V6: =TEXT(B6,"yyyy-mm") -> 2025-01 | W6: =1+COUNTIFS($B$2:$B$756,B6,$C$2:$C$756,"<"&C6) -> 1 | X6: =IF(AND(ISNUMBER(P6),Q6>0),P6*365/Q6,"") -> 0.058336361 | Y6: =IF(AND(C7=C6,ISNUMBER(R7)),R7,"") -> -0.057575 | Z6: =IF(AND(W6=1,Q6>Basis_Analysis!$B$3,ISNUMBER(Y6)),1,0) -> 1 | AA6: =IF(W6=1,IF(SUMIFS($L$2:$L$756,$B$2:$B$756,B6,$W$2:$W$756,2)>0,SUMIFS($L$2:$L$756,$B$2:$B$756,B6,$W$2:$W$756,2),""),"") -> 1104225 | AB6: =IF(AND(W6=1,ISNUMBER(AA6)),L6/(L6+AA6),"") -> 0.91972382
A7: NIFTY | B7: 45665 | C7: 45687 | D7: 23800 | E7: 23839 | F7: 23593.3 | G7: 23781.35 | H7: 23776.35 | I7: 23781.35 | J7: 237903 | K7: 1411045.4 | L7: 12927575 | M7: 276475 | N7: 23688.95 | O7: =IF(AND(ISNUMBER(G7),ISNUMBER(N7)),G7-N7,"") -> 92.4 | P7: =IF(ISNUMBER(O7),O7/N7,"") -> 0.0039005528 | Q7: =C7-B7 -> 22 | R7: =IF(AND(C7=C6,ISNUMBER(G7),ISNUMBER(G6)),(G7/G6-1)*100,"") -> -0.057575 | S7: =IF(AND(C7=C6,ISNUMBER(L7),ISNUMBER(L6)),(L7/L6-1)*100,"") -> 2.1853831 | T7: =IF(AND(C7=C6,ISNUMBER(G7),ISNUMBER(G6)),G7-G6,"") -> -13.7 | U7: =IF(OR(NOT(ISNUMBER(R7)),NOT(ISNUMBER(S7))),"Not classified",IF(AND(R7>0,S7>0),"Long buildup (interpretation)",IF(AND(R7<0,S7>0),"Short buildup (interpretation)",IF(AND(R7>0,S7<0),"Short covering (interpretation)",IF(AND(R7<0,S7<0),"Long unwinding (interpretation)","Neutral"))))) -> Short buildup (interpretation) | V7: =TEXT(B7,"yyyy-mm") -> 2025-01 | W7: =1+COUNTIFS($B$2:$B$756,B7,$C$2:$C$756,"<"&C7) -> 1 | X7: =IF(AND(ISNUMBER(P7),Q7>0),P7*365/Q7,"") -> 0.064713717 | Y7: =IF(AND(C8=C7,ISNUMBER(R8)),R8,"") -> -0.56031302 | Z7: =IF(AND(W7=1,Q7>Basis_Analysis!$B$3,ISNUMBER(Y7)),1,0) -> 1 | AA7: =IF(W7=1,IF(SUMIFS($L$2:$L$756,$B$2:$B$756,B7,$W$2:$W$756,2)>0,SUMIFS($L$2:$L$756,$B$2:$B$756,B7,$W$2:$W$756,2),""),"") -> 1231575 | AB7: =IF(AND(W7=1,ISNUMBER(AA7)),L7/(L7+AA7),"") -> 0.91301914
A8: NIFTY | B8: 45666 | C8: 45687 | D8: 23759 | E8: 23759 | F8: 23612.9 | G8: 23648.1 | H8: 23671.1 | I8: 23648.1 | J8: 182951 | K8: 1082342.1 | L8: 13641200 | M8: 713625 | N8: 23526.5 | O8: =IF(AND(ISNUMBER(G8),ISNUMBER(N8)),G8-N8,"") -> 121.6 | P8: =IF(ISNUMBER(O8),O8/N8,"") -> 0.0051686396 | Q8: =C8-B8 -> 21 | R8: =IF(AND(C8=C7,ISNUMBER(G8),ISNUMBER(G7)),(G8/G7-1)*100,"") -> -0.56031302 | S8: =IF(AND(C8=C7,ISNUMBER(L8),ISNUMBER(L7)),(L8/L7-1)*100,"") -> 5.5201768 | T8: =IF(AND(C8=C7,ISNUMBER(G8),ISNUMBER(G7)),G8-G7,"") -> -133.25 | U8: =IF(OR(NOT(ISNUMBER(R8)),NOT(ISNUMBER(S8))),"Not classified",IF(AND(R8>0,S8>0),"Long buildup (interpretation)",IF(AND(R8<0,S8>0),"Short buildup (interpretation)",IF(AND(R8>0,S8<0),"Short covering (interpretation)",IF(AND(R8<0,S8<0),"Long unwinding (interpretation)","Neutral"))))) -> Short buildup (interpretation) | V8: =TEXT(B8,"yyyy-mm") -> 2025-01 | W8: =1+COUNTIFS($B$2:$B$756,B8,$C$2:$C$756,"<"&C8) -> 1 | X8: =IF(AND(ISNUMBER(P8),Q8>0),P8*365/Q8,"") -> 0.089835879 | Y8: =IF(AND(C9=C8,ISNUMBER(R9)),R9,"") -> -0.62351732 | Z8: =IF(AND(W8=1,Q8>Basis_Analysis!$B$3,ISNUMBER(Y8)),1,0) -> 1 | AA8: =IF(W8=1,IF(SUMIFS($L$2:$L$756,$B$2:$B$756,B8,$W$2:$W$756,2)>0,SUMIFS($L$2:$L$756,$B$2:$B$756,B8,$W$2:$W$756,2),""),"") -> 1442700 | AB8: =IF(AND(W8=1,ISNUMBER(AA8)),L8/(L8+AA8),"") -> 0.90435497
A9: NIFTY | B9: 45667 | C9: 45687 | D9: 23625.05 | E9: 23684.9 | F9: 23430 | G9: 23500.65 | H9: 23515 | I9: 23500.65 | J9: 261703 | K9: 1541207.8 | L9: 13543325 | M9: -97875 | N9: 23431.5 | O9: =IF(AND(ISNUMBER(G9),ISNUMBER(N9)),G9-N9,"") -> 69.15 | P9: =IF(ISNUMBER(O9),O9/N9,"") -> 0.0029511555 | Q9: =C9-B9 -> 20 | R9: =IF(AND(C9=C8,ISNUMBER(G9),ISNUMBER(G8)),(G9/G8-1)*100,"") -> -0.62351732 | S9: =IF(AND(C9=C8,ISNUMBER(L9),ISNUMBER(L8)),(L9/L8-1)*100,"") -> -0.71749553 | T9: =IF(AND(C9=C8,ISNUMBER(G9),ISNUMBER(G8)),G9-G8,"") -> -147.45 | U9: =IF(OR(NOT(ISNUMBER(R9)),NOT(ISNUMBER(S9))),"Not classified",IF(AND(R9>0,S9>0),"Long buildup (interpretation)",IF(AND(R9<0,S9>0),"Short buildup (interpretation)",IF(AND(R9>0,S9<0),"Short covering (interpretation)",IF(AND(R9<0,S9<0),"Long unwinding (interpretation)","Neutral"))))) -> Long unwinding (interpretation) | V9: =TEXT(B9,"yyyy-mm") -> 2025-01 | W9: =1+COUNTIFS($B$2:$B$756,B9,$C$2:$C$756,"<"&C9) -> 1 | X9: =IF(AND(ISNUMBER(P9),Q9>0),P9*365/Q9,"") -> 0.053858588 | Y9: =IF(AND(C10=C9,ISNUMBER(R10)),R10,"") -> -1.4405985 | Z9: =IF(AND(W9=1,Q9>Basis_Analysis!$B$3,ISNUMBER(Y9)),1,0) -> 1 | AA9: =IF(W9=1,IF(SUMIFS($L$2:$L$756,$B$2:$B$756,B9,$W$2:$W$756,2)>0,SUMIFS($L$2:$L$756,$B$2:$B$756,B9,$W$2:$W$756,2),""),"") -> 1833600 | AB9: =IF(AND(W9=1,ISNUMBER(AA9)),L9/(L9+AA9),"") -> 0.88075639
A10: NIFTY | B10: 45670 | C10: 45687 | D10: 23400 | E10: 23408.3 | F10: 23112.1 | G10: 23162.1 | H10: 23168.05 | I10: 23162.1 | J10: 278782 | K10: 1620516.1 | L10: 13866925 | M10: 323600 | N10: 23085.95 | O10: =IF(AND(ISNUMBER(G10),ISNUMBER(N10)),G10-N10,"") -> 76.15 | P10: =IF(ISNUMBER(O10),O10/N10,"") -> 0.0032985431 | Q10: =C10-B10 -> 17 | R10: =IF(AND(C10=C9,ISNUMBER(G10),ISNUMBER(G9)),(G10/G9-1)*100,"") -> -1.4405985 | S10: =IF(AND(C10=C9,ISNUMBER(L10),ISNUMBER(L9)),(L10/L9-1)*100,"") -> 2.3893689 | T10: =IF(AND(C10=C9,ISNUMBER(G10),ISNUMBER(G9)),G10-G9,"") -> -338.55 | U10: =IF(OR(NOT(ISNUMBER(R10)),NOT(ISNUMBER(S10))),"Not classified",IF(AND(R10>0,S10>0),"Long buildup (interpretation)",IF(AND(R10<0,S10>0),"Short buildup (interpretation)",IF(AND(R10>0,S10<0),"Short covering (interpretation)",IF(AND(R10<0,S10<0),"Long unwinding (interpretation)","Neutral"))))) -> Short buildup (interpretation) | V10: =TEXT(B10,"yyyy-mm") -> 2025-01 | W10: =1+COUNTIFS($B$2:$B$756,B10,$C$2:$C$756,"<"&C10) -> 1 | X10: =IF(AND(ISNUMBER(P10),Q10>0),P10*365/Q10,"") -> 0.07082166 | Y10: =IF(AND(C11=C10,ISNUMBER(R11)),R11,"") -> 0.47340267 | Z10: =IF(AND(W10=1,Q10>Basis_Analysis!$B$3,ISNUMBER(Y10)),1,0) -> 1 | AA10: =IF(W10=1,IF(SUMIFS($L$2:$L$756,$B$2:$B$756,B10,$W$2:$W$756,2)>0,SUMIFS($L$2:$L$756,$B$2:$B$756,B10,$W$2:$W$756,2),""),"") -> 2335725 | AB10: =IF(AND(W10=1,ISNUMBER(AA10)),L10/(L10+AA10),"") -> 0.85584303
A11: NIFTY | B11: 45671 | C11: 45687 | D11: 23248 | E11: 23339 | F11: 23198.45 | G11: 23271.75 | H11: 23280 | I11: 23271.75 | J11: 194699 | K11: 1132412.7 | L11: 13753850 | M11: -113075 | N11: 23176.05 | O11: =IF(AND(ISNUMBER(G11),ISNUMBER(N11)),G11-N11,"") -> 95.7 | P11: =IF(ISNUMBER(O11),O11/N11,"") -> 0.0041292628 | Q11: =C11-B11 -> 16 | R11: =IF(AND(C11=C10,ISNUMBER(G11),ISNUMBER(G10)),(G11/G10-1)*100,"") -> 0.47340267 | S11: =IF(AND(C11=C10,ISNUMBER(L11),ISNUMBER(L10)),(L11/L10-1)*100,"") -> -0.81542952 | T11: =IF(AND(C11=C10,ISNUMBER(G11),ISNUMBER(G10)),G11-G10,"") -> 109.65 | U11: =IF(OR(NOT(ISNUMBER(R11)),NOT(ISNUMBER(S11))),"Not classified",IF(AND(R11>0,S11>0),"Long buildup (interpretation)",IF(AND(R11<0,S11>0),"Short buildup (interpretation)",IF(AND(R11>0,S11<0),"Short covering (interpretation)",IF(AND(R11<0,S11<0),"Long unwinding (interpretation)","Neutral"))))) -> Short covering (interpretation) | V11: =TEXT(B11,"yyyy-mm") -> 2025-01 | W11: =1+COUNTIFS($B$2:$B$756,B11,$C$2:$C$756,"<"&C11) -> 1 | X11: =IF(AND(ISNUMBER(P11),Q11>0),P11*365/Q11,"") -> 0.094198807 | Y11: =IF(AND(C12=C11,ISNUMBER(R12)),R12,"") -> -0.025137774 | Z11: =IF(AND(W11=1,Q11>Basis_Analysis!$B$3,ISNUMBER(Y11)),1,0) -> 1 | AA11: =IF(W11=1,IF(SUMIFS($L$2:$L$756,$B$2:$B$756,B11,$W$2:$W$756,2)>0,SUMIFS($L$2:$L$756,$B$2:$B$756,B11,$W$2:$W$756,2),""),"") -> 2802150 | AB11: =IF(AND(W11=1,ISNUMBER(AA11)),L11/(L11+AA11),"") -> 0.83074716
A12: NIFTY | B12: 45672 | C12: 45687 | D12: 23302.05 | E12: 23345 | F12: 23201 | G12: 23265.9 | H12: 23275.95 | I12: 23265.9 | J12: 143790 | K12: 836498.9 | L12: 13536300 | M12: -217550 | N12: 23213.2 | O12: =IF(AND(ISNUMBER(G12),ISNUMBER(N12)),G12-N12,"") -> 52.7 | P12: =IF(ISNUMBER(O12),O12/N12,"") -> 0.00227026 | Q12: =C12-B12 -> 15 | R12: =IF(AND(C12=C11,ISNUMBER(G12),ISNUMBER(G11)),(G12/G11-1)*100,"") -> -0.025137774 | S12: =IF(AND(C12=C11,ISNUMBER(L12),ISNUMBER(L11)),(L12/L11-1)*100,"") -> -1.5817389 | T12: =IF(AND(C12=C11,ISNUMBER(G12),ISNUMBER(G11)),G12-G11,"") -> -5.85 | U12: =IF(OR(NOT(ISNUMBER(R12)),NOT(ISNUMBER(S12))),"Not classified",IF(AND(R12>0,S12>0),"Long buildup (interpretation)",IF(AND(R12<0,S12>0),"Short buildup (interpretation)",IF(AND(R12>0,S12<0),"Short covering (interpretation)",IF(AND(R12<0,S12<0),"Long unwinding (interpretation)","Neutral"))))) -> Long unwinding (interpretation) | V12: =TEXT(B12,"yyyy-mm") -> 2025-01 | W12: =1+COUNTIFS($B$2:$B$756,B12,$C$2:$C$756,"<"&C12) -> 1 | X12: =IF(AND(ISNUMBER(P12),Q12>0),P12*365/Q12,"") -> 0.055242994 | Y12: =IF(AND(C13=C12,ISNUMBER(R13)),R13,"") -> 0.47988687 | Z12: =IF(AND(W12=1,Q12>Basis_Analysis!$B$3,ISNUMBER(Y12)),1,0) -> 1 | AA12: =IF(W12=1,IF(SUMIFS($L$2:$L$756,$B$2:$B$756,B12,$W$2:$W$756,2)>0,SUMIFS($L$2:$L$756,$B$2:$B$756,B12,$W$2:$W$756,2),""),"") -> 2906625 | AB12: =IF(AND(W12=1,ISNUMBER(AA12)),L12/(L12+AA12),"") -> 0.82322944
A13: NIFTY | B13: 45673 | C13: 45687 | D13: 23406 | E13: 23423.9 | F13: 23346.15 | G13: 23377.55 | H13: 23406.9 | I13: 23377.55 | J13: 171198 | K13: 1000856.6 | L13: 13500850 | M13: -35450 | N13: 23311.8 | O13: =IF(AND(ISNUMBER(G13),ISNUMBER(N13)),G13-N13,"") -> 65.75 | P13: =IF(ISNUMBER(O13),O13/N13,"") -> 0.00282046 | Q13: =C13-B13 -> 14 | R13: =IF(AND(C13=C12,ISNUMBER(G13),ISNUMBER(G12)),(G13/G12-1)*100,"") -> 0.47988687 | S13: =IF(AND(C13=C12,ISNUMBER(L13),ISNUMBER(L12)),(L13/L12-1)*100,"") -> -0.2618884 | T13: =IF(AND(C13=C12,ISNUMBER(G13),ISNUMBER(G12)),G13-G12,"") -> 111.65 | U13: =IF(OR(NOT(ISNUMBER(R13)),NOT(ISNUMBER(S13))),"Not classified",IF(AND(R13>0,S13>0),"Long buildup (interpretation)",IF(AND(R13<0,S13>0),"Short buildup (interpretation)",IF(AND(R13>0,S13<0),"Short covering (interpretation)",IF(AND(R13<0,S13<0),"Long unwinding (interpretation)","Neutral"))))) -> Short covering (interpretation) | V13: =TEXT(B13,"yyyy-mm") -> 2025-01 | W13: =1+COUNTIFS($B$2:$B$756,B13,$C$2:$C$756,"<"&C13) -> 1 | X13: =IF(AND(ISNUMBER(P13),Q13>0),P13*365/Q13,"") -> 0.073533422 | Y13: =IF(AND(C14=C13,ISNUMBER(R14)),R14,"") -> -0.47203407 | Z13: =IF(AND(W13=1,Q13>Basis_Analysis!$B$3,ISNUMBER(Y13)),1,0) -> 1 | AA13: =IF(W13=1,IF(SUMIFS($L$2:$L$756,$B$2:$B$756,B13,$W$2:$W$756,2)>0,SUMIFS($L$2:$L$756,$B$2:$B$756,B13,$W$2:$W$756,2),""),"") -> 3265050 | AB13: =IF(AND(W13=1,ISNUMBER(AA13)),L13/(L13+AA13),"") -> 0.8052565
... A48: NIFTY | B48: 45691 | C48: 45715 | D48: 23390 | E48: 23463.25 | F48: 23305.35 | G48: 23442.75 | H48: 23440 | I48: 23442.75 | J48: 83636 | K48: 1466718.4 | L48: 17125575 | M48: -266700 | N48: 23361.05 | O48: =IF(AND(ISNUMBER(G48),ISNUMBER(N48)),G48-N48,"") -> 81.7 | P48: =IF(ISNUMBER(O48),O48/N48,"") -> 0.0034972743 | Q48: =C48-B48 -> 24 | R48: =IF(AND(C48=C47,ISNUMBER(G48),ISNUMBER(G47)),(G48/G47-1)*100,"") -> -0.47886804 | S48: =IF(AND(C48=C47,ISNUMBER(L48),ISNUMBER(L47)),(L48/L47-1)*100,"") -> -1.5334394 | T48: =IF(AND(C48=C47,ISNUMBER(G48),ISNUMBER(G47)),G48-G47,"") -> -112.8 | U48: =IF(OR(NOT(ISNUMBER(R48)),NOT(ISNUMBER(S48))),"Not classified",IF(AND(R48>0,S48>0),"Long buildup (interpretation)",IF(AND(R48<0,S48>0),"Short buildup (interpretation)",IF(AND(R48>0,S48<0),"Short covering (interpretation)",IF(AND(R48<0,S48<0),"Long unwinding (interpretation)","Neutral"))))) -> Long unwinding (interpretation) | V48: =TEXT(B48,"yyyy-mm") -> 2025-02 | W48: =1+COUNTIFS($B$2:$B$756,B48,$C$2:$C$756,"<"&C48) -> 1 | X48: =IF(AND(ISNUMBER(P48),Q48>0),P48*365/Q48,"") -> 0.053187713 | Y48: =IF(AND(C49=C48,ISNUMBER(R49)),R49,"") -> 1.4616459 | Z48: =IF(AND(W48=1,Q48>Basis_Analysis!$B$3,ISNUMBER(Y48)),1,0) -> 1 | AA48: =IF(W48=1,IF(SUMIFS($L$2:$L$756,$B$2:$B$756,B48,$W$2:$W$756,2)>0,SUMIFS($L$2:$L$756,$B$2:$B$756,B48,$W$2:$W$756,2),""),"") -> 862950 | AB48: =IF(AND(W48=1,ISNUMBER(AA48)),L48/(L48+AA48),"") -> 0.95202775
A49: NIFTY | B49: 45692 | C49: 45715 | D49: 23550 | E49: 23796.75 | F49: 23496.9 | G49: 23785.4 | H49: 23791 | I49: 23785.4 | J49: 137005 | K49: 2430569 | L49: 16697400 | M49: -428175 | O49: =IF(AND(ISNUMBER(G49),ISNUMBER(N49)),G49-N49,"") | P49: =IF(ISNUMBER(O49),O49/N49,"") | Q49: =C49-B49 -> 23 | R49: =IF(AND(C49=C48,ISNUMBER(G49),ISNUMBER(G48)),(G49/G48-1)*100,"") -> 1.4616459 | S49: =IF(AND(C49=C48,ISNUMBER(L49),ISNUMBER(L48)),(L49/L48-1)*100,"") -> -2.500208 | T49: =IF(AND(C49=C48,ISNUMBER(G49),ISNUMBER(G48)),G49-G48,"") -> 342.65 | U49: =IF(OR(NOT(ISNUMBER(R49)),NOT(ISNUMBER(S49))),"Not classified",IF(AND(R49>0,S49>0),"Long buildup (interpretation)",IF(AND(R49<0,S49>0),"Short buildup (interpretation)",IF(AND(R49>0,S49<0),"Short covering (interpretation)",IF(AND(R49<0,S49<0),"Long unwinding (interpretation)","Neutral"))))) -> Short covering (interpretation) | V49: =TEXT(B49,"yyyy-mm") -> 2025-02 | W49: =1+COUNTIFS($B$2:$B$756,B49,$C$2:$C$756,"<"&C49) -> 1 | X49: =IF(AND(ISNUMBER(P49),Q49>0),P49*365/Q49,"") | Y49: =IF(AND(C50=C49,ISNUMBER(R50)),R50,"") -> -0.053814525 | Z49: =IF(AND(W49=1,Q49>Basis_Analysis!$B$3,ISNUMBER(Y49)),1,0) -> 1 | AA49: =IF(W49=1,IF(SUMIFS($L$2:$L$756,$B$2:$B$756,B49,$W$2:$W$756,2)>0,SUMIFS($L$2:$L$756,$B$2:$B$756,B49,$W$2:$W$756,2),""),"") -> 885900 | AB49: =IF(AND(W49=1,ISNUMBER(AA49)),L49/(L49+AA49),"") -> 0.94961697
A50: NIFTY | B50: 45693 | C50: 45715 | D50: 23825 | E50: 23853.8 | F50: 23755 | G50: 23772.6 | H50: 23757 | I50: 23772.6 | J50: 51116 | K50: 912928.48 | L50: 16613175 | M50: -84225 | N50: 23696.3 | O50: =IF(AND(ISNUMBER(G50),ISNUMBER(N50)),G50-N50,"") -> 76.3 | P50: =IF(ISNUMBER(O50),O50/N50,"") -> 0.003219912 | Q50: =C50-B50 -> 22 | R50: =IF(AND(C50=C49,ISNUMBER(G50),ISNUMBER(G49)),(G50/G49-1)*100,"") -> -0.053814525 | S50: =IF(AND(C50=C49,ISNUMBER(L50),ISNUMBER(L49)),(L50/L49-1)*100,"") -> -0.50441985 | T50: =IF(AND(C50=C49,ISNUMBER(G50),ISNUMBER(G49)),G50-G49,"") -> -12.8 | U50: =IF(OR(NOT(ISNUMBER(R50)),NOT(ISNUMBER(S50))),"Not classified",IF(AND(R50>0,S50>0),"Long buildup (interpretation)",IF(AND(R50<0,S50>0),"Short buildup (interpretation)",IF(AND(R50>0,S50<0),"Short covering (interpretation)",IF(AND(R50<0,S50<0),"Long unwinding (interpretation)","Neutral"))))) -> Long unwinding (interpretation) | V50: =TEXT(B50,"yyyy-mm") -> 2025-02 | W50: =1+COUNTIFS($B$2:$B$756,B50,$C$2:$C$756,"<"&C50) -> 1 | X50: =IF(AND(ISNUMBER(P50),Q50>0),P50*365/Q50,"") -> 0.053421267 | Y50: =IF(AND(C51=C50,ISNUMBER(R51)),R51,"") -> -0.35208601 | Z50: =IF(AND(W50=1,Q50>Basis_Analysis!$B$3,ISNUMBER(Y50)),1,0) -> 1 | AA50: =IF(W50=1,IF(SUMIFS($L$2:$L$756,$B$2:$B$756,B50,$W$2:$W$756,2)>0,SUMIFS($L$2:$L$756,$B$2:$B$756,B50,$W$2:$W$756,2),""),"") -> 888975 | AB50: =IF(AND(W50=1,ISNUMBER(AA50)),L50/(L50+AA50),"") -> 0.94920767
A51: NIFTY | B51: 45694 | C51: 45715 | D51: 23822.4 | E51: 23835 | F51: 23660 | G51: 23688.9 | H51: 23706.9 | I51: 23688.9 | J51: 55302 | K51: 983344.41 | L51: 16787400 | M51: 174225 | N51: 23603.35 | O51: =IF(AND(ISNUMBER(G51),ISNUMBER(N51)),G51-N51,"") -> 85.55 | P51: =IF(ISNUMBER(O51),O51/N51,"") -> 0.0036244855 | Q51: =C51-B51 -> 21 | R51: =IF(AND(C51=C50,ISNUMBER(G51),ISNUMBER(G50)),(G51/G50-1)*100,"") -> -0.35208601 | S51: =IF(AND(C51=C50,ISNUMBER(L51),ISNUMBER(L50)),(L51/L50-1)*100,"") -> 1.0487159 | T51: =IF(AND(C51=C50,ISNUMBER(G51),ISNUMBER(G50)),G51-G50,"") -> -83.7 | U51: =IF(OR(NOT(ISNUMBER(R51)),NOT(ISNUMBER(S51))),"Not classified",IF(AND(R51>0,S51>0),"Long buildup (interpretation)",IF(AND(R51<0,S51>0),"Short buildup (interpretation)",IF(AND(R51>0,S51<0),"Short covering (interpretation)",IF(AND(R51<0,S51<0),"Long unwinding (interpretation)","Neutral"))))) -> Short buildup (interpretation) | V51: =TEXT(B51,"yyyy-mm") -> 2025-02 | W51: =1+COUNTIFS($B$2:$B$756,B51,$C$2:$C$756,"<"&C51) -> 1 | X51: =IF(AND(ISNUMBER(P51),Q51>0),P51*365/Q51,"") -> 0.06299701 | Y51: =IF(AND(C52=C51,ISNUMBER(R52)),R52,"") -> -0.31217152 | Z51: =IF(AND(W51=1,Q51>Basis_Analysis!$B$3,ISNUMBER(Y51)),1,0) -> 1 | AA51: =IF(W51=1,IF(SUMIFS($L$2:$L$756,$B$2:$B$756,B51,$W$2:$W$756,2)>0,SUMIFS($L$2:$L$756,$B$2:$B$756,B51,$W$2:$W$756,2),""),"") -> 930525 | AB51: =IF(AND(W51=1,ISNUMBER(AA51)),L51/(L51+AA51),"") -> 0.94748115
A52: NIFTY | B52: 45695 | C52: 45715 | D52: 23712 | E52: 23794.65 | F52: 23521 | G52: 23614.95 | H52: 23622.85 | I52: 23614.95 | J52: 94840 | K52: 1682200.6 | L52: 16761000 | M52: -26400 | N52: 23559.95 | O52: =IF(AND(ISNUMBER(G52),ISNUMBER(N52)),G52-N52,"") -> 55 | P52: =IF(ISNUMBER(O52),O52/N52,"") -> 0.0023344701 | Q52: =C52-B52 -> 20 | R52: =IF(AND(C52=C51,ISNUMBER(G52),ISNUMBER(G51)),(G52/G51-1)*100,"") -> -0.31217152 | S52: =IF(AND(C52=C51,ISNUMBER(L52),ISNUMBER(L51)),(L52/L51-1)*100,"") -> -0.1572608 | T52: =IF(AND(C52=C51,ISNUMBER(G52),ISNUMBER(G51)),G52-G51,"") -> -73.95 | U52: =IF(OR(NOT(ISNUMBER(R52)),NOT(ISNUMBER(S52))),"Not classified",IF(AND(R52>0,S52>0),"Long buildup (interpretation)",IF(AND(R52<0,S52>0),"Short buildup (interpretation)",IF(AND(R52>0,S52<0),"Short covering (interpretation)",IF(AND(R52<0,S52<0),"Long unwinding (interpretation)","Neutral"))))) -> Long unwinding (interpretation) | V52: =TEXT(B52,"yyyy-mm") -> 2025-02 | W52: =1+COUNTIFS($B$2:$B$756,B52,$C$2:$C$756,"<"&C52) -> 1 | X52: =IF(AND(ISNUMBER(P52),Q52>0),P52*365/Q52,"") -> 0.04260408 | Y52: =IF(AND(C53=C52,ISNUMBER(R53)),R53,"") -> -0.65975156 | Z52: =IF(AND(W52=1,Q52>Basis_Analysis!$B$3,ISNUMBER(Y52)),1,0) -> 1 | AA52: =IF(W52=1,IF(SUMIFS($L$2:$L$756,$B$2:$B$756,B52,$W$2:$W$756,2)>0,SUMIFS($L$2:$L$756,$B$2:$B$756,B52,$W$2:$W$756,2),""),"") -> 963300 | AB52: =IF(AND(W52=1,ISNUMBER(AA52)),L52/(L52+AA52),"") -> 0.94565089
A53: NIFTY | B53: 45698 | C53: 45715 | D53: 23589.95 | E53: 23623 | F53: 23388 | G53: 23459.15 | H53: 23457.75 | I53: 23459.15 | J53: 68065 | K53: 1197950.1 | L53: 17100975 | M53: 339975 | N53: 23381.6 | O53: =IF(AND(ISNUMBER(G53),ISNUMBER(N53)),G53-N53,"") -> 77.55 | P53: =IF(ISNUMBER(O53),O53/N53,"") -> 0.0033167106 | Q53: =C53-B53 -> 17 | R53: =IF(AND(C53=C52,ISNUMBER(G53),ISNUMBER(G52)),(G53/G52-1)*100,"") -> -0.65975156 | S53: =IF(AND(C53=C52,ISNUMBER(L53),ISNUMBER(L52)),(L53/L52-1)*100,"") -> 2.0283694 | T53: =IF(AND(C53=C52,ISNUMBER(G53),ISNUMBER(G52)),G53-G52,"") -> -155.8 | U53: =IF(OR(NOT(ISNUMBER(R53)),NOT(ISNUMBER(S53))),"Not classified",IF(AND(R53>0,S53>0),"Long buildup (interpretation)",IF(AND(R53<0,S53>0),"Short buildup (interpretation)",IF(AND(R53>0,S53<0),"Short covering (interpretation)",IF(AND(R53<0,S53<0),"Long unwinding (interpretation)","Neutral"))))) -> Short buildup (interpretation) | V53: =TEXT(B53,"yyyy-mm") -> 2025-02 | W53: =1+COUNTIFS($B$2:$B$756,B53,$C$2:$C$756,"<"&C53) -> 1 | X53: =IF(AND(ISNUMBER(P53),Q53>0),P53*365/Q53,"") -> 0.071211727 | Y53: =IF(AND(C54=C53,ISNUMBER(R54)),R54,"") -> -1.3043951 | Z53: =IF(AND(W53=1,Q53>Basis_Analysis!$B$3,ISNUMBER(Y53)),1,0) -> 1 | AA53: =IF(W53=1,IF(SUMIFS($L$2:$L$756,$B$2:$B$756,B53,$W$2:$W$756,2)>0,SUMIFS($L$2:$L$756,$B$2:$B$756,B53,$W$2:$W$756,2),""),"") -> 1041825 | AB53: =IF(AND(W53=1,ISNUMBER(AA53)),L53/(L53+AA53),"") -> 0.94257639
A54: NIFTY | B54: 45699 | C54: 45715 | D54: 23421 | E54: 23470 | F54: 23060 | G54: 23153.15 | H54: 23139 | I54: 23153.15 | J54: 87766 | K54: 1529357.2 | L54: 17240925 | M54: 139950 | N54: 23071.8 | O54: =IF(AND(ISNUMBER(G54),ISNUMBER(N54)),G54-N54,"") -> 81.35 | P54: =IF(ISNUMBER(O54),O54/N54,"") -> 0.0035259494 | Q54: =C54-B54 -> 16 | R54: =IF(AND(C54=C53,ISNUMBER(G54),ISNUMBER(G53)),(G54/G53-1)*100,"") -> -1.3043951 | S54: =IF(AND(C54=C53,ISNUMBER(L54),ISNUMBER(L53)),(L54/L53-1)*100,"") -> 0.81837439 | T54: =IF(AND(C54=C53,ISNUMBER(G54),ISNUMBER(G53)),G54-G53,"") -> -306 | U54: =IF(OR(NOT(ISNUMBER(R54)),NOT(ISNUMBER(S54))),"Not classified",IF(AND(R54>0,S54>0),"Long buildup (interpretation)",IF(AND(R54<0,S54>0),"Short buildup (interpretation)",IF(AND(R54>0,S54<0),"Short covering (interpretation)",IF(AND(R54<0,S54<0),"Long unwinding (interpretation)","Neutral"))))) -> Short buildup (interpretation) | V54: =TEXT(B54,"yyyy-mm") -> 2025-02 | W54: =1+COUNTIFS($B$2:$B$756,B54,$C$2:$C$756,"<"&C54) -> 1 | X54: =IF(AND(ISNUMBER(P54),Q54>0),P54*365/Q54,"") -> 0.080435721 | Y54: =IF(AND(C55=C54,ISNUMBER(R55)),R55,"") -> -0.12654866 | Z54: =IF(AND(W54=1,Q54>Basis_Analysis!$B$3,ISNUMBER(Y54)),1,0) -> 1 | AA54: =IF(W54=1,IF(SUMIFS($L$2:$L$756,$B$2:$B$756,B54,$W$2:$W$756,2)>0,SUMIFS($L$2:$L$756,$B$2:$B$756,B54,$W$2:$W$756,2),""),"") -> 1152825 | AB54: =IF(AND(W54=1,ISNUMBER(AA54)),L54/(L54+AA54),"") -> 0.93732518
A55: NIFTY | B55: 45700 | C55: 45715 | D55: 23134.4 | E55: 23236.45 | F55: 22900 | G55: 23123.85 | H55: 23132 | I55: 23123.85 | J55: 132065 | K55: 2285259.9 | L55: 17572200 | M55: 331275 | N55: 23045.25 | O55: =IF(AND(ISNUMBER(G55),ISNUMBER(N55)),G55-N55,"") -> 78.6 | P55: =IF(ISNUMBER(O55),O55/N55,"") -> 0.0034106812 | Q55: =C55-B55 -> 15 | R55: =IF(AND(C55=C54,ISNUMBER(G55),ISNUMBER(G54)),(G55/G54-1)*100,"") -> -0.12654866 | S55: =IF(AND(C55=C54,ISNUMBER(L55),ISNUMBER(L54)),(L55/L54-1)*100,"") -> 1.9214456 | T55: =IF(AND(C55=C54,ISNUMBER(G55),ISNUMBER(G54)),G55-G54,"") -> -29.3 | U55: =IF(OR(NOT(ISNUMBER(R55)),NOT(ISNUMBER(S55))),"Not classified",IF(AND(R55>0,S55>0),"Long buildup (interpretation)",IF(AND(R55<0,S55>0),"Short buildup (interpretation)",IF(AND(R55>0,S55<0),"Short covering (interpretation)",IF(AND(R55<0,S55<0),"Long unwinding (interpretation)","Neutral"))))) -> Short buildup (interpretation) | V55: =TEXT(B55,"yyyy-mm") -> 2025-02 | W55: =1+COUNTIFS($B$2:$B$756,B55,$C$2:$C$756,"<"&C55) -> 1 | X55: =IF(AND(ISNUMBER(P55),Q55>0),P55*365/Q55,"") -> 0.082993242 | Y55: =IF(AND(C56=C55,ISNUMBER(R56)),R56,"") -> -0.069625084 | Z55: =IF(AND(W55=1,Q55>Basis_Analysis!$B$3,ISNUMBER(Y55)),1,0) -> 1 | AA55: =IF(W55=1,IF(SUMIFS($L$2:$L$756,$B$2:$B$756,B55,$W$2:$W$756,2)>0,SUMIFS($L$2:$L$756,$B$2:$B$756,B55,$W$2:$W$756,2),""),"") -> 1292625 | AB55: =IF(AND(W55=1,ISNUMBER(AA55)),L55/(L55+AA55),"") -> 0.93147962
A56: NIFTY | B56: 45701 | C56: 45715 | D56: 23119 | E56: 23310 | F56: 23066 | G56: 23107.75 | H56: 23094.65 | I56: 23107.75 | J56: 82593 | K56: 1436407.4 | L56: 17272950 | M56: -299250 | N56: 23031.4 | O56: =IF(AND(ISNUMBER(G56),ISNUMBER(N56)),G56-N56,"") -> 76.35 | P56: =IF(ISNUMBER(O56),O56/N56,"") -> 0.0033150395 | Q56: =C56-B56 -> 14 | R56: =IF(AND(C56=C55,ISNUMBER(G56),ISNUMBER(G55)),(G56/G55-1)*100,"") -> -0.069625084 | S56: =IF(AND(C56=C55,ISNUMBER(L56),ISNUMBER(L55)),(L56/L55-1)*100,"") -> -1.702974 | T56: =IF(AND(C56=C55,ISNUMBER(G56),ISNUMBER(G55)),G56-G55,"") -> -16.1 | U56: =IF(OR(NOT(ISNUMBER(R56)),NOT(ISNUMBER(S56))),"Not classified",IF(AND(R56>0,S56>0),"Long buildup (interpretation)",IF(AND(R56<0,S56>0),"Short buildup (interpretation)",IF(AND(R56>0,S56<0),"Short covering (interpretation)",IF(AND(R56<0,S56<0),"Long unwinding (interpretation)","Neutral"))))) -> Long unwinding (interpretation) | V56: =TEXT(B56,"yyyy-mm") -> 2025-02 | W56: =1+COUNTIFS($B$2:$B$756,B56,$C$2:$C$756,"<"&C56) -> 1 | X56: =IF(AND(ISNUMBER(P56),Q56>0),P56*365/Q56,"") -> 0.086427815 | Y56: =IF(AND(C57=C56,ISNUMBER(R57)),R57,"") -> -0.48511863 | Z56: =IF(AND(W56=1,Q56>Basis_Analysis!$B$3,ISNUMBER(Y56)),1,0) -> 1 | AA56: =IF(W56=1,IF(SUMIFS($L$2:$L$756,$B$2:$B$756,B56,$W$2:$W$756,2)>0,SUMIFS($L$2:$L$756,$B$2:$B$756,B56,$W$2:$W$756,2),""),"") -> 1432575 | AB56: =IF(AND(W56=1,ISNUMBER(AA56)),L56/(L56+AA56),"") -> 0.92341434
A57: NIFTY | B57: 45702 | C57: 45715 | D57: 23169 | E57: 23205.5 | F57: 22846.45 | G57: 22995.65 | H57: 22972.3 | I57: 22995.65 | J57: 109312 | K57: 1886074.7 | L57: 17385600 | M57: 112650 | N57: 22929.25 | O57: =IF(AND(ISNUMBER(G57),ISNUMBER(N57)),G57-N57,"") -> 66.4 | P57: =IF(ISNUMBER(O57),O57/N57,"") -> 0.0028958645 | Q57: =C57-B57 -> 13 | R57: =IF(AND(C57=C56,ISNUMBER(G57),ISNUMBER(G56)),(G57/G56-1)*100,"") -> -0.48511863 | S57: =IF(AND(C57=C56,ISNUMBER(L57),ISNUMBER(L56)),(L57/L56-1)*100,"") -> 0.6521758 | T57: =IF(AND(C57=C56,ISNUMBER(G57),ISNUMBER(G56)),G57-G56,"") -> -112.1 | U57: =IF(OR(NOT(ISNUMBER(R57)),NOT(ISNUMBER(S57))),"Not classified",IF(AND(R57>0,S57>0),"Long buildup (interpretation)",IF(AND(R57<0,S57>0),"Short buildup (interpretation)",IF(AND(R57>0,S57<0),"Short covering (interpretation)",IF(AND(R57<0,S57<0),"Long unwinding (interpretation)","Neutral"))))) -> Short buildup (interpretation) | V57: =TEXT(B57,"yyyy-mm") -> 2025-02 | W57: =1+COUNTIFS($B$2:$B$756,B57,$C$2:$C$756,"<"&C57) -> 1 | X57: =IF(AND(ISNUMBER(P57),Q57>0),P57*365/Q57,"") -> 0.081306963 | Y57: =IF(AND(C58=C57,ISNUMBER(R58)),R58,"") -> 0.13372094 | Z57: =IF(AND(W57=1,Q57>Basis_Analysis!$B$3,ISNUMBER(Y57)),1,0) -> 1 | AA57: =IF(W57=1,IF(SUMIFS($L$2:$L$756,$B$2:$B$756,B57,$W$2:$W$756,2)>0,SUMIFS($L$2:$L$756,$B$2:$B$756,B57,$W$2:$W$756,2),""),"") -> 1659225 | AB57: =IF(AND(W57=1,ISNUMBER(AA57)),L57/(L57+AA57),"") -> 0.91287791
A58: NIFTY | B58: 45705 | C58: 45715 | D58: 22945.4 | E58: 23049 | F58: 22826.25 | G58: 23026.4 | H58: 23043.4 | I58: 23026.4 | J58: 92954 | K58: 1599595.3 | L58: 17193300 | M58: -192300 | N58: 22959.5 | O58: =IF(AND(ISNUMBER(G58),ISNUMBER(N58)),G58-N58,"") -> 66.9 | P58: =IF(ISNUMBER(O58),O58/N58,"") -> 0.0029138265 | Q58: =C58-B58 -> 10 | R58: =IF(AND(C58=C57,ISNUMBER(G58),ISNUMBER(G57)),(G58/G57-1)*100,"") -> 0.13372094 | S58: =IF(AND(C58=C57,ISNUMBER(L58),ISNUMBER(L57)),(L58/L57-1)*100,"") -> -1.1060878 | T58: =IF(AND(C58=C57,ISNUMBER(G58),ISNUMBER(G57)),G58-G57,"") -> 30.75 | U58: =IF(OR(NOT(ISNUMBER(R58)),NOT(ISNUMBER(S58))),"Not classified",IF(AND(R58>0,S58>0),"Long buildup (interpretation)",IF(AND(R58<0,S58>0),"Short buildup (interpretation)",IF(AND(R58>0,S58<0),"Short covering (interpretation)",IF(AND(R58<0,S58<0),"Long unwinding (interpretation)","Neutral"))))) -> Short covering (interpretation) | V58: =TEXT(B58,"yyyy-mm") -> 2025-02 | W58: =1+COUNTIFS($B$2:$B$756,B58,$C$2:$C$756,"<"&C58) -> 1 | X58: =IF(AND(ISNUMBER(P58),Q58>0),P58*365/Q58,"") -> 0.10635467 | Y58: =IF(AND(C59=C58,ISNUMBER(R59)),R59,"") -> -0.23364486 | Z58: =IF(AND(W58=1,Q58>Basis_Analysis!$B$3,ISNUMBER(Y58)),1,0) -> 1 | AA58: =IF(W58=1,IF(SUMIFS($L$2:$L$756,$B$2:$B$756,B58,$W$2:$W$756,2)>0,SUMIFS($L$2:$L$756,$B$2:$B$756,B58,$W$2:$W$756,2),""),"") -> 1804125 | AB58: =IF(AND(W58=1,ISNUMBER(AA58)),L58/(L58+AA58),"") -> 0.90503318
A59: NIFTY | B59: 45706 | C59: 45715 | D59: 23029.1 | E59: 23029.1 | F59: 22838.8 | G59: 22972.6 | H59: 22948.1 | I59: 22972.6 | J59: 73098 | K59: 1257358.6 | L59: 16780425 | M59: -412875 | N59: 22945.3 | O59: =IF(AND(ISNUMBER(G59),ISNUMBER(N59)),G59-N59,"") -> 27.3 | P59: =IF(ISNUMBER(O59),O59/N59,"") -> 0.0011897861 | Q59: =C59-B59 -> 9 | R59: =IF(AND(C59=C58,ISNUMBER(G59),ISNUMBER(G58)),(G59/G58-1)*100,"") -> -0.23364486 | S59: =IF(AND(C59=C58,ISNUMBER(L59),ISNUMBER(L58)),(L59/L58-1)*100,"") -> -2.4013715 | T59: =IF(AND(C59=C58,ISNUMBER(G59),ISNUMBER(G58)),G59-G58,"") -> -53.8 | U59: =IF(OR(NOT(ISNUMBER(R59)),NOT(ISNUMBER(S59))),"Not classified",IF(AND(R59>0,S59>0),"Long buildup (interpretation)",IF(AND(R59<0,S59>0),"Short buildup (interpretation)",IF(AND(R59>0,S59<0),"Short covering (interpretation)",IF(AND(R59<0,S59<0),"Long unwinding (interpretation)","Neutral"))))) -> Long unwinding (interpretation) | V59: =TEXT(B59,"yyyy-mm") -> 2025-02 | W59: =1+COUNTIFS($B$2:$B$756,B59,$C$2:$C$756,"<"&C59) -> 1 | X59: =IF(AND(ISNUMBER(P59),Q59>0),P59*365/Q59,"") -> 0.048252438 | Y59: =IF(AND(C60=C59,ISNUMBER(R60)),R60,"") -> -0.035259396 | Z59: =IF(AND(W59=1,Q59>Basis_Analysis!$B$3,ISNUMBER(Y59)),1,0) -> 1 | AA59: =IF(W59=1,IF(SUMIFS($L$2:$L$756,$B$2:$B$756,B59,$W$2:$W$756,2)>0,SUMIFS($L$2:$L$756,$B$2:$B$756,B59,$W$2:$W$756,2),""),"") -> 2020050 | AB59: =IF(AND(W59=1,ISNUMBER(AA59)),L59/(L59+AA59),"") -> 0.89255325
A60: NIFTY | B60: 45707 | C60: 45715 | D60: 22900.2 | E60: 23106.2 | F60: 22881.15 | G60: 22964.5 | H60: 22950 | I60: 22964.5 | J60: 86464 | K60: 1491427.1 | L60: 16659825 | M60: -120600 | N60: 22932.9 | O60: =IF(AND(ISNUMBER(G60),ISNUMBER(N60)),G60-N60,"") -> 31.6 | P60: =IF(ISNUMBER(O60),O60/N60,"") -> 0.001377933 | Q60: =C60-B60 -> 8 | R60: =IF(AND(C60=C59,ISNUMBER(G60),ISNUMBER(G59)),(G60/G59-1)*100,"") -> -0.035259396 | S60: =IF(AND(C60=C59,ISNUMBER(L60),ISNUMBER(L59)),(L60/L59-1)*100,"") -> -0.71869455 | T60: =IF(AND(C60=C59,ISNUMBER(G60),ISNUMBER(G59)),G60-G59,"") -> -8.1 | U60: =IF(OR(NOT(ISNUMBER(R60)),NOT(ISNUMBER(S60))),"Not classified",IF(AND(R60>0,S60>0),"Long buildup (interpretation)",IF(AND(R60<0,S60>0),"Short buildup (interpretation)",IF(AND(R60>0,S60<0),"Short covering (interpretation)",IF(AND(R60<0,S60<0),"Long unwinding (interpretation)","Neutral"))))) -> Long unwinding (interpretation) | V60: =TEXT(B60,"yyyy-mm") -> 2025-02 | W60: =1+COUNTIFS($B$2:$B$756,B60,$C$2:$C$756,"<"&C60) -> 1 | X60: =IF(AND(ISNUMBER(P60),Q60>0),P60*365/Q60,"") -> 0.062868194 | Y60: =IF(AND(C61=C60,ISNUMBER(R61)),R61,"") -> -0.095800039 | Z60: =IF(AND(W60=1,Q60>Basis_Analysis!$B$3,ISNUMBER(Y60)),1,0) -> 1 | AA60: =IF(W60=1,IF(SUMIFS($L$2:$L$756,$B$2:$B$756,B60,$W$2:$W$756,2)>0,SUMIFS($L$2:$L$756,$B$2:$B$756,B60,$W$2:$W$756,2),""),"") -> 2306175 | AB60: =IF(AND(W60=1,ISNUMBER(AA60)),L60/(L60+AA60),"") -> 0.87840478
A61: NIFTY | B61: 45708 | C61: 45715 | D61: 22895 | E61: 22960.95 | F61: 22855 | G61: 22942.5 | H61: 22934.9 | I61: 22942.5 | J61: 54621 | K61: 939120.41 | L61: 16391775 | M61: -268050 | N61: 22913.15 | O61: =IF(AND(ISNUMBER(G61),ISNUMBER(N61)),G61-N61,"") -> 29.35 | P61: =IF(ISNUMBER(O61),O61/N61,"") -> 0.0012809238 | Q61: =C61-B61 -> 7 | R61: =IF(AND(C61=C60,ISNUMBER(G61),ISNUMBER(G60)),(G61/G60-1)*100,"") -> -0.095800039 | S61: =IF(AND(C61=C60,ISNUMBER(L61),ISNUMBER(L60)),(L61/L60-1)*100,"") -> -1.6089605 | T61: =IF(AND(C61=C60,ISNUMBER(G61),ISNUMBER(G60)),G61-G60,"") -> -22 | U61: =IF(OR(NOT(ISNUMBER(R61)),NOT(ISNUMBER(S61))),"Not classified",IF(AND(R61>0,S61>0),"Long buildup (interpretation)",IF(AND(R61<0,S61>0),"Short buildup (interpretation)",IF(AND(R61>0,S61<0),"Short covering (interpretation)",IF(AND(R61<0,S61<0),"Long unwinding (interpretation)","Neutral"))))) -> Long unwinding (interpretation) | V61: =TEXT(B61,"yyyy-mm") -> 2025-02 | W61: =1+COUNTIFS($B$2:$B$756,B61,$C$2:$C$756,"<"&C61) -> 1 | X61: =IF(AND(ISNUMBER(P61),Q61>0),P61*365/Q61,"") -> 0.066791029 | Y61: =IF(AND(C62=C61,ISNUMBER(R62)),R62,"") -> -0.52261088 | Z61: =IF(AND(W61=1,Q61>Basis_Analysis!$B$3,ISNUMBER(Y61)),1,0) -> 1 | AA61: =IF(W61=1,IF(SUMIFS($L$2:$L$756,$B$2:$B$756,B61,$W$2:$W$756,2)>0,SUMIFS($L$2:$L$756,$B$2:$B$756,B61,$W$2:$W$756,2),""),"") -> 2879400 | AB61: =IF(AND(W61=1,ISNUMBER(AA61)),L61/(L61+AA61),"") -> 0.85058514
... A90: NIFTY | B90: 45691 | C90: 45743 | D90: 23575 | E90: 23595 | F90: 23451 | G90: 23581.25 | H90: 23576.95 | I90: 23581.25 | J90: 4563 | K90: 80494.68 | L90: 862950 | M90: 1725 | N90: 23361.05 | O90: =IF(AND(ISNUMBER(G90),ISNUMBER(N90)),G90-N90,"") -> 220.2 | P90: =IF(ISNUMBER(O90),O90/N90,"") -> 0.0094259462 | Q90: =C90-B90 -> 52 | R90: =IF(AND(C90=C89,ISNUMBER(G90),ISNUMBER(G89)),(G90/G89-1)*100,"") -> -0.47648892 | S90: =IF(AND(C90=C89,ISNUMBER(L90),ISNUMBER(L89)),(L90/L89-1)*100,"") -> 0.20029609 | T90: =IF(AND(C90=C89,ISNUMBER(G90),ISNUMBER(G89)),G90-G89,"") -> -112.9 | U90: =IF(OR(NOT(ISNUMBER(R90)),NOT(ISNUMBER(S90))),"Not classified",IF(AND(R90>0,S90>0),"Long buildup (interpretation)",IF(AND(R90<0,S90>0),"Short buildup (interpretation)",IF(AND(R90>0,S90<0),"Short covering (interpretation)",IF(AND(R90<0,S90<0),"Long unwinding (interpretation)","Neutral"))))) -> Short buildup (interpretation) | V90: =TEXT(B90,"yyyy-mm") -> 2025-02 | W90: =1+COUNTIFS($B$2:$B$756,B90,$C$2:$C$756,"<"&C90) -> 2 | X90: =IF(AND(ISNUMBER(P90),Q90>0),P90*365/Q90,"") -> 0.066162891 | Y90: =IF(AND(C91=C90,ISNUMBER(R91)),R91,"") -> 1.4511529 | Z90: =IF(AND(W90=1,Q90>Basis_Analysis!$B$3,ISNUMBER(Y90)),1,0) -> 0 | AA90: =IF(W90=1,IF(SUMIFS($L$2:$L$756,$B$2:$B$756,B90,$W$2:$W$756,2)>0,SUMIFS($L$2:$L$756,$B$2:$B$756,B90,$W$2:$W$756,2),""),"") | AB90: =IF(AND(W90=1,ISNUMBER(AA90)),L90/(L90+AA90),"")
A91: NIFTY | B91: 45692 | C91: 45743 | D91: 23666 | E91: 23932.7 | F91: 23642.1 | G91: 23923.45 | H91: 23932 | I91: 23923.45 | J91: 7802 | K91: 139273.28 | L91: 885900 | M91: 22950 | O91: =IF(AND(ISNUMBER(G91),ISNUMBER(N91)),G91-N91,"") | P91: =IF(ISNUMBER(O91),O91/N91,"") | Q91: =C91-B91 -> 51 | R91: =IF(AND(C91=C90,ISNUMBER(G91),ISNUMBER(G90)),(G91/G90-1)*100,"") -> 1.4511529 | S91: =IF(AND(C91=C90,ISNUMBER(L91),ISNUMBER(L90)),(L91/L90-1)*100,"") -> 2.659482 | T91: =IF(AND(C91=C90,ISNUMBER(G91),ISNUMBER(G90)),G91-G90,"") -> 342.2 | U91: =IF(OR(NOT(ISNUMBER(R91)),NOT(ISNUMBER(S91))),"Not classified",IF(AND(R91>0,S91>0),"Long buildup (interpretation)",IF(AND(R91<0,S91>0),"Short buildup (interpretation)",IF(AND(R91>0,S91<0),"Short covering (interpretation)",IF(AND(R91<0,S91<0),"Long unwinding (interpretation)","Neutral"))))) -> Long buildup (interpretation) | V91: =TEXT(B91,"yyyy-mm") -> 2025-02 | W91: =1+COUNTIFS($B$2:$B$756,B91,$C$2:$C$756,"<"&C91) -> 2 | X91: =IF(AND(ISNUMBER(P91),Q91>0),P91*365/Q91,"") | Y91: =IF(AND(C92=C91,ISNUMBER(R92)),R92,"") -> -0.031976993 | Z91: =IF(AND(W91=1,Q91>Basis_Analysis!$B$3,ISNUMBER(Y91)),1,0) -> 0 | AA91: =IF(W91=1,IF(SUMIFS($L$2:$L$756,$B$2:$B$756,B91,$W$2:$W$756,2)>0,SUMIFS($L$2:$L$756,$B$2:$B$756,B91,$W$2:$W$756,2),""),"") | AB91: =IF(AND(W91=1,ISNUMBER(AA91)),L91/(L91+AA91),"")
A92: NIFTY | B92: 45693 | C92: 45743 | D92: 23935 | E92: 23991.65 | F92: 23897.65 | G92: 23915.8 | H92: 23898 | I92: 23915.8 | J92: 3179 | K92: 57116.18 | L92: 888975 | M92: 3075 | N92: 23696.3 | O92: =IF(AND(ISNUMBER(G92),ISNUMBER(N92)),G92-N92,"") -> 219.5 | P92: =IF(ISNUMBER(O92),O92/N92,"") -> 0.0092630495 | Q92: =C92-B92 -> 50 | R92: =IF(AND(C92=C91,ISNUMBER(G92),ISNUMBER(G91)),(G92/G91-1)*100,"") -> -0.031976993 | S92: =IF(AND(C92=C91,ISNUMBER(L92),ISNUMBER(L91)),(L92/L91-1)*100,"") -> 0.34710464 | T92: =IF(AND(C92=C91,ISNUMBER(G92),ISNUMBER(G91)),G92-G91,"") -> -7.65 | U92: =IF(OR(NOT(ISNUMBER(R92)),NOT(ISNUMBER(S92))),"Not classified",IF(AND(R92>0,S92>0),"Long buildup (interpretation)",IF(AND(R92<0,S92>0),"Short buildup (interpretation)",IF(AND(R92>0,S92<0),"Short covering (interpretation)",IF(AND(R92<0,S92<0),"Long unwinding (interpretation)","Neutral"))))) -> Short buildup (interpretation) | V92: =TEXT(B92,"yyyy-mm") -> 2025-02 | W92: =1+COUNTIFS($B$2:$B$756,B92,$C$2:$C$756,"<"&C92) -> 2 | X92: =IF(AND(ISNUMBER(P92),Q92>0),P92*365/Q92,"") -> 0.067620261 | Y92: =IF(AND(C93=C92,ISNUMBER(R93)),R93,"") -> -0.33659756 | Z92: =IF(AND(W92=1,Q92>Basis_Analysis!$B$3,ISNUMBER(Y92)),1,0) -> 0 | AA92: =IF(W92=1,IF(SUMIFS($L$2:$L$756,$B$2:$B$756,B92,$W$2:$W$756,2)>0,SUMIFS($L$2:$L$756,$B$2:$B$756,B92,$W$2:$W$756,2),""),"") | AB92: =IF(AND(W92=1,ISNUMBER(AA92)),L92/(L92+AA92),"")
A93: NIFTY | B93: 45694 | C93: 45743 | D93: 23964.6 | E93: 23964.6 | F93: 23805.05 | G93: 23835.3 | H93: 23850 | I93: 23835.3 | J93: 2823 | K93: 50507.53 | L93: 930525 | M93: 41550 | N93: 23603.35 | O93: =IF(AND(ISNUMBER(G93),ISNUMBER(N93)),G93-N93,"") -> 231.95 | P93: =IF(ISNUMBER(O93),O93/N93,"") -> 0.0098269949 | Q93: =C93-B93 -> 49 | R93: =IF(AND(C93=C92,ISNUMBER(G93),ISNUMBER(G92)),(G93/G92-1)*100,"") -> -0.33659756 | S93: =IF(AND(C93=C92,ISNUMBER(L93),ISNUMBER(L92)),(L93/L92-1)*100,"") -> 4.6739222 | T93: =IF(AND(C93=C92,ISNUMBER(G93),ISNUMBER(G92)),G93-G92,"") -> -80.5 | U93: =IF(OR(NOT(ISNUMBER(R93)),NOT(ISNUMBER(S93))),"Not classified",IF(AND(R93>0,S93>0),"Long buildup (interpretation)",IF(AND(R93<0,S93>0),"Short buildup (interpretation)",IF(AND(R93>0,S93<0),"Short covering (interpretation)",IF(AND(R93<0,S93<0),"Long unwinding (interpretation)","Neutral"))))) -> Short buildup (interpretation) | V93: =TEXT(B93,"yyyy-mm") -> 2025-02 | W93: =1+COUNTIFS($B$2:$B$756,B93,$C$2:$C$756,"<"&C93) -> 2 | X93: =IF(AND(ISNUMBER(P93),Q93>0),P93*365/Q93,"") -> 0.073201084 | Y93: =IF(AND(C94=C93,ISNUMBER(R94)),R94,"") -> -0.29200388 | Z93: =IF(AND(W93=1,Q93>Basis_Analysis!$B$3,ISNUMBER(Y93)),1,0) -> 0 | AA93: =IF(W93=1,IF(SUMIFS($L$2:$L$756,$B$2:$B$756,B93,$W$2:$W$756,2)>0,SUMIFS($L$2:$L$756,$B$2:$B$756,B93,$W$2:$W$756,2),""),"") | AB93: =IF(AND(W93=1,ISNUMBER(AA93)),L93/(L93+AA93),"")
A94: NIFTY | B94: 45695 | C94: 45743 | D94: 23852.45 | E94: 23934.1 | F94: 23671 | G94: 23765.7 | H94: 23770 | I94: 23765.7 | J94: 5279 | K94: 94187.35 | L94: 963300 | M94: 32775 | N94: 23559.95 | O94: =IF(AND(ISNUMBER(G94),ISNUMBER(N94)),G94-N94,"") -> 205.75 | P94: =IF(ISNUMBER(O94),O94/N94,"") -> 0.0087330406 | Q94: =C94-B94 -> 48 | R94: =IF(AND(C94=C93,ISNUMBER(G94),ISNUMBER(G93)),(G94/G93-1)*100,"") -> -0.29200388 | S94: =IF(AND(C94=C93,ISNUMBER(L94),ISNUMBER(L93)),(L94/L93-1)*100,"") -> 3.5222052 | T94: =IF(AND(C94=C93,ISNUMBER(G94),ISNUMBER(G93)),G94-G93,"") -> -69.6 | U94: =IF(OR(NOT(ISNUMBER(R94)),NOT(ISNUMBER(S94))),"Not classified",IF(AND(R94>0,S94>0),"Long buildup (interpretation)",IF(AND(R94<0,S94>0),"Short buildup (interpretation)",IF(AND(R94>0,S94<0),"Short covering (interpretation)",IF(AND(R94<0,S94<0),"Long unwinding (interpretation)","Neutral"))))) -> Short buildup (interpretation) | V94: =TEXT(B94,"yyyy-mm") -> 2025-02 | W94: =1+COUNTIFS($B$2:$B$756,B94,$C$2:$C$756,"<"&C94) -> 2 | X94: =IF(AND(ISNUMBER(P94),Q94>0),P94*365/Q94,"") -> 0.066407496 | Y94: =IF(AND(C95=C94,ISNUMBER(R95)),R95,"") -> -0.65262121 | Z94: =IF(AND(W94=1,Q94>Basis_Analysis!$B$3,ISNUMBER(Y94)),1,0) -> 0 | AA94: =IF(W94=1,IF(SUMIFS($L$2:$L$756,$B$2:$B$756,B94,$W$2:$W$756,2)>0,SUMIFS($L$2:$L$756,$B$2:$B$756,B94,$W$2:$W$756,2),""),"") | AB94: =IF(AND(W94=1,ISNUMBER(AA94)),L94/(L94+AA94),"")
A95: NIFTY | B95: 45698 | C95: 45743 | D95: 23746 | E95: 23752.1 | F95: 23540 | G95: 23610.6 | H95: 23608 | I95: 23610.6 | J95: 4887 | K95: 86533.95 | L95: 1041825 | M95: 78525 | N95: 23381.6 | O95: =IF(AND(ISNUMBER(G95),ISNUMBER(N95)),G95-N95,"") -> 229 | P95: =IF(ISNUMBER(O95),O95/N95,"") -> 0.0097940261 | Q95: =C95-B95 -> 45 | R95: =IF(AND(C95=C94,ISNUMBER(G95),ISNUMBER(G94)),(G95/G94-1)*100,"") -> -0.65262121 | S95: =IF(AND(C95=C94,ISNUMBER(L95),ISNUMBER(L94)),(L95/L94-1)*100,"") -> 8.1516661 | T95: =IF(AND(C95=C94,ISNUMBER(G95),ISNUMBER(G94)),G95-G94,"") -> -155.1 | U95: =IF(OR(NOT(ISNUMBER(R95)),NOT(ISNUMBER(S95))),"Not classified",IF(AND(R95>0,S95>0),"Long buildup (interpretation)",IF(AND(R95<0,S95>0),"Short buildup (interpretation)",IF(AND(R95>0,S95<0),"Short covering (interpretation)",IF(AND(R95<0,S95<0),"Long unwinding (interpretation)","Neutral"))))) -> Short buildup (interpretation) | V95: =TEXT(B95,"yyyy-mm") -> 2025-02 | W95: =1+COUNTIFS($B$2:$B$756,B95,$C$2:$C$756,"<"&C95) -> 2 | X95: =IF(AND(ISNUMBER(P95),Q95>0),P95*365/Q95,"") -> 0.079440434 | Y95: =IF(AND(C96=C95,ISNUMBER(R96)),R96,"") -> -1.3417702 | Z95: =IF(AND(W95=1,Q95>Basis_Analysis!$B$3,ISNUMBER(Y95)),1,0) -> 0 | AA95: =IF(W95=1,IF(SUMIFS($L$2:$L$756,$B$2:$B$756,B95,$W$2:$W$756,2)>0,SUMIFS($L$2:$L$756,$B$2:$B$756,B95,$W$2:$W$756,2),""),"") | AB95: =IF(AND(W95=1,ISNUMBER(AA95)),L95/(L95+AA95),"")
A96: NIFTY | B96: 45699 | C96: 45743 | D96: 23568.4 | E96: 23594.6 | F96: 23203.5 | G96: 23293.8 | H96: 23276.95 | I96: 23293.8 | J96: 9000 | K96: 157715.28 | L96: 1152825 | M96: 111000 | N96: 23071.8 | O96: =IF(AND(ISNUMBER(G96),ISNUMBER(N96)),G96-N96,"") -> 222 | P96: =IF(ISNUMBER(O96),O96/N96,"") -> 0.0096221361 | Q96: =C96-B96 -> 44 | R96: =IF(AND(C96=C95,ISNUMBER(G96),ISNUMBER(G95)),(G96/G95-1)*100,"") -> -1.3417702 | S96: =IF(AND(C96=C95,ISNUMBER(L96),ISNUMBER(L95)),(L96/L95-1)*100,"") -> 10.654381 | T96: =IF(AND(C96=C95,ISNUMBER(G96),ISNUMBER(G95)),G96-G95,"") -> -316.8 | U96: =IF(OR(NOT(ISNUMBER(R96)),NOT(ISNUMBER(S96))),"Not classified",IF(AND(R96>0,S96>0),"Long buildup (interpretation)",IF(AND(R96<0,S96>0),"Short buildup (interpretation)",IF(AND(R96>0,S96<0),"Short covering (interpretation)",IF(AND(R96<0,S96<0),"Long unwinding (interpretation)","Neutral"))))) -> Short buildup (interpretation) | V96: =TEXT(B96,"yyyy-mm") -> 2025-02 | W96: =1+COUNTIFS($B$2:$B$756,B96,$C$2:$C$756,"<"&C96) -> 2 | X96: =IF(AND(ISNUMBER(P96),Q96>0),P96*365/Q96,"") -> 0.079819993 | Y96: =IF(AND(C97=C96,ISNUMBER(R97)),R97,"") -> -0.12020366 | Z96: =IF(AND(W96=1,Q96>Basis_Analysis!$B$3,ISNUMBER(Y96)),1,0) -> 0 | AA96: =IF(W96=1,IF(SUMIFS($L$2:$L$756,$B$2:$B$756,B96,$W$2:$W$756,2)>0,SUMIFS($L$2:$L$756,$B$2:$B$756,B96,$W$2:$W$756,2),""),"") | AB96: =IF(AND(W96=1,ISNUMBER(AA96)),L96/(L96+AA96),"")
A97: NIFTY | B97: 45700 | C97: 45743 | D97: 23283.8 | E97: 23375 | F97: 23040 | G97: 23265.8 | H97: 23270 | I97: 23265.8 | J97: 11291 | K97: 196445.83 | L97: 1292625 | M97: 139800 | N97: 23045.25 | O97: =IF(AND(ISNUMBER(G97),ISNUMBER(N97)),G97-N97,"") -> 220.55 | P97: =IF(ISNUMBER(O97),O97/N97,"") -> 0.0095703019 | Q97: =C97-B97 -> 43 | R97: =IF(AND(C97=C96,ISNUMBER(G97),ISNUMBER(G96)),(G97/G96-1)*100,"") -> -0.12020366 | S97: =IF(AND(C97=C96,ISNUMBER(L97),ISNUMBER(L96)),(L97/L96-1)*100,"") -> 12.126732 | T97: =IF(AND(C97=C96,ISNUMBER(G97),ISNUMBER(G96)),G97-G96,"") -> -28 | U97: =IF(OR(NOT(ISNUMBER(R97)),NOT(ISNUMBER(S97))),"Not classified",IF(AND(R97>0,S97>0),"Long buildup (interpretation)",IF(AND(R97<0,S97>0),"Short buildup (interpretation)",IF(AND(R97>0,S97<0),"Short covering (interpretation)",IF(AND(R97<0,S97<0),"Long unwinding (interpretation)","Neutral"))))) -> Short buildup (interpretation) | V97: =TEXT(B97,"yyyy-mm") -> 2025-02 | W97: =1+COUNTIFS($B$2:$B$756,B97,$C$2:$C$756,"<"&C97) -> 2 | X97: =IF(AND(ISNUMBER(P97),Q97>0),P97*365/Q97,"") -> 0.081236284 | Y97: =IF(AND(C98=C97,ISNUMBER(R98)),R98,"") -> -0.10143644 | Z97: =IF(AND(W97=1,Q97>Basis_Analysis!$B$3,ISNUMBER(Y97)),1,0) -> 0 | AA97: =IF(W97=1,IF(SUMIFS($L$2:$L$756,$B$2:$B$756,B97,$W$2:$W$756,2)>0,SUMIFS($L$2:$L$756,$B$2:$B$756,B97,$W$2:$W$756,2),""),"") | AB97: =IF(AND(W97=1,ISNUMBER(AA97)),L97/(L97+AA97),"")
A98: NIFTY | B98: 45701 | C98: 45743 | D98: 23290 | E98: 23442 | F98: 23207.55 | G98: 23242.2 | H98: 23230 | I98: 23242.2 | J98: 8033 | K98: 140460.37 | L98: 1432575 | M98: 139950 | N98: 23031.4 | O98: =IF(AND(ISNUMBER(G98),ISNUMBER(N98)),G98-N98,"") -> 210.8 | P98: =IF(ISNUMBER(O98),O98/N98,"") -> 0.0091527219 | Q98: =C98-B98 -> 42 | R98: =IF(AND(C98=C97,ISNUMBER(G98),ISNUMBER(G97)),(G98/G97-1)*100,"") -> -0.10143644 | S98: =IF(AND(C98=C97,ISNUMBER(L98),ISNUMBER(L97)),(L98/L97-1)*100,"") -> 10.826806 | T98: =IF(AND(C98=C97,ISNUMBER(G98),ISNUMBER(G97)),G98-G97,"") -> -23.6 | U98: =IF(OR(NOT(ISNUMBER(R98)),NOT(ISNUMBER(S98))),"Not classified",IF(AND(R98>0,S98>0),"Long buildup (interpretation)",IF(AND(R98<0,S98>0),"Short buildup (interpretation)",IF(AND(R98>0,S98<0),"Short covering (interpretation)",IF(AND(R98<0,S98<0),"Long unwinding (interpretation)","Neutral"))))) -> Short buildup (interpretation) | V98: =TEXT(B98,"yyyy-mm") -> 2025-02 | W98: =1+COUNTIFS($B$2:$B$756,B98,$C$2:$C$756,"<"&C98) -> 2 | X98: =IF(AND(ISNUMBER(P98),Q98>0),P98*365/Q98,"") -> 0.079541512 | Y98: =IF(AND(C99=C98,ISNUMBER(R99)),R99,"") -> -0.48682999 | Z98: =IF(AND(W98=1,Q98>Basis_Analysis!$B$3,ISNUMBER(Y98)),1,0) -> 0 | AA98: =IF(W98=1,IF(SUMIFS($L$2:$L$756,$B$2:$B$756,B98,$W$2:$W$756,2)>0,SUMIFS($L$2:$L$756,$B$2:$B$756,B98,$W$2:$W$756,2),""),"") | AB98: =IF(AND(W98=1,ISNUMBER(AA98)),L98/(L98+AA98),"")
A99: NIFTY | B99: 45702 | C99: 45743 | D99: 23299 | E99: 23344 | F99: 22982.3 | G99: 23129.05 | H99: 23115 | I99: 23129.05 | J99: 12285 | K99: 213077.06 | L99: 1659225 | M99: 226650 | N99: 22929.25 | O99: =IF(AND(ISNUMBER(G99),ISNUMBER(N99)),G99-N99,"") -> 199.8 | P99: =IF(ISNUMBER(O99),O99/N99,"") -> 0.0087137608 | Q99: =C99-B99 -> 41 | R99: =IF(AND(C99=C98,ISNUMBER(G99),ISNUMBER(G98)),(G99/G98-1)*100,"") -> -0.48682999 | S99: =IF(AND(C99=C98,ISNUMBER(L99),ISNUMBER(L98)),(L99/L98-1)*100,"") -> 15.821161 | T99: =IF(AND(C99=C98,ISNUMBER(G99),ISNUMBER(G98)),G99-G98,"") -> -113.15 | U99: =IF(OR(NOT(ISNUMBER(R99)),NOT(ISNUMBER(S99))),"Not classified",IF(AND(R99>0,S99>0),"Long buildup (interpretation)",IF(AND(R99<0,S99>0),"Short buildup (interpretation)",IF(AND(R99>0,S99<0),"Short covering (interpretation)",IF(AND(R99<0,S99<0),"Long unwinding (interpretation)","Neutral"))))) -> Short buildup (interpretation) | V99: =TEXT(B99,"yyyy-mm") -> 2025-02 | W99: =1+COUNTIFS($B$2:$B$756,B99,$C$2:$C$756,"<"&C99) -> 2 | X99: =IF(AND(ISNUMBER(P99),Q99>0),P99*365/Q99,"") -> 0.077573724 | Y99: =IF(AND(C100=C99,ISNUMBER(R100)),R100,"") -> 0.14267771 | Z99: =IF(AND(W99=1,Q99>Basis_Analysis!$B$3,ISNUMBER(Y99)),1,0) -> 0 | AA99: =IF(W99=1,IF(SUMIFS($L$2:$L$756,$B$2:$B$756,B99,$W$2:$W$756,2)>0,SUMIFS($L$2:$L$756,$B$2:$B$756,B99,$W$2:$W$756,2),""),"") | AB99: =IF(AND(W99=1,ISNUMBER(AA99)),L99/(L99+AA99),"")
A100: NIFTY | B100: 45705 | C100: 45743 | D100: 23050.15 | E100: 23185 | F100: 22962.2 | G100: 23162.05 | H100: 23178.35 | I100: 23162.05 | J100: 10208 | K100: 176602.54 | L100: 1804125 | M100: 144900 | N100: 22959.5 | O100: =IF(AND(ISNUMBER(G100),ISNUMBER(N100)),G100-N100,"") -> 202.55 | P100: =IF(ISNUMBER(O100),O100/N100,"") -> 0.0088220562 | Q100: =C100-B100 -> 38 | R100: =IF(AND(C100=C99,ISNUMBER(G100),ISNUMBER(G99)),(G100/G99-1)*100,"") -> 0.14267771 | S100: =IF(AND(C100=C99,ISNUMBER(L100),ISNUMBER(L99)),(L100/L99-1)*100,"") -> 8.7329928 | T100: =IF(AND(C100=C99,ISNUMBER(G100),ISNUMBER(G99)),G100-G99,"") -> 33 | U100: =IF(OR(NOT(ISNUMBER(R100)),NOT(ISNUMBER(S100))),"Not classified",IF(AND(R100>0,S100>0),"Long buildup (interpretation)",IF(AND(R100<0,S100>0),"Short buildup (interpretation)",IF(AND(R100>0,S100<0),"Short covering (interpretation)",IF(AND(R100<0,S100<0),"Long unwinding (interpretation)","Neutral"))))) -> Long buildup (interpretation) | V100: =TEXT(B100,"yyyy-mm") -> 2025-02 | W100: =1+COUNTIFS($B$2:$B$756,B100,$C$2:$C$756,"<"&C100) -> 2 | X100: =IF(AND(ISNUMBER(P100),Q100>0),P100*365/Q100,"") -> 0.084738172 | Y100: =IF(AND(C101=C100,ISNUMBER(R101)),R101,"") -> -0.26206661 | Z100: =IF(AND(W100=1,Q100>Basis_Analysis!$B$3,ISNUMBER(Y100)),1,0) -> 0 | AA100: =IF(W100=1,IF(SUMIFS($L$2:$L$756,$B$2:$B$756,B100,$W$2:$W$756,2)>0,SUMIFS($L$2:$L$756,$B$2:$B$756,B100,$W$2:$W$756,2),""),"") | AB100: =IF(AND(W100=1,ISNUMBER(AA100)),L100/(L100+AA100),"")
A101: NIFTY | B101: 45706 | C101: 45743 | D101: 23142.7 | E101: 23150 | F101: 22977.2 | G101: 23101.35 | H101: 23085 | I101: 23101.35 | J101: 10369 | K101: 179362.92 | L101: 2020050 | M101: 215925 | N101: 22945.3 | O101: =IF(AND(ISNUMBER(G101),ISNUMBER(N101)),G101-N101,"") -> 156.05 | P101: =IF(ISNUMBER(O101),O101/N101,"") -> 0.0068009571 | Q101: =C101-B101 -> 37 | R101: =IF(AND(C101=C100,ISNUMBER(G101),ISNUMBER(G100)),(G101/G100-1)*100,"") -> -0.26206661 | S101: =IF(AND(C101=C100,ISNUMBER(L101),ISNUMBER(L100)),(L101/L100-1)*100,"") -> 11.968406 | T101: =IF(AND(C101=C100,ISNUMBER(G101),ISNUMBER(G100)),G101-G100,"") -> -60.7 | U101: =IF(OR(NOT(ISNUMBER(R101)),NOT(ISNUMBER(S101))),"Not classified",IF(AND(R101>0,S101>0),"Long buildup (interpretation)",IF(AND(R101<0,S101>0),"Short buildup (interpretation)",IF(AND(R101>0,S101<0),"Short covering (interpretation)",IF(AND(R101<0,S101<0),"Long unwinding (interpretation)","Neutral"))))) -> Short buildup (interpretation) | V101: =TEXT(B101,"yyyy-mm") -> 2025-02 | W101: =1+COUNTIFS($B$2:$B$756,B101,$C$2:$C$756,"<"&C101) -> 2 | X101: =IF(AND(ISNUMBER(P101),Q101>0),P101*365/Q101,"") -> 0.067090522 | Y101: =IF(AND(C102=C101,ISNUMBER(R102)),R102,"") -> -0.0067095646 | Z101: =IF(AND(W101=1,Q101>Basis_Analysis!$B$3,ISNUMBER(Y101)),1,0) -> 0 | AA101: =IF(W101=1,IF(SUMIFS($L$2:$L$756,$B$2:$B$756,B101,$W$2:$W$756,2)>0,SUMIFS($L$2:$L$756,$B$2:$B$756,B101,$W$2:$W$756,2),""),"") | AB101: =IF(AND(W101=1,ISNUMBER(AA101)),L101/(L101+AA101),"")
A102: NIFTY | B102: 45707 | C102: 45743 | D102: 23080.95 | E102: 23237.95 | F102: 23012.95 | G102: 23099.8 | H102: 23091 | I102: 23099.8 | J102: 11489 | K102: 199266.89 | L102: 2306175 | M102: 286125 | N102: 22932.9 | O102: =IF(AND(ISNUMBER(G102),ISNUMBER(N102)),G102-N102,"") -> 166.9 | P102: =IF(ISNUMBER(O102),O102/N102,"") -> 0.0072777538 | Q102: =C102-B102 -> 36 | R102: =IF(AND(C102=C101,ISNUMBER(G102),ISNUMBER(G101)),(G102/G101-1)*100,"") -> -0.0067095646 | S102: =IF(AND(C102=C101,ISNUMBER(L102),ISNUMBER(L101)),(L102/L101-1)*100,"") -> 14.164253 | T102: =IF(AND(C102=C101,ISNUMBER(G102),ISNUMBER(G101)),G102-G101,"") -> -1.55 | U102: =IF(OR(NOT(ISNUMBER(R102)),NOT(ISNUMBER(S102))),"Not classified",IF(AND(R102>0,S102>0),"Long buildup (interpretation)",IF(AND(R102<0,S102>0),"Short buildup (interpretation)",IF(AND(R102>0,S102<0),"Short covering (interpretation)",IF(AND(R102<0,S102<0),"Long unwinding (interpretation)","Neutral"))))) -> Short buildup (interpretation) | V102: =TEXT(B102,"yyyy-mm") -> 2025-02 | W102: =1+COUNTIFS($B$2:$B$756,B102,$C$2:$C$756,"<"&C102) -> 2 | X102: =IF(AND(ISNUMBER(P102),Q102>0),P102*365/Q102,"") -> 0.073788337 | Y102: =IF(AND(C103=C102,ISNUMBER(R103)),R103,"") -> -0.071212738 | Z102: =IF(AND(W102=1,Q102>Basis_Analysis!$B$3,ISNUMBER(Y102)),1,0) -> 0 | AA102: =IF(W102=1,IF(SUMIFS($L$2:$L$756,$B$2:$B$756,B102,$W$2:$W$756,2)>0,SUMIFS($L$2:$L$756,$B$2:$B$756,B102,$W$2:$W$756,2),""),"") | AB102: =IF(AND(W102=1,ISNUMBER(AA102)),L102/(L102+AA102),"")
A103: NIFTY | B103: 45708 | C103: 45743 | D103: 22911 | E103: 23100.3 | F103: 22898.35 | G103: 23083.35 | H103: 23077.95 | I103: 23083.35 | J103: 14937 | K103: 258408.87 | L103: 2879400 | M103: 573225 | N103: 22913.15 | O103: =IF(AND(ISNUMBER(G103),ISNUMBER(N103)),G103-N103,"") -> 170.2 | P103: =IF(ISNUMBER(O103),O103/N103,"") -> 0.007428049 | Q103: =C103-B103 -> 35 | R103: =IF(AND(C103=C102,ISNUMBER(G103),ISNUMBER(G102)),(G103/G102-1)*100,"") -> -0.071212738 | S103: =IF(AND(C103=C102,ISNUMBER(L103),ISNUMBER(L102)),(L103/L102-1)*100,"") -> 24.856093 | T103: =IF(AND(C103=C102,ISNUMBER(G103),ISNUMBER(G102)),G103-G102,"") -> -16.45 | U103: =IF(OR(NOT(ISNUMBER(R103)),NOT(ISNUMBER(S103))),"Not classified",IF(AND(R103>0,S103>0),"Long buildup (interpretation)",IF(AND(R103<0,S103>0),"Short buildup (interpretation)",IF(AND(R103>0,S103<0),"Short covering (interpretation)",IF(AND(R103<0,S103<0),"Long unwinding (interpretation)","Neutral"))))) -> Short buildup (interpretation) | V103: =TEXT(B103,"yyyy-mm") -> 2025-02 | W103: =1+COUNTIFS($B$2:$B$756,B103,$C$2:$C$756,"<"&C103) -> 2 | X103: =IF(AND(ISNUMBER(P103),Q103>0),P103*365/Q103,"") -> 0.077463939 | Y103: =IF(AND(C104=C103,ISNUMBER(R104)),R104,"") -> -0.52115486 | Z103: =IF(AND(W103=1,Q103>Basis_Analysis!$B$3,ISNUMBER(Y103)),1,0) -> 0 | AA103: =IF(W103=1,IF(SUMIFS($L$2:$L$756,$B$2:$B$756,B103,$W$2:$W$756,2)>0,SUMIFS($L$2:$L$756,$B$2:$B$756,B103,$W$2:$W$756,2),""),"") | AB103: =IF(AND(W103=1,ISNUMBER(AA103)),L103/(L103+AA103),"")
... A126: NIFTY | B126: 45743 | C126: 45743 | D126: 23470 | E126: 23643.1 | F126: 23455.05 | G126: 23593.6 | H126: 23595 | I126: 23591.95 | J126: 72007 | K126: 1274038.3 | L126: 4421475 | M126: -2645925 | N126: 23591.95 | O126: =IF(AND(ISNUMBER(G126),ISNUMBER(N126)),G126-N126,"") -> 1.65 | P126: =IF(ISNUMBER(O126),O126/N126,"") -> 6.9939111e-05 | Q126: =C126-B126 -> 0 | R126: =IF(AND(C126=C125,ISNUMBER(G126),ISNUMBER(G125)),(G126/G125-1)*100,"") -> 0.30482231 | S126: =IF(AND(C126=C125,ISNUMBER(L126),ISNUMBER(L125)),(L126/L125-1)*100,"") -> -37.43845 | T126: =IF(AND(C126=C125,ISNUMBER(G126),ISNUMBER(G125)),G126-G125,"") -> 71.7 | U126: =IF(OR(NOT(ISNUMBER(R126)),NOT(ISNUMBER(S126))),"Not classified",IF(AND(R126>0,S126>0),"Long buildup (interpretation)",IF(AND(R126<0,S126>0),"Short buildup (interpretation)",IF(AND(R126>0,S126<0),"Short covering (interpretation)",IF(AND(R126<0,S126<0),"Long unwinding (interpretation)","Neutral"))))) -> Short covering (interpretation) | V126: =TEXT(B126,"yyyy-mm") -> 2025-03 | W126: =1+COUNTIFS($B$2:$B$756,B126,$C$2:$C$756,"<"&C126) -> 1 | X126: =IF(AND(ISNUMBER(P126),Q126>0),P126*365/Q126,"") | Y126: =IF(AND(C127=C126,ISNUMBER(R127)),R127,"") | Z126: =IF(AND(W126=1,Q126>Basis_Analysis!$B$3,ISNUMBER(Y126)),1,0) -> 0 | AA126: =IF(W126=1,IF(SUMIFS($L$2:$L$756,$B$2:$B$756,B126,$W$2:$W$756,2)>0,SUMIFS($L$2:$L$756,$B$2:$B$756,B126,$W$2:$W$756,2),""),"") -> 12423450 | AB126: =IF(AND(W126=1,ISNUMBER(AA126)),L126/(L126+AA126),"") -> 0.26248113
A127: NIFTY | B127: 45687 | C127: 45771 | O127: =IF(AND(ISNUMBER(G127),ISNUMBER(N127)),G127-N127,"") | P127: =IF(ISNUMBER(O127),O127/N127,"") | Q127: =C127-B127 -> 84 | R127: =IF(AND(C127=C126,ISNUMBER(G127),ISNUMBER(G126)),(G127/G126-1)*100,"") | S127: =IF(AND(C127=C126,ISNUMBER(L127),ISNUMBER(L126)),(L127/L126-1)*100,"") | T127: =IF(AND(C127=C126,ISNUMBER(G127),ISNUMBER(G126)),G127-G126,"") | U127: =IF(OR(NOT(ISNUMBER(R127)),NOT(ISNUMBER(S127))),"Not classified",IF(AND(R127>0,S127>0),"Long buildup (interpretation)",IF(AND(R127<0,S127>0),"Short buildup (interpretation)",IF(AND(R127>0,S127<0),"Short covering (interpretation)",IF(AND(R127<0,S127<0),"Long unwinding (interpretation)","Neutral"))))) -> Not classified | V127: =TEXT(B127,"yyyy-mm") -> 2025-01 | W127: =1+COUNTIFS($B$2:$B$756,B127,$C$2:$C$756,"<"&C127) -> 4 | X127: =IF(AND(ISNUMBER(P127),Q127>0),P127*365/Q127,"") | Y127: =IF(AND(C128=C127,ISNUMBER(R128)),R128,"") | Z127: =IF(AND(W127=1,Q127>Basis_Analysis!$B$3,ISNUMBER(Y127)),1,0) -> 0 | AA127: =IF(W127=1,IF(SUMIFS($L$2:$L$756,$B$2:$B$756,B127,$W$2:$W$756,2)>0,SUMIFS($L$2:$L$756,$B$2:$B$756,B127,$W$2:$W$756,2),""),"") | AB127: =IF(AND(W127=1,ISNUMBER(AA127)),L127/(L127+AA127),"")
A128: NIFTY | B128: 45688 | C128: 45771 | D128: 23705 | E128: 23920 | F128: 23700 | G128: 23899.4 | H128: 23912.9 | I128: 23899.4 | J128: 1273 | K128: 22756.97 | L128: 49125 | M128: 49125 | N128: 23508.4 | O128: =IF(AND(ISNUMBER(G128),ISNUMBER(N128)),G128-N128,"") -> 391 | P128: =IF(ISNUMBER(O128),O128/N128,"") -> 0.016632353 | Q128: =C128-B128 -> 83 | R128: =IF(AND(C128=C127,ISNUMBER(G128),ISNUMBER(G127)),(G128/G127-1)*100,"") | S128: =IF(AND(C128=C127,ISNUMBER(L128),ISNUMBER(L127)),(L128/L127-1)*100,"") | T128: =IF(AND(C128=C127,ISNUMBER(G128),ISNUMBER(G127)),G128-G127,"") | U128: =IF(OR(NOT(ISNUMBER(R128)),NOT(ISNUMBER(S128))),"Not classified",IF(AND(R128>0,S128>0),"Long buildup (interpretation)",IF(AND(R128<0,S128>0),"Short buildup (interpretation)",IF(AND(R128>0,S128<0),"Short covering (interpretation)",IF(AND(R128<0,S128<0),"Long unwinding (interpretation)","Neutral"))))) -> Not classified | V128: =TEXT(B128,"yyyy-mm") -> 2025-01 | W128: =1+COUNTIFS($B$2:$B$756,B128,$C$2:$C$756,"<"&C128) -> 3 | X128: =IF(AND(ISNUMBER(P128),Q128>0),P128*365/Q128,"") -> 0.073142274 | Y128: =IF(AND(C129=C128,ISNUMBER(R129)),R129,"") -> -0.25293522 | Z128: =IF(AND(W128=1,Q128>Basis_Analysis!$B$3,ISNUMBER(Y128)),1,0) -> 0 | AA128: =IF(W128=1,IF(SUMIFS($L$2:$L$756,$B$2:$B$756,B128,$W$2:$W$756,2)>0,SUMIFS($L$2:$L$756,$B$2:$B$756,B128,$W$2:$W$756,2),""),"") | AB128: =IF(AND(W128=1,ISNUMBER(AA128)),L128/(L128+AA128),"")
A129: NIFTY | B129: 45689 | C129: 45771 | D129: 23892.3 | E129: 23988 | F129: 23714.1 | G129: 23838.95 | H129: 23850.9 | I129: 23838.95 | J129: 1789 | K129: 32005.27 | L129: 64500 | M129: 15375 | N129: 23482.15 | O129: =IF(AND(ISNUMBER(G129),ISNUMBER(N129)),G129-N129,"") -> 356.8 | P129: =IF(ISNUMBER(O129),O129/N129,"") -> 0.01519452 | Q129: =C129-B129 -> 82 | R129: =IF(AND(C129=C128,ISNUMBER(G129),ISNUMBER(G128)),(G129/G128-1)*100,"") -> -0.25293522 | S129: =IF(AND(C129=C128,ISNUMBER(L129),ISNUMBER(L128)),(L129/L128-1)*100,"") -> 31.29771 | T129: =IF(AND(C129=C128,ISNUMBER(G129),ISNUMBER(G128)),G129-G128,"") -> -60.45 | U129: =IF(OR(NOT(ISNUMBER(R129)),NOT(ISNUMBER(S129))),"Not classified",IF(AND(R129>0,S129>0),"Long buildup (interpretation)",IF(AND(R129<0,S129>0),"Short buildup (interpretation)",IF(AND(R129>0,S129<0),"Short covering (interpretation)",IF(AND(R129<0,S129<0),"Long unwinding (interpretation)","Neutral"))))) -> Short buildup (interpretation) | V129: =TEXT(B129,"yyyy-mm") -> 2025-02 | W129: =1+COUNTIFS($B$2:$B$756,B129,$C$2:$C$756,"<"&C129) -> 3 | X129: =IF(AND(ISNUMBER(P129),Q129>0),P129*365/Q129,"") -> 0.067634144 | Y129: =IF(AND(C130=C129,ISNUMBER(R130)),R130,"") -> -0.49435902 | Z129: =IF(AND(W129=1,Q129>Basis_Analysis!$B$3,ISNUMBER(Y129)),1,0) -> 0 | AA129: =IF(W129=1,IF(SUMIFS($L$2:$L$756,$B$2:$B$756,B129,$W$2:$W$756,2)>0,SUMIFS($L$2:$L$756,$B$2:$B$756,B129,$W$2:$W$756,2),""),"") | AB129: =IF(AND(W129=1,ISNUMBER(AA129)),L129/(L129+AA129),"")
A130: NIFTY | B130: 45691 | C130: 45771 | D130: 23750 | E130: 23750 | F130: 23590 | G130: 23721.1 | H130: 23718.05 | I130: 23721.1 | J130: 1247 | K130: 22133.46 | L130: 80625 | M130: 16125 | N130: 23361.05 | O130: =IF(AND(ISNUMBER(G130),ISNUMBER(N130)),G130-N130,"") -> 360.05 | P130: =IF(ISNUMBER(O130),O130/N130,"") -> 0.015412407 | Q130: =C130-B130 -> 80 | R130: =IF(AND(C130=C129,ISNUMBER(G130),ISNUMBER(G129)),(G130/G129-1)*100,"") -> -0.49435902 | S130: =IF(AND(C130=C129,ISNUMBER(L130),ISNUMBER(L129)),(L130/L129-1)*100,"") -> 25 | T130: =IF(AND(C130=C129,ISNUMBER(G130),ISNUMBER(G129)),G130-G129,"") -> -117.85 | U130: =IF(OR(NOT(ISNUMBER(R130)),NOT(ISNUMBER(S130))),"Not classified",IF(AND(R130>0,S130>0),"Long buildup (interpretation)",IF(AND(R130<0,S130>0),"Short buildup (interpretation)",IF(AND(R130>0,S130<0),"Short covering (interpretation)",IF(AND(R130<0,S130<0),"Long unwinding (interpretation)","Neutral"))))) -> Short buildup (interpretation) | V130: =TEXT(B130,"yyyy-mm") -> 2025-02 | W130: =1+COUNTIFS($B$2:$B$756,B130,$C$2:$C$756,"<"&C130) -> 3 | X130: =IF(AND(ISNUMBER(P130),Q130>0),P130*365/Q130,"") -> 0.070319105 | Y130: =IF(AND(C131=C130,ISNUMBER(R131)),R131,"") -> 1.4472347 | Z130: =IF(AND(W130=1,Q130>Basis_Analysis!$B$3,ISNUMBER(Y130)),1,0) -> 0 | AA130: =IF(W130=1,IF(SUMIFS($L$2:$L$756,$B$2:$B$756,B130,$W$2:$W$756,2)>0,SUMIFS($L$2:$L$756,$B$2:$B$756,B130,$W$2:$W$756,2),""),"") | AB130: =IF(AND(W130=1,ISNUMBER(AA130)),L130/(L130+AA130),"")
A131: NIFTY | B131: 45692 | C131: 45771 | D131: 23799.95 | E131: 24075 | F131: 23780.65 | G131: 24064.4 | H131: 24074.55 | I131: 24064.4 | J131: 2218 | K131: 39831.22 | L131: 103575 | M131: 22950 | O131: =IF(AND(ISNUMBER(G131),ISNUMBER(N131)),G131-N131,"") | P131: =IF(ISNUMBER(O131),O131/N131,"") | Q131: =C131-B131 -> 79 | R131: =IF(AND(C131=C130,ISNUMBER(G131),ISNUMBER(G130)),(G131/G130-1)*100,"") -> 1.4472347 | S131: =IF(AND(C131=C130,ISNUMBER(L131),ISNUMBER(L130)),(L131/L130-1)*100,"") -> 28.465116 | T131: =IF(AND(C131=C130,ISNUMBER(G131),ISNUMBER(G130)),G131-G130,"") -> 343.3 | U131: =IF(OR(NOT(ISNUMBER(R131)),NOT(ISNUMBER(S131))),"Not classified",IF(AND(R131>0,S131>0),"Long buildup (interpretation)",IF(AND(R131<0,S131>0),"Short buildup (interpretation)",IF(AND(R131>0,S131<0),"Short covering (interpretation)",IF(AND(R131<0,S131<0),"Long unwinding (interpretation)","Neutral"))))) -> Long buildup (interpretation) | V131: =TEXT(B131,"yyyy-mm") -> 2025-02 | W131: =1+COUNTIFS($B$2:$B$756,B131,$C$2:$C$756,"<"&C131) -> 3 | X131: =IF(AND(ISNUMBER(P131),Q131>0),P131*365/Q131,"") | Y131: =IF(AND(C132=C131,ISNUMBER(R132)),R132,"") -> -0.0097654627 | Z131: =IF(AND(W131=1,Q131>Basis_Analysis!$B$3,ISNUMBER(Y131)),1,0) -> 0 | AA131: =IF(W131=1,IF(SUMIFS($L$2:$L$756,$B$2:$B$756,B131,$W$2:$W$756,2)>0,SUMIFS($L$2:$L$756,$B$2:$B$756,B131,$W$2:$W$756,2),""),"") | AB131: =IF(AND(W131=1,ISNUMBER(AA131)),L131/(L131+AA131),"")
A132: NIFTY | B132: 45693 | C132: 45771 | D132: 24111 | E132: 24130.2 | F132: 24041 | G132: 24062.05 | H132: 24041 | I132: 24062.05 | J132: 1057 | K132: 19105.77 | L132: 114450 | M132: 10875 | N132: 23696.3 | O132: =IF(AND(ISNUMBER(G132),ISNUMBER(N132)),G132-N132,"") -> 365.75 | P132: =IF(ISNUMBER(O132),O132/N132,"") -> 0.015434899 | Q132: =C132-B132 -> 78 | R132: =IF(AND(C132=C131,ISNUMBER(G132),ISNUMBER(G131)),(G132/G131-1)*100,"") -> -0.0097654627 | S132: =IF(AND(C132=C131,ISNUMBER(L132),ISNUMBER(L131)),(L132/L131-1)*100,"") -> 10.499638 | T132: =IF(AND(C132=C131,ISNUMBER(G132),ISNUMBER(G131)),G132-G131,"") -> -2.35 | U132: =IF(OR(NOT(ISNUMBER(R132)),NOT(ISNUMBER(S132))),"Not classified",IF(AND(R132>0,S132>0),"Long buildup (interpretation)",IF(AND(R132<0,S132>0),"Short buildup (interpretation)",IF(AND(R132>0,S132<0),"Short covering (interpretation)",IF(AND(R132<0,S132<0),"Long unwinding (interpretation)","Neutral"))))) -> Short buildup (interpretation) | V132: =TEXT(B132,"yyyy-mm") -> 2025-02 | W132: =1+COUNTIFS($B$2:$B$756,B132,$C$2:$C$756,"<"&C132) -> 3 | X132: =IF(AND(ISNUMBER(P132),Q132>0),P132*365/Q132,"") -> 0.072227413 | Y132: =IF(AND(C133=C132,ISNUMBER(R133)),R133,"") -> -0.35533132 | Z132: =IF(AND(W132=1,Q132>Basis_Analysis!$B$3,ISNUMBER(Y132)),1,0) -> 0 | AA132: =IF(W132=1,IF(SUMIFS($L$2:$L$756,$B$2:$B$756,B132,$W$2:$W$756,2)>0,SUMIFS($L$2:$L$756,$B$2:$B$756,B132,$W$2:$W$756,2),""),"") | AB132: =IF(AND(W132=1,ISNUMBER(AA132)),L132/(L132+AA132),"")
A133: NIFTY | B133: 45694 | C133: 45771 | D133: 24041 | E133: 24104.3 | F133: 23955 | G133: 23976.55 | H133: 23990 | I133: 23976.55 | J133: 1022 | K133: 18391.77 | L133: 135675 | M133: 21225 | N133: 23603.35 | O133: =IF(AND(ISNUMBER(G133),ISNUMBER(N133)),G133-N133,"") -> 373.2 | P133: =IF(ISNUMBER(O133),O133/N133,"") -> 0.015811315 | Q133: =C133-B133 -> 77 | R133: =IF(AND(C133=C132,ISNUMBER(G133),ISNUMBER(G132)),(G133/G132-1)*100,"") -> -0.35533132 | S133: =IF(AND(C133=C132,ISNUMBER(L133),ISNUMBER(L132)),(L133/L132-1)*100,"") -> 18.545216 | T133: =IF(AND(C133=C132,ISNUMBER(G133),ISNUMBER(G132)),G133-G132,"") -> -85.5 | U133: =IF(OR(NOT(ISNUMBER(R133)),NOT(ISNUMBER(S133))),"Not classified",IF(AND(R133>0,S133>0),"Long buildup (interpretation)",IF(AND(R133<0,S133>0),"Short buildup (interpretation)",IF(AND(R133>0,S133<0),"Short covering (interpretation)",IF(AND(R133<0,S133<0),"Long unwinding (interpretation)","Neutral"))))) -> Short buildup (interpretation) | V133: =TEXT(B133,"yyyy-mm") -> 2025-02 | W133: =1+COUNTIFS($B$2:$B$756,B133,$C$2:$C$756,"<"&C133) -> 3 | X133: =IF(AND(ISNUMBER(P133),Q133>0),P133*365/Q133,"") -> 0.07494974 | Y133: =IF(AND(C134=C133,ISNUMBER(R134)),R134,"") -> -0.30404708 | Z133: =IF(AND(W133=1,Q133>Basis_Analysis!$B$3,ISNUMBER(Y133)),1,0) -> 0 | AA133: =IF(W133=1,IF(SUMIFS($L$2:$L$756,$B$2:$B$756,B133,$W$2:$W$756,2)>0,SUMIFS($L$2:$L$756,$B$2:$B$756,B133,$W$2:$W$756,2),""),"") | AB133: =IF(AND(W133=1,ISNUMBER(AA133)),L133/(L133+AA133),"")
A134: NIFTY | B134: 45695 | C134: 45771 | D134: 23980.35 | E134: 24075 | F134: 23818.15 | G134: 23903.65 | H134: 23901.95 | I134: 23903.65 | J134: 1476 | K134: 26478.9 | L134: 147900 | M134: 12225 | N134: 23559.95 | O134: =IF(AND(ISNUMBER(G134),ISNUMBER(N134)),G134-N134,"") -> 343.7 | P134: =IF(ISNUMBER(O134),O134/N134,"") -> 0.014588316 | Q134: =C134-B134 -> 76 | R134: =IF(AND(C134=C133,ISNUMBER(G134),ISNUMBER(G133)),(G134/G133-1)*100,"") -> -0.30404708 | S134: =IF(AND(C134=C133,ISNUMBER(L134),ISNUMBER(L133)),(L134/L133-1)*100,"") -> 9.010503 | T134: =IF(AND(C134=C133,ISNUMBER(G134),ISNUMBER(G133)),G134-G133,"") -> -72.9 | U134: =IF(OR(NOT(ISNUMBER(R134)),NOT(ISNUMBER(S134))),"Not classified",IF(AND(R134>0,S134>0),"Long buildup (interpretation)",IF(AND(R134<0,S134>0),"Short buildup (interpretation)",IF(AND(R134>0,S134<0),"Short covering (interpretation)",IF(AND(R134<0,S134<0),"Long unwinding (interpretation)","Neutral"))))) -> Short buildup (interpretation) | V134: =TEXT(B134,"yyyy-mm") -> 2025-02 | W134: =1+COUNTIFS($B$2:$B$756,B134,$C$2:$C$756,"<"&C134) -> 3 | X134: =IF(AND(ISNUMBER(P134),Q134>0),P134*365/Q134,"") -> 0.070062308 | Y134: =IF(AND(C135=C134,ISNUMBER(R135)),R135,"") -> -0.6331669 | Z134: =IF(AND(W134=1,Q134>Basis_Analysis!$B$3,ISNUMBER(Y134)),1,0) -> 0 | AA134: =IF(W134=1,IF(SUMIFS($L$2:$L$756,$B$2:$B$756,B134,$W$2:$W$756,2)>0,SUMIFS($L$2:$L$756,$B$2:$B$756,B134,$W$2:$W$756,2),""),"") | AB134: =IF(AND(W134=1,ISNUMBER(AA134)),L134/(L134+AA134),"")
A135: NIFTY | B135: 45698 | C135: 45771 | D135: 23850 | E135: 23862.25 | F135: 23690 | G135: 23752.3 | H135: 23743.25 | I135: 23752.3 | J135: 1428 | K135: 25442.48 | L135: 176925 | M135: 29025 | N135: 23381.6 | O135: =IF(AND(ISNUMBER(G135),ISNUMBER(N135)),G135-N135,"") -> 370.7 | P135: =IF(ISNUMBER(O135),O135/N135,"") -> 0.015854347 | Q135: =C135-B135 -> 73 | R135: =IF(AND(C135=C134,ISNUMBER(G135),ISNUMBER(G134)),(G135/G134-1)*100,"") -> -0.6331669 | S135: =IF(AND(C135=C134,ISNUMBER(L135),ISNUMBER(L134)),(L135/L134-1)*100,"") -> 19.624746 | T135: =IF(AND(C135=C134,ISNUMBER(G135),ISNUMBER(G134)),G135-G134,"") -> -151.35 | U135: =IF(OR(NOT(ISNUMBER(R135)),NOT(ISNUMBER(S135))),"Not classified",IF(AND(R135>0,S135>0),"Long buildup (interpretation)",IF(AND(R135<0,S135>0),"Short buildup (interpretation)",IF(AND(R135>0,S135<0),"Short covering (interpretation)",IF(AND(R135<0,S135<0),"Long unwinding (interpretation)","Neutral"))))) -> Short buildup (interpretation) | V135: =TEXT(B135,"yyyy-mm") -> 2025-02 | W135: =1+COUNTIFS($B$2:$B$756,B135,$C$2:$C$756,"<"&C135) -> 3 | X135: =IF(AND(ISNUMBER(P135),Q135>0),P135*365/Q135,"") -> 0.079271735 | Y135: =IF(AND(C136=C135,ISNUMBER(R136)),R136,"") -> -1.3106099 | Z135: =IF(AND(W135=1,Q135>Basis_Analysis!$B$3,ISNUMBER(Y135)),1,0) -> 0 | AA135: =IF(W135=1,IF(SUMIFS($L$2:$L$756,$B$2:$B$756,B135,$W$2:$W$756,2)>0,SUMIFS($L$2:$L$756,$B$2:$B$756,B135,$W$2:$W$756,2),""),"") | AB135: =IF(AND(W135=1,ISNUMBER(AA135)),L135/(L135+AA135),"")
A136: NIFTY | B136: 45699 | C136: 45771 | D136: 23739.85 | E136: 23739.85 | F136: 23350 | G136: 23441 | H136: 23423 | I136: 23441 | J136: 2562 | K136: 45201.04 | L136: 224550 | M136: 47625 | N136: 23071.8 | O136: =IF(AND(ISNUMBER(G136),ISNUMBER(N136)),G136-N136,"") -> 369.2 | P136: =IF(ISNUMBER(O136),O136/N136,"") -> 0.016002219 | Q136: =C136-B136 -> 72 | R136: =IF(AND(C136=C135,ISNUMBER(G136),ISNUMBER(G135)),(G136/G135-1)*100,"") -> -1.3106099 | S136: =IF(AND(C136=C135,ISNUMBER(L136),ISNUMBER(L135)),(L136/L135-1)*100,"") -> 26.918186 | T136: =IF(AND(C136=C135,ISNUMBER(G136),ISNUMBER(G135)),G136-G135,"") -> -311.3 | U136: =IF(OR(NOT(ISNUMBER(R136)),NOT(ISNUMBER(S136))),"Not classified",IF(AND(R136>0,S136>0),"Long buildup (interpretation)",IF(AND(R136<0,S136>0),"Short buildup (interpretation)",IF(AND(R136>0,S136<0),"Short covering (interpretation)",IF(AND(R136<0,S136<0),"Long unwinding (interpretation)","Neutral"))))) -> Short buildup (interpretation) | V136: =TEXT(B136,"yyyy-mm") -> 2025-02 | W136: =1+COUNTIFS($B$2:$B$756,B136,$C$2:$C$756,"<"&C136) -> 3 | X136: =IF(AND(ISNUMBER(P136),Q136>0),P136*365/Q136,"") -> 0.081122361 | Y136: =IF(AND(C137=C136,ISNUMBER(R137)),R137,"") -> -0.12755429 | Z136: =IF(AND(W136=1,Q136>Basis_Analysis!$B$3,ISNUMBER(Y136)),1,0) -> 0 | AA136: =IF(W136=1,IF(SUMIFS($L$2:$L$756,$B$2:$B$756,B136,$W$2:$W$756,2)>0,SUMIFS($L$2:$L$756,$B$2:$B$756,B136,$W$2:$W$756,2),""),"") | AB136: =IF(AND(W136=1,ISNUMBER(AA136)),L136/(L136+AA136),"")
A137: NIFTY | B137: 45700 | C137: 45771 | D137: 23400 | E137: 23512 | F137: 23190.8 | G137: 23411.1 | H137: 23425 | I137: 23411.1 | J137: 3205 | K137: 56092.4 | L137: 260175 | M137: 35625 | N137: 23045.25 | O137: =IF(AND(ISNUMBER(G137),ISNUMBER(N137)),G137-N137,"") -> 365.85 | P137: =IF(ISNUMBER(O137),O137/N137,"") -> 0.015875289 | Q137: =C137-B137 -> 71 | R137: =IF(AND(C137=C136,ISNUMBER(G137),ISNUMBER(G136)),(G137/G136-1)*100,"") -> -0.12755429 | S137: =IF(AND(C137=C136,ISNUMBER(L137),ISNUMBER(L136)),(L137/L136-1)*100,"") -> 15.865063 | T137: =IF(AND(C137=C136,ISNUMBER(G137),ISNUMBER(G136)),G137-G136,"") -> -29.9 | U137: =IF(OR(NOT(ISNUMBER(R137)),NOT(ISNUMBER(S137))),"Not classified",IF(AND(R137>0,S137>0),"Long buildup (interpretation)",IF(AND(R137<0,S137>0),"Short buildup (interpretation)",IF(AND(R137>0,S137<0),"Short covering (interpretation)",IF(AND(R137<0,S137<0),"Long unwinding (interpretation)","Neutral"))))) -> Short buildup (interpretation) | V137: =TEXT(B137,"yyyy-mm") -> 2025-02 | W137: =1+COUNTIFS($B$2:$B$756,B137,$C$2:$C$756,"<"&C137) -> 3 | X137: =IF(AND(ISNUMBER(P137),Q137>0),P137*365/Q137,"") -> 0.0816124 | Y137: =IF(AND(C138=C137,ISNUMBER(R138)),R138,"") -> -0.084148118 | Z137: =IF(AND(W137=1,Q137>Basis_Analysis!$B$3,ISNUMBER(Y137)),1,0) -> 0 | AA137: =IF(W137=1,IF(SUMIFS($L$2:$L$756,$B$2:$B$756,B137,$W$2:$W$756,2)>0,SUMIFS($L$2:$L$756,$B$2:$B$756,B137,$W$2:$W$756,2),""),"") | AB137: =IF(AND(W137=1,ISNUMBER(AA137)),L137/(L137+AA137),"")
A138: NIFTY | B138: 45701 | C138: 45771 | D138: 23326.8 | E138: 23583.3 | F138: 23326.8 | G138: 23391.4 | H138: 23385 | I138: 23391.4 | J138: 1808 | K138: 31825.93 | L138: 271275 | M138: 11100 | N138: 23031.4 | O138: =IF(AND(ISNUMBER(G138),ISNUMBER(N138)),G138-N138,"") -> 360 | P138: =IF(ISNUMBER(O138),O138/N138,"") -> 0.015630834 | Q138: =C138-B138 -> 70 | R138: =IF(AND(C138=C137,ISNUMBER(G138),ISNUMBER(G137)),(G138/G137-1)*100,"") -> -0.084148118 | S138: =IF(AND(C138=C137,ISNUMBER(L138),ISNUMBER(L137)),(L138/L137-1)*100,"") -> 4.2663592 | T138: =IF(AND(C138=C137,ISNUMBER(G138),ISNUMBER(G137)),G138-G137,"") -> -19.7 | U138: =IF(OR(NOT(ISNUMBER(R138)),NOT(ISNUMBER(S138))),"Not classified",IF(AND(R138>0,S138>0),"Long buildup (interpretation)",IF(AND(R138<0,S138>0),"Short buildup (interpretation)",IF(AND(R138>0,S138<0),"Short covering (interpretation)",IF(AND(R138<0,S138<0),"Long unwinding (interpretation)","Neutral"))))) -> Short buildup (interpretation) | V138: =TEXT(B138,"yyyy-mm") -> 2025-02 | W138: =1+COUNTIFS($B$2:$B$756,B138,$C$2:$C$756,"<"&C138) -> 3 | X138: =IF(AND(ISNUMBER(P138),Q138>0),P138*365/Q138,"") -> 0.081503637 | Y138: =IF(AND(C139=C138,ISNUMBER(R139)),R139,"") -> -0.48543482 | Z138: =IF(AND(W138=1,Q138>Basis_Analysis!$B$3,ISNUMBER(Y138)),1,0) -> 0 | AA138: =IF(W138=1,IF(SUMIFS($L$2:$L$756,$B$2:$B$756,B138,$W$2:$W$756,2)>0,SUMIFS($L$2:$L$756,$B$2:$B$756,B138,$W$2:$W$756,2),""),"") | AB138: =IF(AND(W138=1,ISNUMBER(AA138)),L138/(L138+AA138),"")
A139: NIFTY | B139: 45702 | C139: 45771 | D139: 23450.25 | E139: 23482.25 | F139: 23130.05 | G139: 23277.85 | H139: 23254 | I139: 23277.85 | J139: 3254 | K139: 56773.81 | L139: 317925 | M139: 46650 | N139: 22929.25 | O139: =IF(AND(ISNUMBER(G139),ISNUMBER(N139)),G139-N139,"") -> 348.6 | P139: =IF(ISNUMBER(O139),O139/N139,"") -> 0.015203288 | Q139: =C139-B139 -> 69 | R139: =IF(AND(C139=C138,ISNUMBER(G139),ISNUMBER(G138)),(G139/G138-1)*100,"") -> -0.48543482 | S139: =IF(AND(C139=C138,ISNUMBER(L139),ISNUMBER(L138)),(L139/L138-1)*100,"") -> 17.196572 | T139: =IF(AND(C139=C138,ISNUMBER(G139),ISNUMBER(G138)),G139-G138,"") -> -113.55 | U139: =IF(OR(NOT(ISNUMBER(R139)),NOT(ISNUMBER(S139))),"Not classified",IF(AND(R139>0,S139>0),"Long buildup (interpretation)",IF(AND(R139<0,S139>0),"Short buildup (interpretation)",IF(AND(R139>0,S139<0),"Short covering (interpretation)",IF(AND(R139<0,S139<0),"Long unwinding (interpretation)","Neutral"))))) -> Short buildup (interpretation) | V139: =TEXT(B139,"yyyy-mm") -> 2025-02 | W139: =1+COUNTIFS($B$2:$B$756,B139,$C$2:$C$756,"<"&C139) -> 3 | X139: =IF(AND(ISNUMBER(P139),Q139>0),P139*365/Q139,"") -> 0.080423192 | Y139: =IF(AND(C140=C139,ISNUMBER(R140)),R140,"") -> 0.11427172 | Z139: =IF(AND(W139=1,Q139>Basis_Analysis!$B$3,ISNUMBER(Y139)),1,0) -> 0 | AA139: =IF(W139=1,IF(SUMIFS($L$2:$L$756,$B$2:$B$756,B139,$W$2:$W$756,2)>0,SUMIFS($L$2:$L$756,$B$2:$B$756,B139,$W$2:$W$756,2),""),"") | AB139: =IF(AND(W139=1,ISNUMBER(AA139)),L139/(L139+AA139),"")
A140: NIFTY | B140: 45705 | C140: 45771 | D140: 23186.05 | E140: 23325 | F140: 23116 | G140: 23304.45 | H140: 23319.35 | I140: 23304.45 | J140: 2629 | K140: 45773.86 | L140: 358425 | M140: 40500 | N140: 22959.5 | O140: =IF(AND(ISNUMBER(G140),ISNUMBER(N140)),G140-N140,"") -> 344.95 | P140: =IF(ISNUMBER(O140),O140/N140,"") -> 0.015024282 | Q140: =C140-B140 -> 66 | R140: =IF(AND(C140=C139,ISNUMBER(G140),ISNUMBER(G139)),(G140/G139-1)*100,"") -> 0.11427172 | S140: =IF(AND(C140=C139,ISNUMBER(L140),ISNUMBER(L139)),(L140/L139-1)*100,"") -> 12.738854 | T140: =IF(AND(C140=C139,ISNUMBER(G140),ISNUMBER(G139)),G140-G139,"") -> 26.6 | U140: =IF(OR(NOT(ISNUMBER(R140)),NOT(ISNUMBER(S140))),"Not classified",IF(AND(R140>0,S140>0),"Long buildup (interpretation)",IF(AND(R140<0,S140>0),"Short buildup (interpretation)",IF(AND(R140>0,S140<0),"Short covering (interpretation)",IF(AND(R140<0,S140<0),"Long unwinding (interpretation)","Neutral"))))) -> Long buildup (interpretation) | V140: =TEXT(B140,"yyyy-mm") -> 2025-02 | W140: =1+COUNTIFS($B$2:$B$756,B140,$C$2:$C$756,"<"&C140) -> 3 | X140: =IF(AND(ISNUMBER(P140),Q140>0),P140*365/Q140,"") -> 0.083088832 | Y140: =IF(AND(C141=C140,ISNUMBER(R141)),R141,"") -> -0.22871168 | Z140: =IF(AND(W140=1,Q140>Basis_Analysis!$B$3,ISNUMBER(Y140)),1,0) -> 0 | AA140: =IF(W140=1,IF(SUMIFS($L$2:$L$756,$B$2:$B$756,B140,$W$2:$W$756,2)>0,SUMIFS($L$2:$L$756,$B$2:$B$756,B140,$W$2:$W$756,2),""),"") | AB140: =IF(AND(W140=1,ISNUMBER(AA140)),L140/(L140+AA140),"")
A141: NIFTY | B141: 45706 | C141: 45771 | D141: 23362.85 | E141: 23362.85 | F141: 23121.85 | G141: 23251.15 | H141: 23235 | I141: 23251.15 | J141: 2166 | K141: 37714.22 | L141: 383025 | M141: 24600 | N141: 22945.3 | O141: =IF(AND(ISNUMBER(G141),ISNUMBER(N141)),G141-N141,"") -> 305.85 | P141: =IF(ISNUMBER(O141),O141/N141,"") -> 0.013329527 | Q141: =C141-B141 -> 65 | R141: =IF(AND(C141=C140,ISNUMBER(G141),ISNUMBER(G140)),(G141/G140-1)*100,"") -> -0.22871168 | S141: =IF(AND(C141=C140,ISNUMBER(L141),ISNUMBER(L140)),(L141/L140-1)*100,"") -> 6.8633605 | T141: =IF(AND(C141=C140,ISNUMBER(G141),ISNUMBER(G140)),G141-G140,"") -> -53.3 | U141: =IF(OR(NOT(ISNUMBER(R141)),NOT(ISNUMBER(S141))),"Not classified",IF(AND(R141>0,S141>0),"Long buildup (interpretation)",IF(AND(R141<0,S141>0),"Short buildup (interpretation)",IF(AND(R141>0,S141<0),"Short covering (interpretation)",IF(AND(R141<0,S141<0),"Long unwinding (interpretation)","Neutral"))))) -> Short buildup (interpretation) | V141: =TEXT(B141,"yyyy-mm") -> 2025-02 | W141: =1+COUNTIFS($B$2:$B$756,B141,$C$2:$C$756,"<"&C141) -> 3 | X141: =IF(AND(ISNUMBER(P141),Q141>0),P141*365/Q141,"") -> 0.074850422 | Y141: =IF(AND(C142=C141,ISNUMBER(R142)),R142,"") -> -0.01784858 | Z141: =IF(AND(W141=1,Q141>Basis_Analysis!$B$3,ISNUMBER(Y141)),1,0) -> 0 | AA141: =IF(W141=1,IF(SUMIFS($L$2:$L$756,$B$2:$B$756,B141,$W$2:$W$756,2)>0,SUMIFS($L$2:$L$756,$B$2:$B$756,B141,$W$2:$W$756,2),""),"") | AB141: =IF(AND(W141=1,ISNUMBER(AA141)),L141/(L141+AA141),"")
A142: NIFTY | B142: 45707 | C142: 45771 | D142: 23250 | E142: 23380.9 | F142: 23160 | G142: 23247 | H142: 23241 | I142: 23247 | J142: 2576 | K142: 44963.84 | L142: 427500 | M142: 44475 | N142: 22932.9 | O142: =IF(AND(ISNUMBER(G142),ISNUMBER(N142)),G142-N142,"") -> 314.1 | P142: =IF(ISNUMBER(O142),O142/N142,"") -> 0.01369648 | Q142: =C142-B142 -> 64 | R142: =IF(AND(C142=C141,ISNUMBER(G142),ISNUMBER(G141)),(G142/G141-1)*100,"") -> -0.01784858 | S142: =IF(AND(C142=C141,ISNUMBER(L142),ISNUMBER(L141)),(L142/L141-1)*100,"") -> 11.611514 | T142: =IF(AND(C142=C141,ISNUMBER(G142),ISNUMBER(G141)),G142-G141,"") -> -4.15 | U142: =IF(OR(NOT(ISNUMBER(R142)),NOT(ISNUMBER(S142))),"Not classified",IF(AND(R142>0,S142>0),"Long buildup (interpretation)",IF(AND(R142<0,S142>0),"Short buildup (interpretation)",IF(AND(R142>0,S142<0),"Short covering (interpretation)",IF(AND(R142<0,S142<0),"Long unwinding (interpretation)","Neutral"))))) -> Short buildup (interpretation) | V142: =TEXT(B142,"yyyy-mm") -> 2025-02 | W142: =1+COUNTIFS($B$2:$B$756,B142,$C$2:$C$756,"<"&C142) -> 3 | X142: =IF(AND(ISNUMBER(P142),Q142>0),P142*365/Q142,"") -> 0.078112736 | Y142: =IF(AND(C143=C142,ISNUMBER(R143)),R143,"") -> -0.088398503 | Z142: =IF(AND(W142=1,Q142>Basis_Analysis!$B$3,ISNUMBER(Y142)),1,0) -> 0 | AA142: =IF(W142=1,IF(SUMIFS($L$2:$L$756,$B$2:$B$756,B142,$W$2:$W$756,2)>0,SUMIFS($L$2:$L$756,$B$2:$B$756,B142,$W$2:$W$756,2),""),"") | AB142: =IF(AND(W142=1,ISNUMBER(AA142)),L142/(L142+AA142),"")
A143: NIFTY | B143: 45708 | C143: 45771 | D143: 23201 | E143: 23241.85 | F143: 23145 | G143: 23226.45 | H143: 23225 | I143: 23226.45 | J143: 1474 | K143: 25653.28 | L143: 452850 | M143: 25350 | N143: 22913.15 | O143: =IF(AND(ISNUMBER(G143),ISNUMBER(N143)),G143-N143,"") -> 313.3 | P143: =IF(ISNUMBER(O143),O143/N143,"") -> 0.013673371 | Q143: =C143-B143 -> 63 | R143: =IF(AND(C143=C142,ISNUMBER(G143),ISNUMBER(G142)),(G143/G142-1)*100,"") -> -0.088398503 | S143: =IF(AND(C143=C142,ISNUMBER(L143),ISNUMBER(L142)),(L143/L142-1)*100,"") -> 5.9298246 | T143: =IF(AND(C143=C142,ISNUMBER(G143),ISNUMBER(G142)),G143-G142,"") -> -20.55 | U143: =IF(OR(NOT(ISNUMBER(R143)),NOT(ISNUMBER(S143))),"Not classified",IF(AND(R143>0,S143>0),"Long buildup (interpretation)",IF(AND(R143<0,S143>0),"Short buildup (interpretation)",IF(AND(R143>0,S143<0),"Short covering (interpretation)",IF(AND(R143<0,S143<0),"Long unwinding (interpretation)","Neutral"))))) -> Short buildup (interpretation) | V143: =TEXT(B143,"yyyy-mm") -> 2025-02 | W143: =1+COUNTIFS($B$2:$B$756,B143,$C$2:$C$756,"<"&C143) -> 3 | X143: =IF(AND(ISNUMBER(P143),Q143>0),P143*365/Q143,"") -> 0.079218737 | Y143: =IF(AND(C144=C143,ISNUMBER(R144)),R144,"") -> -0.52224942 | Z143: =IF(AND(W143=1,Q143>Basis_Analysis!$B$3,ISNUMBER(Y143)),1,0) -> 0 | AA143: =IF(W143=1,IF(SUMIFS($L$2:$L$756,$B$2:$B$756,B143,$W$2:$W$756,2)>0,SUMIFS($L$2:$L$756,$B$2:$B$756,B143,$W$2:$W$756,2),""),"") | AB143: =IF(AND(W143=1,ISNUMBER(AA143)),L143/(L143+AA143),"")
... A166: NIFTY | B166: 45743 | C166: 45771 | D166: 23650 | E166: 23812.3 | F166: 23575.1 | G166: 23777.65 | H166: 23810 | I166: 23777.65 | J166: 83340 | K166: 1484613.6 | L166: 12423450 | M166: 2438550 | N166: 23591.95 | O166: =IF(AND(ISNUMBER(G166),ISNUMBER(N166)),G166-N166,"") -> 185.7 | P166: =IF(ISNUMBER(O166),O166/N166,"") -> 0.007871329 | Q166: =C166-B166 -> 28 | R166: =IF(AND(C166=C165,ISNUMBER(G166),ISNUMBER(G165)),(G166/G165-1)*100,"") -> 0.40622513 | S166: =IF(AND(C166=C165,ISNUMBER(L166),ISNUMBER(L165)),(L166/L165-1)*100,"") -> 24.422378 | T166: =IF(AND(C166=C165,ISNUMBER(G166),ISNUMBER(G165)),G166-G165,"") -> 96.2 | U166: =IF(OR(NOT(ISNUMBER(R166)),NOT(ISNUMBER(S166))),"Not classified",IF(AND(R166>0,S166>0),"Long buildup (interpretation)",IF(AND(R166<0,S166>0),"Short buildup (interpretation)",IF(AND(R166>0,S166<0),"Short covering (interpretation)",IF(AND(R166<0,S166<0),"Long unwinding (interpretation)","Neutral"))))) -> Long buildup (interpretation) | V166: =TEXT(B166,"yyyy-mm") -> 2025-03 | W166: =1+COUNTIFS($B$2:$B$756,B166,$C$2:$C$756,"<"&C166) -> 2 | X166: =IF(AND(ISNUMBER(P166),Q166>0),P166*365/Q166,"") -> 0.1026084 | Y166: =IF(AND(C167=C166,ISNUMBER(R167)),R167,"") -> -0.58878821 | Z166: =IF(AND(W166=1,Q166>Basis_Analysis!$B$3,ISNUMBER(Y166)),1,0) -> 0 | AA166: =IF(W166=1,IF(SUMIFS($L$2:$L$756,$B$2:$B$756,B166,$W$2:$W$756,2)>0,SUMIFS($L$2:$L$756,$B$2:$B$756,B166,$W$2:$W$756,2),""),"") | AB166: =IF(AND(W166=1,ISNUMBER(AA166)),L166/(L166+AA166),"")
A167: NIFTY | B167: 45744 | C167: 45771 | D167: 23775.05 | E167: 23801.6 | F167: 23560 | G167: 23637.65 | H167: 23643 | I167: 23637.65 | J167: 97506 | K167: 1731152.9 | L167: 12560100 | M167: 136650 | O167: =IF(AND(ISNUMBER(G167),ISNUMBER(N167)),G167-N167,"") | P167: =IF(ISNUMBER(O167),O167/N167,"") | Q167: =C167-B167 -> 27 | R167: =IF(AND(C167=C166,ISNUMBER(G167),ISNUMBER(G166)),(G167/G166-1)*100,"") -> -0.58878821 | S167: =IF(AND(C167=C166,ISNUMBER(L167),ISNUMBER(L166)),(L167/L166-1)*100,"") -> 1.099936 | T167: =IF(AND(C167=C166,ISNUMBER(G167),ISNUMBER(G166)),G167-G166,"") -> -140 | U167: =IF(OR(NOT(ISNUMBER(R167)),NOT(ISNUMBER(S167))),"Not classified",IF(AND(R167>0,S167>0),"Long buildup (interpretation)",IF(AND(R167<0,S167>0),"Short buildup (interpretation)",IF(AND(R167>0,S167<0),"Short covering (interpretation)",IF(AND(R167<0,S167<0),"Long unwinding (interpretation)","Neutral"))))) -> Short buildup (interpretation) | V167: =TEXT(B167,"yyyy-mm") -> 2025-03 | W167: =1+COUNTIFS($B$2:$B$756,B167,$C$2:$C$756,"<"&C167) -> 1 | X167: =IF(AND(ISNUMBER(P167),Q167>0),P167*365/Q167,"") | Y167: =IF(AND(C168=C167,ISNUMBER(R168)),R168,"") -> -1.337908 | Z167: =IF(AND(W167=1,Q167>Basis_Analysis!$B$3,ISNUMBER(Y167)),1,0) -> 1 | AA167: =IF(W167=1,IF(SUMIFS($L$2:$L$756,$B$2:$B$756,B167,$W$2:$W$756,2)>0,SUMIFS($L$2:$L$756,$B$2:$B$756,B167,$W$2:$W$756,2),""),"") -> 1693200 | AB167: =IF(AND(W167=1,ISNUMBER(AA167)),L167/(L167+AA167),"") -> 0.88120646
A168: NIFTY | B168: 45748 | C168: 45771 | D168: 23530 | E168: 23668 | F168: 23290 | G168: 23321.4 | H168: 23308.55 | I168: 23321.4 | J168: 122621 | K168: 2155245.2 | L168: 12808425 | M168: 248325 | N168: 23165.7 | O168: =IF(AND(ISNUMBER(G168),ISNUMBER(N168)),G168-N168,"") -> 155.7 | P168: =IF(ISNUMBER(O168),O168/N168,"") -> 0.0067211438 | Q168: =C168-B168 -> 23 | R168: =IF(AND(C168=C167,ISNUMBER(G168),ISNUMBER(G167)),(G168/G167-1)*100,"") -> -1.337908 | S168: =IF(AND(C168=C167,ISNUMBER(L168),ISNUMBER(L167)),(L168/L167-1)*100,"") -> 1.9770941 | T168: =IF(AND(C168=C167,ISNUMBER(G168),ISNUMBER(G167)),G168-G167,"") -> -316.25 | U168: =IF(OR(NOT(ISNUMBER(R168)),NOT(ISNUMBER(S168))),"Not classified",IF(AND(R168>0,S168>0),"Long buildup (interpretation)",IF(AND(R168<0,S168>0),"Short buildup (interpretation)",IF(AND(R168>0,S168<0),"Short covering (interpretation)",IF(AND(R168<0,S168<0),"Long unwinding (interpretation)","Neutral"))))) -> Short buildup (interpretation) | V168: =TEXT(B168,"yyyy-mm") -> 2025-04 | W168: =1+COUNTIFS($B$2:$B$756,B168,$C$2:$C$756,"<"&C168) -> 1 | X168: =IF(AND(ISNUMBER(P168),Q168>0),P168*365/Q168,"") -> 0.10666163 | Y168: =IF(AND(C169=C168,ISNUMBER(R169)),R169,"") -> 0.5040435 | Z168: =IF(AND(W168=1,Q168>Basis_Analysis!$B$3,ISNUMBER(Y168)),1,0) -> 1 | AA168: =IF(W168=1,IF(SUMIFS($L$2:$L$756,$B$2:$B$756,B168,$W$2:$W$756,2)>0,SUMIFS($L$2:$L$756,$B$2:$B$756,B168,$W$2:$W$756,2),""),"") -> 1450875 | AB168: =IF(AND(W168=1,ISNUMBER(AA168)),L168/(L168+AA168),"") -> 0.89825062
A169: NIFTY | B169: 45749 | C169: 45771 | D169: 23326.95 | E169: 23459.6 | F169: 23300 | G169: 23438.95 | H169: 23435 | I169: 23438.95 | J169: 64204 | K169: 1126529.2 | L169: 12604950 | M169: -203475 | N169: 23332.35 | O169: =IF(AND(ISNUMBER(G169),ISNUMBER(N169)),G169-N169,"") -> 106.6 | P169: =IF(ISNUMBER(O169),O169/N169,"") -> 0.004568764 | Q169: =C169-B169 -> 22 | R169: =IF(AND(C169=C168,ISNUMBER(G169),ISNUMBER(G168)),(G169/G168-1)*100,"") -> 0.5040435 | S169: =IF(AND(C169=C168,ISNUMBER(L169),ISNUMBER(L168)),(L169/L168-1)*100,"") -> -1.5886028 | T169: =IF(AND(C169=C168,ISNUMBER(G169),ISNUMBER(G168)),G169-G168,"") -> 117.55 | U169: =IF(OR(NOT(ISNUMBER(R169)),NOT(ISNUMBER(S169))),"Not classified",IF(AND(R169>0,S169>0),"Long buildup (interpretation)",IF(AND(R169<0,S169>0),"Short buildup (interpretation)",IF(AND(R169>0,S169<0),"Short covering (interpretation)",IF(AND(R169<0,S169<0),"Long unwinding (interpretation)","Neutral"))))) -> Short covering (interpretation) | V169: =TEXT(B169,"yyyy-mm") -> 2025-04 | W169: =1+COUNTIFS($B$2:$B$756,B169,$C$2:$C$756,"<"&C169) -> 1 | X169: =IF(AND(ISNUMBER(P169),Q169>0),P169*365/Q169,"") -> 0.075799948 | Y169: =IF(AND(C170=C169,ISNUMBER(R170)),R170,"") -> -0.48210351 | Z169: =IF(AND(W169=1,Q169>Basis_Analysis!$B$3,ISNUMBER(Y169)),1,0) -> 1 | AA169: =IF(W169=1,IF(SUMIFS($L$2:$L$756,$B$2:$B$756,B169,$W$2:$W$756,2)>0,SUMIFS($L$2:$L$756,$B$2:$B$756,B169,$W$2:$W$756,2),""),"") -> 1473975 | AB169: =IF(AND(W169=1,ISNUMBER(AA169)),L169/(L169+AA169),"") -> 0.89530628
A170: NIFTY | B170: 45750 | C170: 45771 | D170: 23215 | E170: 23411.1 | F170: 23215 | G170: 23325.95 | H170: 23325.9 | I170: 23325.95 | J170: 68519 | K170: 1199671.4 | L170: 13032300 | M170: 427350 | N170: 23250.1 | O170: =IF(AND(ISNUMBER(G170),ISNUMBER(N170)),G170-N170,"") -> 75.85 | P170: =IF(ISNUMBER(O170),O170/N170,"") -> 0.0032623516 | Q170: =C170-B170 -> 21 | R170: =IF(AND(C170=C169,ISNUMBER(G170),ISNUMBER(G169)),(G170/G169-1)*100,"") -> -0.48210351 | S170: =IF(AND(C170=C169,ISNUMBER(L170),ISNUMBER(L169)),(L170/L169-1)*100,"") -> 3.3903347 | T170: =IF(AND(C170=C169,ISNUMBER(G170),ISNUMBER(G169)),G170-G169,"") -> -113 | U170: =IF(OR(NOT(ISNUMBER(R170)),NOT(ISNUMBER(S170))),"Not classified",IF(AND(R170>0,S170>0),"Long buildup (interpretation)",IF(AND(R170<0,S170>0),"Short buildup (interpretation)",IF(AND(R170>0,S170<0),"Short covering (interpretation)",IF(AND(R170<0,S170<0),"Long unwinding (interpretation)","Neutral"))))) -> Short buildup (interpretation) | V170: =TEXT(B170,"yyyy-mm") -> 2025-04 | W170: =1+COUNTIFS($B$2:$B$756,B170,$C$2:$C$756,"<"&C170) -> 1 | X170: =IF(AND(ISNUMBER(P170),Q170>0),P170*365/Q170,"") -> 0.056702777 | Y170: =IF(AND(C171=C170,ISNUMBER(R171)),R171,"") -> -1.5767847 | Z170: =IF(AND(W170=1,Q170>Basis_Analysis!$B$3,ISNUMBER(Y170)),1,0) -> 1 | AA170: =IF(W170=1,IF(SUMIFS($L$2:$L$756,$B$2:$B$756,B170,$W$2:$W$756,2)>0,SUMIFS($L$2:$L$756,$B$2:$B$756,B170,$W$2:$W$756,2),""),"") -> 1470375 | AB170: =IF(AND(W170=1,ISNUMBER(AA170)),L170/(L170+AA170),"") -> 0.89861353
A171: NIFTY | B171: 45751 | C171: 45771 | D171: 23229.7 | E171: 23250 | F171: 22920.05 | G171: 22958.15 | H171: 22967.5 | I171: 22958.15 | J171: 108118 | K171: 1869311.4 | L171: 13654275 | M171: 621975 | N171: 22904.45 | O171: =IF(AND(ISNUMBER(G171),ISNUMBER(N171)),G171-N171,"") -> 53.7 | P171: =IF(ISNUMBER(O171),O171/N171,"") -> 0.0023445226 | Q171: =C171-B171 -> 20 | R171: =IF(AND(C171=C170,ISNUMBER(G171),ISNUMBER(G170)),(G171/G170-1)*100,"") -> -1.5767847 | S171: =IF(AND(C171=C170,ISNUMBER(L171),ISNUMBER(L170)),(L171/L170-1)*100,"") -> 4.7725651 | T171: =IF(AND(C171=C170,ISNUMBER(G171),ISNUMBER(G170)),G171-G170,"") -> -367.8 | U171: =IF(OR(NOT(ISNUMBER(R171)),NOT(ISNUMBER(S171))),"Not classified",IF(AND(R171>0,S171>0),"Long buildup (interpretation)",IF(AND(R171<0,S171>0),"Short buildup (interpretation)",IF(AND(R171>0,S171<0),"Short covering (interpretation)",IF(AND(R171<0,S171<0),"Long unwinding (interpretation)","Neutral"))))) -> Short buildup (interpretation) | V171: =TEXT(B171,"yyyy-mm") -> 2025-04 | W171: =1+COUNTIFS($B$2:$B$756,B171,$C$2:$C$756,"<"&C171) -> 1 | X171: =IF(AND(ISNUMBER(P171),Q171>0),P171*365/Q171,"") -> 0.042787537 | Y171: =IF(AND(C172=C171,ISNUMBER(R172)),R172,"") -> -3.0244162 | Z171: =IF(AND(W171=1,Q171>Basis_Analysis!$B$3,ISNUMBER(Y171)),1,0) -> 1 | AA171: =IF(W171=1,IF(SUMIFS($L$2:$L$756,$B$2:$B$756,B171,$W$2:$W$756,2)>0,SUMIFS($L$2:$L$756,$B$2:$B$756,B171,$W$2:$W$756,2),""),"") -> 1478550 | AB171: =IF(AND(W171=1,ISNUMBER(AA171)),L171/(L171+AA171),"") -> 0.90229518
A172: NIFTY | B172: 45754 | C172: 45771 | D172: 22201.5 | E172: 22347 | F172: 21860 | G172: 22263.8 | H172: 22320 | I172: 22263.8 | J172: 262265 | K172: 4346378.1 | L172: 13875975 | M172: 221700 | O172: =IF(AND(ISNUMBER(G172),ISNUMBER(N172)),G172-N172,"") | P172: =IF(ISNUMBER(O172),O172/N172,"") | Q172: =C172-B172 -> 17 | R172: =IF(AND(C172=C171,ISNUMBER(G172),ISNUMBER(G171)),(G172/G171-1)*100,"") -> -3.0244162 | S172: =IF(AND(C172=C171,ISNUMBER(L172),ISNUMBER(L171)),(L172/L171-1)*100,"") -> 1.6236673 | T172: =IF(AND(C172=C171,ISNUMBER(G172),ISNUMBER(G171)),G172-G171,"") -> -694.35 | U172: =IF(OR(NOT(ISNUMBER(R172)),NOT(ISNUMBER(S172))),"Not classified",IF(AND(R172>0,S172>0),"Long buildup (interpretation)",IF(AND(R172<0,S172>0),"Short buildup (interpretation)",IF(AND(R172>0,S172<0),"Short covering (interpretation)",IF(AND(R172<0,S172<0),"Long unwinding (interpretation)","Neutral"))))) -> Short buildup (interpretation) | V172: =TEXT(B172,"yyyy-mm") -> 2025-04 | W172: =1+COUNTIFS($B$2:$B$756,B172,$C$2:$C$756,"<"&C172) -> 1 | X172: =IF(AND(ISNUMBER(P172),Q172>0),P172*365/Q172,"") | Y172: =IF(AND(C173=C172,ISNUMBER(R173)),R173,"") -> 1.6463946 | Z172: =IF(AND(W172=1,Q172>Basis_Analysis!$B$3,ISNUMBER(Y172)),1,0) -> 1 | AA172: =IF(W172=1,IF(SUMIFS($L$2:$L$756,$B$2:$B$756,B172,$W$2:$W$756,2)>0,SUMIFS($L$2:$L$756,$B$2:$B$756,B172,$W$2:$W$756,2),""),"") -> 1586775 | AB172: =IF(AND(W172=1,ISNUMBER(AA172)),L172/(L172+AA172),"") -> 0.8973808
A173: NIFTY | B173: 45755 | C173: 45771 | D173: 22511.6 | E173: 22744.9 | F173: 22341 | G173: 22630.35 | H173: 22646.25 | I173: 22630.35 | J173: 156069 | K173: 2642385.5 | L173: 13430775 | M173: -445200 | O173: =IF(AND(ISNUMBER(G173),ISNUMBER(N173)),G173-N173,"") | P173: =IF(ISNUMBER(O173),O173/N173,"") | Q173: =C173-B173 -> 16 | R173: =IF(AND(C173=C172,ISNUMBER(G173),ISNUMBER(G172)),(G173/G172-1)*100,"") -> 1.6463946 | S173: =IF(AND(C173=C172,ISNUMBER(L173),ISNUMBER(L172)),(L173/L172-1)*100,"") -> -3.2084232 | T173: =IF(AND(C173=C172,ISNUMBER(G173),ISNUMBER(G172)),G173-G172,"") -> 366.55 | U173: =IF(OR(NOT(ISNUMBER(R173)),NOT(ISNUMBER(S173))),"Not classified",IF(AND(R173>0,S173>0),"Long buildup (interpretation)",IF(AND(R173<0,S173>0),"Short buildup (interpretation)",IF(AND(R173>0,S173<0),"Short covering (interpretation)",IF(AND(R173<0,S173<0),"Long unwinding (interpretation)","Neutral"))))) -> Short covering (interpretation) | V173: =TEXT(B173,"yyyy-mm") -> 2025-04 | W173: =1+COUNTIFS($B$2:$B$756,B173,$C$2:$C$756,"<"&C173) -> 1 | X173: =IF(AND(ISNUMBER(P173),Q173>0),P173*365/Q173,"") | Y173: =IF(AND(C174=C173,ISNUMBER(R174)),R174,"") -> -0.66591988 | Z173: =IF(AND(W173=1,Q173>Basis_Analysis!$B$3,ISNUMBER(Y173)),1,0) -> 1 | AA173: =IF(W173=1,IF(SUMIFS($L$2:$L$756,$B$2:$B$756,B173,$W$2:$W$756,2)>0,SUMIFS($L$2:$L$756,$B$2:$B$756,B173,$W$2:$W$756,2),""),"") -> 1633125 | AB173: =IF(AND(W173=1,ISNUMBER(AA173)),L173/(L173+AA173),"") -> 0.89158684
A174: NIFTY | B174: 45756 | C174: 45771 | D174: 22544 | E174: 22544 | F174: 22405.05 | G174: 22479.65 | H174: 22504 | I174: 22479.65 | J174: 90619 | K174: 1527520.7 | L174: 13164825 | M174: -265950 | N174: 22399.15 | O174: =IF(AND(ISNUMBER(G174),ISNUMBER(N174)),G174-N174,"") -> 80.5 | P174: =IF(ISNUMBER(O174),O174/N174,"") -> 0.0035938864 | Q174: =C174-B174 -> 15 | R174: =IF(AND(C174=C173,ISNUMBER(G174),ISNUMBER(G173)),(G174/G173-1)*100,"") -> -0.66591988 | S174: =IF(AND(C174=C173,ISNUMBER(L174),ISNUMBER(L173)),(L174/L173-1)*100,"") -> -1.9801538 | T174: =IF(AND(C174=C173,ISNUMBER(G174),ISNUMBER(G173)),G174-G173,"") -> -150.7 | U174: =IF(OR(NOT(ISNUMBER(R174)),NOT(ISNUMBER(S174))),"Not classified",IF(AND(R174>0,S174>0),"Long buildup (interpretation)",IF(AND(R174<0,S174>0),"Short buildup (interpretation)",IF(AND(R174>0,S174<0),"Short covering (interpretation)",IF(AND(R174<0,S174<0),"Long unwinding (interpretation)","Neutral"))))) -> Long unwinding (interpretation) | V174: =TEXT(B174,"yyyy-mm") -> 2025-04 | W174: =1+COUNTIFS($B$2:$B$756,B174,$C$2:$C$756,"<"&C174) -> 1 | X174: =IF(AND(ISNUMBER(P174),Q174>0),P174*365/Q174,"") -> 0.087451235 | Y174: =IF(AND(C175=C174,ISNUMBER(R175)),R175,"") -> 1.9484289 | Z174: =IF(AND(W174=1,Q174>Basis_Analysis!$B$3,ISNUMBER(Y174)),1,0) -> 1 | AA174: =IF(W174=1,IF(SUMIFS($L$2:$L$756,$B$2:$B$756,B174,$W$2:$W$756,2)>0,SUMIFS($L$2:$L$756,$B$2:$B$756,B174,$W$2:$W$756,2),""),"") -> 1730775 | AB174: =IF(AND(W174=1,ISNUMBER(AA174)),L174/(L174+AA174),"") -> 0.88380629
A175: NIFTY | B175: 45758 | C175: 45771 | D175: 22746 | E175: 23017 | F175: 22746 | G175: 22917.65 | H175: 22948 | I175: 22917.65 | J175: 120725 | K175: 2073778.1 | L175: 12919500 | M175: -245325 | N175: 22828.55 | O175: =IF(AND(ISNUMBER(G175),ISNUMBER(N175)),G175-N175,"") -> 89.1 | P175: =IF(ISNUMBER(O175),O175/N175,"") -> 0.0039030074 | Q175: =C175-B175 -> 13 | R175: =IF(AND(C175=C174,ISNUMBER(G175),ISNUMBER(G174)),(G175/G174-1)*100,"") -> 1.9484289 | S175: =IF(AND(C175=C174,ISNUMBER(L175),ISNUMBER(L174)),(L175/L174-1)*100,"") -> -1.8634885 | T175: =IF(AND(C175=C174,ISNUMBER(G175),ISNUMBER(G174)),G175-G174,"") -> 438 | U175: =IF(OR(NOT(ISNUMBER(R175)),NOT(ISNUMBER(S175))),"Not classified",IF(AND(R175>0,S175>0),"Long buildup (interpretation)",IF(AND(R175<0,S175>0),"Short buildup (interpretation)",IF(AND(R175>0,S175<0),"Short covering (interpretation)",IF(AND(R175<0,S175<0),"Long unwinding (interpretation)","Neutral"))))) -> Short covering (interpretation) | V175: =TEXT(B175,"yyyy-mm") -> 2025-04 | W175: =1+COUNTIFS($B$2:$B$756,B175,$C$2:$C$756,"<"&C175) -> 1 | X175: =IF(AND(ISNUMBER(P175),Q175>0),P175*365/Q175,"") -> 0.10958444 | Y175: =IF(AND(C176=C175,ISNUMBER(R176)),R176,"") -> 1.8468298 | Z175: =IF(AND(W175=1,Q175>Basis_Analysis!$B$3,ISNUMBER(Y175)),1,0) -> 1 | AA175: =IF(W175=1,IF(SUMIFS($L$2:$L$756,$B$2:$B$756,B175,$W$2:$W$756,2)>0,SUMIFS($L$2:$L$756,$B$2:$B$756,B175,$W$2:$W$756,2),""),"") -> 1808700 | AB175: =IF(AND(W175=1,ISNUMBER(AA175)),L175/(L175+AA175),"") -> 0.87719477
A176: NIFTY | B176: 45762 | C176: 45771 | D176: 23295 | E176: 23399.9 | F176: 23252 | G176: 23340.9 | H176: 23364.4 | I176: 23340.9 | J176: 89235 | K176: 1562849.2 | L176: 12380700 | M176: -538800 | N176: 23328.55 | O176: =IF(AND(ISNUMBER(G176),ISNUMBER(N176)),G176-N176,"") -> 12.35 | P176: =IF(ISNUMBER(O176),O176/N176,"") -> 0.00052939424 | Q176: =C176-B176 -> 9 | R176: =IF(AND(C176=C175,ISNUMBER(G176),ISNUMBER(G175)),(G176/G175-1)*100,"") -> 1.8468298 | S176: =IF(AND(C176=C175,ISNUMBER(L176),ISNUMBER(L175)),(L176/L175-1)*100,"") -> -4.17044 | T176: =IF(AND(C176=C175,ISNUMBER(G176),ISNUMBER(G175)),G176-G175,"") -> 423.25 | U176: =IF(OR(NOT(ISNUMBER(R176)),NOT(ISNUMBER(S176))),"Not classified",IF(AND(R176>0,S176>0),"Long buildup (interpretation)",IF(AND(R176<0,S176>0),"Short buildup (interpretation)",IF(AND(R176>0,S176<0),"Short covering (interpretation)",IF(AND(R176<0,S176<0),"Long unwinding (interpretation)","Neutral"))))) -> Short covering (interpretation) | V176: =TEXT(B176,"yyyy-mm") -> 2025-04 | W176: =1+COUNTIFS($B$2:$B$756,B176,$C$2:$C$756,"<"&C176) -> 1 | X176: =IF(AND(ISNUMBER(P176),Q176>0),P176*365/Q176,"") -> 0.021469878 | Y176: =IF(AND(C177=C176,ISNUMBER(R177)),R177,"") -> 0.39672849 | Z176: =IF(AND(W176=1,Q176>Basis_Analysis!$B$3,ISNUMBER(Y176)),1,0) -> 1 | AA176: =IF(W176=1,IF(SUMIFS($L$2:$L$756,$B$2:$B$756,B176,$W$2:$W$756,2)>0,SUMIFS($L$2:$L$756,$B$2:$B$756,B176,$W$2:$W$756,2),""),"") -> 1913475 | AB176: =IF(AND(W176=1,ISNUMBER(AA176)),L176/(L176+AA176),"") -> 0.86613603
A177: NIFTY | B177: 45763 | C177: 45771 | D177: 23338 | E177: 23450 | F177: 23277.2 | G177: 23433.5 | H177: 23440.6 | I177: 23433.5 | J177: 71349 | K177: 1250406.4 | L177: 12106575 | M177: -274125 | N177: 23437.2 | O177: =IF(AND(ISNUMBER(G177),ISNUMBER(N177)),G177-N177,"") -> -3.7 | P177: =IF(ISNUMBER(O177),O177/N177,"") -> -0.00015786869 | Q177: =C177-B177 -> 8 | R177: =IF(AND(C177=C176,ISNUMBER(G177),ISNUMBER(G176)),(G177/G176-1)*100,"") -> 0.39672849 | S177: =IF(AND(C177=C176,ISNUMBER(L177),ISNUMBER(L176)),(L177/L176-1)*100,"") -> -2.2141317 | T177: =IF(AND(C177=C176,ISNUMBER(G177),ISNUMBER(G176)),G177-G176,"") -> 92.6 | U177: =IF(OR(NOT(ISNUMBER(R177)),NOT(ISNUMBER(S177))),"Not classified",IF(AND(R177>0,S177>0),"Long buildup (interpretation)",IF(AND(R177<0,S177>0),"Short buildup (interpretation)",IF(AND(R177>0,S177<0),"Short covering (interpretation)",IF(AND(R177<0,S177<0),"Long unwinding (interpretation)","Neutral"))))) -> Short covering (interpretation) | V177: =TEXT(B177,"yyyy-mm") -> 2025-04 | W177: =1+COUNTIFS($B$2:$B$756,B177,$C$2:$C$756,"<"&C177) -> 1 | X177: =IF(AND(ISNUMBER(P177),Q177>0),P177*365/Q177,"") -> -0.0072027589 | Y177: =IF(AND(C178=C177,ISNUMBER(R178)),R178,"") -> 1.7829176 | Z177: =IF(AND(W177=1,Q177>Basis_Analysis!$B$3,ISNUMBER(Y177)),1,0) -> 1 | AA177: =IF(W177=1,IF(SUMIFS($L$2:$L$756,$B$2:$B$756,B177,$W$2:$W$756,2)>0,SUMIFS($L$2:$L$756,$B$2:$B$756,B177,$W$2:$W$756,2),""),"") -> 2097225 | AB177: =IF(AND(W177=1,ISNUMBER(AA177)),L177/(L177+AA177),"") -> 0.85234761
A178: NIFTY | B178: 45764 | C178: 45771 | D178: 23399.9 | E178: 23872.7 | F178: 23330 | G178: 23851.3 | H178: 23848.9 | I178: 23851.3 | J178: 135421 | K178: 2400335.7 | L178: 11622975 | M178: -483600 | N178: 23851.65 | O178: =IF(AND(ISNUMBER(G178),ISNUMBER(N178)),G178-N178,"") -> -0.35 | P178: =IF(ISNUMBER(O178),O178/N178,"") -> -1.4674037e-05 | Q178: =C178-B178 -> 7 | R178: =IF(AND(C178=C177,ISNUMBER(G178),ISNUMBER(G177)),(G178/G177-1)*100,"") -> 1.7829176 | S178: =IF(AND(C178=C177,ISNUMBER(L178),ISNUMBER(L177)),(L178/L177-1)*100,"") -> -3.9945236 | T178: =IF(AND(C178=C177,ISNUMBER(G178),ISNUMBER(G177)),G178-G177,"") -> 417.8 | U178: =IF(OR(NOT(ISNUMBER(R178)),NOT(ISNUMBER(S178))),"Not classified",IF(AND(R178>0,S178>0),"Long buildup (interpretation)",IF(AND(R178<0,S178>0),"Short buildup (interpretation)",IF(AND(R178>0,S178<0),"Short covering (interpretation)",IF(AND(R178<0,S178<0),"Long unwinding (interpretation)","Neutral"))))) -> Short covering (interpretation) | V178: =TEXT(B178,"yyyy-mm") -> 2025-04 | W178: =1+COUNTIFS($B$2:$B$756,B178,$C$2:$C$756,"<"&C178) -> 1 | X178: =IF(AND(ISNUMBER(P178),Q178>0),P178*365/Q178,"") -> -0.00076514623 | Y178: =IF(AND(C179=C178,ISNUMBER(R179)),R179,"") -> 1.1915493 | Z178: =IF(AND(W178=1,Q178>Basis_Analysis!$B$3,ISNUMBER(Y178)),1,0) -> 1 | AA178: =IF(W178=1,IF(SUMIFS($L$2:$L$756,$B$2:$B$756,B178,$W$2:$W$756,2)>0,SUMIFS($L$2:$L$756,$B$2:$B$756,B178,$W$2:$W$756,2),""),"") -> 2715600 | AB178: =IF(AND(W178=1,ISNUMBER(AA178)),L178/(L178+AA178),"") -> 0.81060879
A179: NIFTY | B179: 45768 | C179: 45771 | D179: 23875.9 | E179: 24194.5 | F179: 23875.6 | G179: 24135.5 | H179: 24131.3 | I179: 24135.5 | J179: 77342 | K179: 1396642.6 | L179: 11051175 | M179: -571800 | N179: 24125.55 | O179: =IF(AND(ISNUMBER(G179),ISNUMBER(N179)),G179-N179,"") -> 9.95 | P179: =IF(ISNUMBER(O179),O179/N179,"") -> 0.00041242583 | Q179: =C179-B179 -> 3 | R179: =IF(AND(C179=C178,ISNUMBER(G179),ISNUMBER(G178)),(G179/G178-1)*100,"") -> 1.1915493 | S179: =IF(AND(C179=C178,ISNUMBER(L179),ISNUMBER(L178)),(L179/L178-1)*100,"") -> -4.9195666 | T179: =IF(AND(C179=C178,ISNUMBER(G179),ISNUMBER(G178)),G179-G178,"") -> 284.2 | U179: =IF(OR(NOT(ISNUMBER(R179)),NOT(ISNUMBER(S179))),"Not classified",IF(AND(R179>0,S179>0),"Long buildup (interpretation)",IF(AND(R179<0,S179>0),"Short buildup (interpretation)",IF(AND(R179>0,S179<0),"Short covering (interpretation)",IF(AND(R179<0,S179<0),"Long unwinding (interpretation)","Neutral"))))) -> Short covering (interpretation) | V179: =TEXT(B179,"yyyy-mm") -> 2025-04 | W179: =1+COUNTIFS($B$2:$B$756,B179,$C$2:$C$756,"<"&C179) -> 1 | X179: =IF(AND(ISNUMBER(P179),Q179>0),P179*365/Q179,"") -> 0.050178476 | Y179: =IF(AND(C180=C179,ISNUMBER(R180)),R180,"") -> 0.13879969 | Z179: =IF(AND(W179=1,Q179>Basis_Analysis!$B$3,ISNUMBER(Y179)),1,0) -> 0 | AA179: =IF(W179=1,IF(SUMIFS($L$2:$L$756,$B$2:$B$756,B179,$W$2:$W$756,2)>0,SUMIFS($L$2:$L$756,$B$2:$B$756,B179,$W$2:$W$756,2),""),"") -> 3508125 | AB179: =IF(AND(W179=1,ISNUMBER(AA179)),L179/(L179+AA179),"") -> 0.75904576
A180: NIFTY | B180: 45769 | C180: 45771 | D180: 24150 | E180: 24239.8 | F180: 24077 | G180: 24169 | H180: 24164.1 | I180: 24169 | J180: 87218 | K180: 1581403.5 | L180: 8816400 | M180: -2234775 | N180: 24167.25 | O180: =IF(AND(ISNUMBER(G180),ISNUMBER(N180)),G180-N180,"") -> 1.75 | P180: =IF(ISNUMBER(O180),O180/N180,"") -> 7.2412045e-05 | Q180: =C180-B180 -> 2 | R180: =IF(AND(C180=C179,ISNUMBER(G180),ISNUMBER(G179)),(G180/G179-1)*100,"") -> 0.13879969 | S180: =IF(AND(C180=C179,ISNUMBER(L180),ISNUMBER(L179)),(L180/L179-1)*100,"") -> -20.222058 | T180: =IF(AND(C180=C179,ISNUMBER(G180),ISNUMBER(G179)),G180-G179,"") -> 33.5 | U180: =IF(OR(NOT(ISNUMBER(R180)),NOT(ISNUMBER(S180))),"Not classified",IF(AND(R180>0,S180>0),"Long buildup (interpretation)",IF(AND(R180<0,S180>0),"Short buildup (interpretation)",IF(AND(R180>0,S180<0),"Short covering (interpretation)",IF(AND(R180<0,S180<0),"Long unwinding (interpretation)","Neutral"))))) -> Short covering (interpretation) | V180: =TEXT(B180,"yyyy-mm") -> 2025-04 | W180: =1+COUNTIFS($B$2:$B$756,B180,$C$2:$C$756,"<"&C180) -> 1 | X180: =IF(AND(ISNUMBER(P180),Q180>0),P180*365/Q180,"") -> 0.013215198 | Y180: =IF(AND(C181=C180,ISNUMBER(R181)),R181,"") -> 0.59456328 | Z180: =IF(AND(W180=1,Q180>Basis_Analysis!$B$3,ISNUMBER(Y180)),1,0) -> 0 | AA180: =IF(W180=1,IF(SUMIFS($L$2:$L$756,$B$2:$B$756,B180,$W$2:$W$756,2)>0,SUMIFS($L$2:$L$756,$B$2:$B$756,B180,$W$2:$W$756,2),""),"") -> 6043200 | AB180: =IF(AND(W180=1,ISNUMBER(AA180)),L180/(L180+AA180),"") -> 0.59331341
A181: NIFTY | B181: 45770 | C181: 45771 | D181: 24310 | E181: 24351.8 | F181: 24121.1 | G181: 24312.7 | H181: 24306.9 | I181: 24312.7 | J181: 99138 | K181: 1804034.7 | L181: 5549550 | M181: -3266850 | N181: 24328.95 | O181: =IF(AND(ISNUMBER(G181),ISNUMBER(N181)),G181-N181,"") -> -16.25 | P181: =IF(ISNUMBER(O181),O181/N181,"") -> -0.00066792854 | Q181: =C181-B181 -> 1 | R181: =IF(AND(C181=C180,ISNUMBER(G181),ISNUMBER(G180)),(G181/G180-1)*100,"") -> 0.59456328 | S181: =IF(AND(C181=C180,ISNUMBER(L181),ISNUMBER(L180)),(L181/L180-1)*100,"") -> -37.05424 | T181: =IF(AND(C181=C180,ISNUMBER(G181),ISNUMBER(G180)),G181-G180,"") -> 143.7 | U181: =IF(OR(NOT(ISNUMBER(R181)),NOT(ISNUMBER(S181))),"Not classified",IF(AND(R181>0,S181>0),"Long buildup (interpretation)",IF(AND(R181<0,S181>0),"Short buildup (interpretation)",IF(AND(R181>0,S181<0),"Short covering (interpretation)",IF(AND(R181<0,S181<0),"Long unwinding (interpretation)","Neutral"))))) -> Short covering (interpretation) | V181: =TEXT(B181,"yyyy-mm") -> 2025-04 | W181: =1+COUNTIFS($B$2:$B$756,B181,$C$2:$C$756,"<"&C181) -> 1 | X181: =IF(AND(ISNUMBER(P181),Q181>0),P181*365/Q181,"") -> -0.24379392 | Y181: =IF(AND(C182=C181,ISNUMBER(R182)),R182,"") -> -0.27557614 | Z181: =IF(AND(W181=1,Q181>Basis_Analysis!$B$3,ISNUMBER(Y181)),1,0) -> 0 | AA181: =IF(W181=1,IF(SUMIFS($L$2:$L$756,$B$2:$B$756,B181,$W$2:$W$756,2)>0,SUMIFS($L$2:$L$756,$B$2:$B$756,B181,$W$2:$W$756,2),""),"") -> 9082350 | AB181: =IF(AND(W181=1,ISNUMBER(AA181)),L181/(L181+AA181),"") -> 0.37927747
A182: NIFTY | B182: 45771 | C182: 45771 | D182: 24288 | E182: 24360 | F182: 24225 | G182: 24245.7 | H182: 24249 | I182: 24246.7 | J182: 55201 | K182: 1004562.5 | L182: 3392175 | M182: -2157375 | N182: 24246.7 | O182: =IF(AND(ISNUMBER(G182),ISNUMBER(N182)),G182-N182,"") -> -1 | P182: =IF(ISNUMBER(O182),O182/N182,"") -> -4.1242726e-05 | Q182: =C182-B182 -> 0 | R182: =IF(AND(C182=C181,ISNUMBER(G182),ISNUMBER(G181)),(G182/G181-1)*100,"") -> -0.27557614 | S182: =IF(AND(C182=C181,ISNUMBER(L182),ISNUMBER(L181)),(L182/L181-1)*100,"") -> -38.874774 | T182: =IF(AND(C182=C181,ISNUMBER(G182),ISNUMBER(G181)),G182-G181,"") -> -67 | U182: =IF(OR(NOT(ISNUMBER(R182)),NOT(ISNUMBER(S182))),"Not classified",IF(AND(R182>0,S182>0),"Long buildup (interpretation)",IF(AND(R182<0,S182>0),"Short buildup (interpretation)",IF(AND(R182>0,S182<0),"Short covering (interpretation)",IF(AND(R182<0,S182<0),"Long unwinding (interpretation)","Neutral"))))) -> Long unwinding (interpretation) | V182: =TEXT(B182,"yyyy-mm") -> 2025-04 | W182: =1+COUNTIFS($B$2:$B$756,B182,$C$2:$C$756,"<"&C182) -> 1 | X182: =IF(AND(ISNUMBER(P182),Q182>0),P182*365/Q182,"") | Y182: =IF(AND(C183=C182,ISNUMBER(R183)),R183,"") | Z182: =IF(AND(W182=1,Q182>Basis_Analysis!$B$3,ISNUMBER(Y182)),1,0) -> 0 | AA182: =IF(W182=1,IF(SUMIFS($L$2:$L$756,$B$2:$B$756,B182,$W$2:$W$756,2)>0,SUMIFS($L$2:$L$756,$B$2:$B$756,B182,$W$2:$W$756,2),""),"") -> 11503875 | AB182: =IF(AND(W182=1,ISNUMBER(AA182)),L182/(L182+AA182),"") -> 0.22772312
A183: NIFTY | B183: 45715 | C183: 45806 | O183: =IF(AND(ISNUMBER(G183),ISNUMBER(N183)),G183-N183,"") | P183: =IF(ISNUMBER(O183),O183/N183,"") | Q183: =C183-B183 -> 91 | R183: =IF(AND(C183=C182,ISNUMBER(G183),ISNUMBER(G182)),(G183/G182-1)*100,"") | S183: =IF(AND(C183=C182,ISNUMBER(L183),ISNUMBER(L182)),(L183/L182-1)*100,"") | T183: =IF(AND(C183=C182,ISNUMBER(G183),ISNUMBER(G182)),G183-G182,"") | U183: =IF(OR(NOT(ISNUMBER(R183)),NOT(ISNUMBER(S183))),"Not classified",IF(AND(R183>0,S183>0),"Long buildup (interpretation)",IF(AND(R183<0,S183>0),"Short buildup (interpretation)",IF(AND(R183>0,S183<0),"Short covering (interpretation)",IF(AND(R183<0,S183<0),"Long unwinding (interpretation)","Neutral"))))) -> Not classified | V183: =TEXT(B183,"yyyy-mm") -> 2025-02 | W183: =1+COUNTIFS($B$2:$B$756,B183,$C$2:$C$756,"<"&C183) -> 4 | X183: =IF(AND(ISNUMBER(P183),Q183>0),P183*365/Q183,"") | Y183: =IF(AND(C184=C183,ISNUMBER(R184)),R184,"") | Z183: =IF(AND(W183=1,Q183>Basis_Analysis!$B$3,ISNUMBER(Y183)),1,0) -> 0 | AA183: =IF(W183=1,IF(SUMIFS($L$2:$L$756,$B$2:$B$756,B183,$W$2:$W$756,2)>0,SUMIFS($L$2:$L$756,$B$2:$B$756,B183,$W$2:$W$756,2),""),"") | AB183: =IF(AND(W183=1,ISNUMBER(AA183)),L183/(L183+AA183),"")
A184: NIFTY | B184: 45716 | C184: 45806 | D184: 22875 | E184: 22875 | F184: 22515.45 | G184: 22556.15 | H184: 22559.7 | I184: 22556.15 | J184: 2724 | K184: 46242.08 | L184: 94950 | M184: 94950 | N184: 22124.7 | O184: =IF(AND(ISNUMBER(G184),ISNUMBER(N184)),G184-N184,"") -> 431.45 | P184: =IF(ISNUMBER(O184),O184/N184,"") -> 0.019500829 | Q184: =C184-B184 -> 90 | R184: =IF(AND(C184=C183,ISNUMBER(G184),ISNUMBER(G183)),(G184/G183-1)*100,"") | S184: =IF(AND(C184=C183,ISNUMBER(L184),ISNUMBER(L183)),(L184/L183-1)*100,"") | T184: =IF(AND(C184=C183,ISNUMBER(G184),ISNUMBER(G183)),G184-G183,"") | U184: =IF(OR(NOT(ISNUMBER(R184)),NOT(ISNUMBER(S184))),"Not classified",IF(AND(R184>0,S184>0),"Long buildup (interpretation)",IF(AND(R184<0,S184>0),"Short buildup (interpretation)",IF(AND(R184>0,S184<0),"Short covering (interpretation)",IF(AND(R184<0,S184<0),"Long unwinding (interpretation)","Neutral"))))) -> Not classified | V184: =TEXT(B184,"yyyy-mm") -> 2025-02 | W184: =1+COUNTIFS($B$2:$B$756,B184,$C$2:$C$756,"<"&C184) -> 3 | X184: =IF(AND(ISNUMBER(P184),Q184>0),P184*365/Q184,"") -> 0.079086697 | Y184: =IF(AND(C185=C184,ISNUMBER(R185)),R185,"") -> -0.095539354 | Z184: =IF(AND(W184=1,Q184>Basis_Analysis!$B$3,ISNUMBER(Y184)),1,0) -> 0 | AA184: =IF(W184=1,IF(SUMIFS($L$2:$L$756,$B$2:$B$756,B184,$W$2:$W$756,2)>0,SUMIFS($L$2:$L$756,$B$2:$B$756,B184,$W$2:$W$756,2),""),"") | AB184: =IF(AND(W184=1,ISNUMBER(AA184)),L184/(L184+AA184),"")
A185: NIFTY | B185: 45719 | C185: 45806 | D185: 22593.65 | E185: 22648.95 | F185: 22420 | G185: 22534.6 | H185: 22546.3 | I185: 22534.6 | J185: 3172 | K185: 53508.62 | L185: 240900 | M185: 145950 | N185: 22119.3 | O185: =IF(AND(ISNUMBER(G185),ISNUMBER(N185)),G185-N185,"") -> 415.3 | P185: =IF(ISNUMBER(O185),O185/N185,"") -> 0.018775459 | Q185: =C185-B185 -> 87 | R185: =IF(AND(C185=C184,ISNUMBER(G185),ISNUMBER(G184)),(G185/G184-1)*100,"") -> -0.095539354 | S185: =IF(AND(C185=C184,ISNUMBER(L185),ISNUMBER(L184)),(L185/L184-1)*100,"") -> 153.71248 | T185: =IF(AND(C185=C184,ISNUMBER(G185),ISNUMBER(G184)),G185-G184,"") -> -21.55 | U185: =IF(OR(NOT(ISNUMBER(R185)),NOT(ISNUMBER(S185))),"Not classified",IF(AND(R185>0,S185>0),"Long buildup (interpretation)",IF(AND(R185<0,S185>0),"Short buildup (interpretation)",IF(AND(R185>0,S185<0),"Short covering (interpretation)",IF(AND(R185<0,S185<0),"Long unwinding (interpretation)","Neutral"))))) -> Short buildup (interpretation) | V185: =TEXT(B185,"yyyy-mm") -> 2025-03 | W185: =1+COUNTIFS($B$2:$B$756,B185,$C$2:$C$756,"<"&C185) -> 3 | X185: =IF(AND(ISNUMBER(P185),Q185>0),P185*365/Q185,"") -> 0.078770602 | Y185: =IF(AND(C186=C185,ISNUMBER(R186)),R186,"") -> -0.37497892 | Z185: =IF(AND(W185=1,Q185>Basis_Analysis!$B$3,ISNUMBER(Y185)),1,0) -> 0 | AA185: =IF(W185=1,IF(SUMIFS($L$2:$L$756,$B$2:$B$756,B185,$W$2:$W$756,2)>0,SUMIFS($L$2:$L$756,$B$2:$B$756,B185,$W$2:$W$756,2),""),"") | AB185: =IF(AND(W185=1,ISNUMBER(AA185)),L185/(L185+AA185),"")
A186: NIFTY | B186: 45720 | C186: 45806 | D186: 22440 | E186: 22500 | F186: 22376.6 | G186: 22450.1 | H186: 22449 | I186: 22450.1 | J186: 2465 | K186: 41499.38 | L186: 330150 | M186: 89250 | N186: 22082.65 | O186: =IF(AND(ISNUMBER(G186),ISNUMBER(N186)),G186-N186,"") -> 367.45 | P186: =IF(ISNUMBER(O186),O186/N186,"") -> 0.01663976 | Q186: =C186-B186 -> 86 | R186: =IF(AND(C186=C185,ISNUMBER(G186),ISNUMBER(G185)),(G186/G185-1)*100,"") -> -0.37497892 | S186: =IF(AND(C186=C185,ISNUMBER(L186),ISNUMBER(L185)),(L186/L185-1)*100,"") -> 37.048568 | T186: =IF(AND(C186=C185,ISNUMBER(G186),ISNUMBER(G185)),G186-G185,"") -> -84.5 | U186: =IF(OR(NOT(ISNUMBER(R186)),NOT(ISNUMBER(S186))),"Not classified",IF(AND(R186>0,S186>0),"Long buildup (interpretation)",IF(AND(R186<0,S186>0),"Short buildup (interpretation)",IF(AND(R186>0,S186<0),"Short covering (interpretation)",IF(AND(R186<0,S186<0),"Long unwinding (interpretation)","Neutral"))))) -> Short buildup (interpretation) | V186: =TEXT(B186,"yyyy-mm") -> 2025-03 | W186: =1+COUNTIFS($B$2:$B$756,B186,$C$2:$C$756,"<"&C186) -> 3 | X186: =IF(AND(ISNUMBER(P186),Q186>0),P186*365/Q186,"") -> 0.070622238 | Y186: =IF(AND(C187=C186,ISNUMBER(R187)),R187,"") -> 1.1374114 | Z186: =IF(AND(W186=1,Q186>Basis_Analysis!$B$3,ISNUMBER(Y186)),1,0) -> 0 | AA186: =IF(W186=1,IF(SUMIFS($L$2:$L$756,$B$2:$B$756,B186,$W$2:$W$756,2)>0,SUMIFS($L$2:$L$756,$B$2:$B$756,B186,$W$2:$W$756,2),""),"") | AB186: =IF(AND(W186=1,ISNUMBER(AA186)),L186/(L186+AA186),"")
A187: NIFTY | B187: 45721 | C187: 45806 | D187: 22403.05 | E187: 22761.1 | F187: 22403.05 | G187: 22705.45 | H187: 22717.65 | I187: 22705.45 | J187: 7243 | K187: 123195.81 | L187: 568050 | M187: 237900 | N187: 22337.3 | O187: =IF(AND(ISNUMBER(G187),ISNUMBER(N187)),G187-N187,"") -> 368.15 | P187: =IF(ISNUMBER(O187),O187/N187,"") -> 0.016481401 | Q187: =C187-B187 -> 85 | R187: =IF(AND(C187=C186,ISNUMBER(G187),ISNUMBER(G186)),(G187/G186-1)*100,"") -> 1.1374114 | S187: =IF(AND(C187=C186,ISNUMBER(L187),ISNUMBER(L186)),(L187/L186-1)*100,"") -> 72.058155 | T187: =IF(AND(C187=C186,ISNUMBER(G187),ISNUMBER(G186)),G187-G186,"") -> 255.35 | U187: =IF(OR(NOT(ISNUMBER(R187)),NOT(ISNUMBER(S187))),"Not classified",IF(AND(R187>0,S187>0),"Long buildup (interpretation)",IF(AND(R187<0,S187>0),"Short buildup (interpretation)",IF(AND(R187>0,S187<0),"Short covering (interpretation)",IF(AND(R187<0,S187<0),"Long unwinding (interpretation)","Neutral"))))) -> Long buildup (interpretation) | V187: =TEXT(B187,"yyyy-mm") -> 2025-03 | W187: =1+COUNTIFS($B$2:$B$756,B187,$C$2:$C$756,"<"&C187) -> 3 | X187: =IF(AND(ISNUMBER(P187),Q187>0),P187*365/Q187,"") -> 0.070773075 | Y187: =IF(AND(C188=C187,ISNUMBER(R188)),R188,"") -> 0.74101152 | Z187: =IF(AND(W187=1,Q187>Basis_Analysis!$B$3,ISNUMBER(Y187)),1,0) -> 0 | AA187: =IF(W187=1,IF(SUMIFS($L$2:$L$756,$B$2:$B$756,B187,$W$2:$W$756,2)>0,SUMIFS($L$2:$L$756,$B$2:$B$756,B187,$W$2:$W$756,2),""),"") | AB187: =IF(AND(W187=1,ISNUMBER(AA187)),L187/(L187+AA187),"")
